Workbook

Sheet 2026年19周纯洗箱情况
A1: 经营单位 | B1: 网点 | C1: 纯洗箱量 | D1: 纯洗箱费 | E1: 合计修洗量 | F1: 合计修洗费 | G1: 修洗箱单箱 | H1: 修箱单箱 | I1: 单箱差额
A2: 南岗分公司 | B2: 南岗堆场 | C2: 1 | D2: 63.02 | E2: 100 | F2: 23763.26 | G2: 237.63 | H2: 239.4 | I2: 1.76
A3: 南岗分公司 | B3: 东江仓码头 | C3: 1 | D3: 63.02 | E3: 90 | F3: 9616.25 | G3: 106.85 | H3: 107.34 | I3: 0.49
A4: 深圳运营中心 | B4: 深圳大铲湾 | C4: 0 | D4: 0 | E4: 102 | F4: 34681.21 | G4: 340.01 | H4: 340.01 | I4: 0
A5: 华慧良修 | B5: 深圳蛇口堆场 | C5: 4 | D5: 118.24 | E5: 321 | F5: 86997.92 | G5: 271.02 | H5: 274.07 | I5: 3.05
A6: 深圳运营中心 | B6: 汕头广澳 | C6: 0 | D6: 0 | E6: 0 | F6: 0 | G6: #DIV/0! | H6: #DIV/0! | I6: #DIV/0!
A7: 深圳运营中心 | B7: 汕头堆场 | C7: 0 | D7: 0 | E7: 242 | F7: 59793.31 | G7: 247.08 | H7: 247.08 | I7: 0
A8: 深圳运营中心 | B8: 汕头国集 | C8: 0 | D8: 0 | E8: 0 | F8: 0 | G8: #DIV/0! | H8: #DIV/0! | I8: #DIV/0!
A9: 广州运营中心 | B9: 黄埔旧港 | C9: 653 | D9: 34360.5 | E9: 1128 | F9: 122134.95 | G9: 108.28 | H9: 184.79 | I9: 76.51
A10: 广州运营中心 | B10: 淡水河码头 | C10: 0 | D10: 0 | E10: 0 | F10: 0 | G10: #DIV/0! | H10: #DIV/0! | I10: #DIV/0!
A11: 广州运营中心 | B11: 新沙港 | C11: 0 | D11: 0 | E11: 9 | F11: 2368.5 | G11: 263.17 | H11: 263.17 | I11: 0
A12: 广州运营中心 | B12: 南沙三期自营 | C12: 0 | D12: 0 | E12: 0 | F12: 0 | G12: #DIV/0! | H12: #DIV/0! | I12: #DIV/0!
A13: 广州运营中心 | B13: 南沙一期码头 | C13: 10 | D13: 630.2 | E13: 135 | F13: 25806.78 | G13: 191.16 | H13: 201.41 | I13: 10.25
A14: 广州运营中心 | B14: 南沙二期 | C14: 6 | D14: 87.6 | E14: 191 | F14: 46614.68 | G14: 244.06 | H14: 251.5 | I14: 7.44
A15: 广州运营中心 | B15: 虎门二期码头 | C15: 266 | D15: 12068.33 | E15: 325 | F15: 35469.28 | G15: 109.14 | H15: 396.63 | I15: 287.49
A16: 广州运营中心 | B16: 虎门港一期 | C16: 0 | D16: 0 | E16: 0 | F16: 0 | G16: #DIV/0! | H16: #DIV/0! | I16: #DIV/0!
A17: 广州运营中心 | B17: 虎门三期码头 | C17: 42 | D17: 1543.99 | E17: 42 | F17: 1543.99 | G17: 36.76 | H17: #DIV/0! | I17: #DIV/0!
A18: 广州运营中心 | B18: 惠州龙溪 | C18: 170 | D18: 8129.58 | E18: 309 | F18: 38544.59 | G18: 124.74 | H18: 218.81 | I18: 94.07
A19: 珠三角运营中心 | B19: 佛山南庄 | C19: 83 | D19: 2678.35 | E19: 232 | F19: 43449.76 | G19: 187.28 | H19: 273.63 | I19: 86.35
A20: 珠三角运营中心 | B20: 白坭南拓 | C20: 0 | D20: 0 | E20: 57 | F20: 12095.76 | G20: 212.21 | H20: 212.21 | I20: 0
A21: 珠三角运营中心 | B21: 佛山南鲲 | C21: 1 | D21: 31.51 | E21: 38 | F21: 11310.24 | G21: 297.64 | H21: 304.83 | I21: 7.19
A22: 珠三角运营中心 | B22: 佛山高明外堆场 | C22: 15 | D22: 472.65 | E22: 167 | F22: 40095.1 | G22: 240.09 | H22: 260.67 | I22: 20.58
A23: 珠三角运营中心 | B23: 佛山高明珠江码头 | C23: 0 | D23: 0 | E23: 0 | F23: 0 | G23: #DIV/0! | H23: #DIV/0! | I23: #DIV/0!
A24: 珠三角运营中心 | B24: 佛山高明战备码头 | C24: 1 | D24: 63.02 | E24: 1 | F24: 63.02 | G24: 63.02 | H24: #DIV/0! | I24: #DIV/0!
A25: 珠三角运营中心 | B25: 珠海高栏 | C25: 0 | D25: 0 | E25: 146 | F25: 39195.82 | G25: 268.46 | H25: 268.46 | I25: 0
A26: 珠三角运营中心 | B26: 肇庆南江 | C26: 0 | D26: 0 | E26: 35 | F26: 10601.08 | G26: 302.89 | H26: 302.89 | I26: 0
A27: 珠三角运营中心 | B27: 肇庆新港 | C27: 62 | D27: 2457.78 | E27: 73 | F27: 5521.81 | G27: 75.64 | H27: 278.55 | I27: 202.91
A28: 珠三角运营中心 | B28: 江门外海 | C28: 0 | D28: 0 | E28: 111 | F28: 34468.74 | G28: 310.53 | H28: 310.53 | I28: 0
A29: 珠三角运营中心 | B29: 贵阳陆港铁路场 | C29: 0 | D29: 0 | E29: 0 | F29: 0 | G29: #DIV/0! | H29: #DIV/0! | I29: #DIV/0!
A30: 珠三角运营中心 | B30: 顺德乐从 | C30: 0 | D30: 0 | E30: 286 | F30: 40496.98 | G30: 141.6 | H30: 141.6 | I30: 0
A31: 珠三角运营中心 | B31: 佛山顺乐自营 | C31: 0 | D31: 0 | E31: 279 | F31: 64412.93 | G31: 230.87 | H31: 230.87 | I31: 0
A32: 珠三角运营中心 | B32: 顺德中储粮 | C32: 0 | D32: 0 | E32: 0 | F32: 0 | G32: #DIV/0! | H32: #DIV/0! | I32: #DIV/0!
A33: 珠三角运营中心 | B33: 高明高荷码头 | C33: 45 | D33: 1417.95 | E33: 46 | F33: 1586 | G33: 34.48 | H33: 168.05 | I33: 133.57
A34: 粤西运营中心 | B34: 湛江外堆场 | C34: 193 | D34: 6298.33 | E34: 291 | F34: 79244.29 | G34: 272.32 | H34: 744.35 | I34: 472.03
A35: 粤西运营中心 | B35: 湛江港 | C35: 249 | D35: 14294.09 | E35: 726 | F35: 79699.05 | G35: 109.78 | H35: 137.12 | I35: 27.34
A36: 粤西运营中心 | B36: 水东 | C36: 16 | D36: 819.26 | E36: 117 | F36: 42651.43 | G36: 364.54 | H36: 414.18 | I36: 49.64
A37: 北部湾运营中心 | B37: 防城港外堆场 | C37: 0 | D37: 0 | E37: 477 | F37: 131295.71 | G37: 275.25 | H37: 275.25 | I37: 0
A38: 北部湾运营中心 | B38: 防城港二堆场 | C38: 0 | D38: 0 | E38: 140 | F38: 40343.91 | G38: 288.17 | H38: 288.17 | I38: 0
A39: 北部湾运营中心 | B39: 广西钦州外堆场自营 | C39: 0 | D39: 0 | E39: 896 | F39: 220295.46 | G39: 245.87 | H39: 245.87 | I39: 0
A40: 北部湾运营中心 | B40: 广西钦州港自营 | C40: 0 | D40: 0 | E40: 37 | F40: 12272.21 | G40: 331.68 | H40: 331.68 | I40: 0
A41: 广州弘运 | B41: 东莞石龙 | C41: 52 | D41: 3277.04 | E41: 154 | F41: 35277.14 | G41: 229.07 | H41: 313.73 | I41: 84.65
A42: 广州弘运 | B42: 南沙弘运外堆场 | C42: 7 | D42: 480.71 | E42: 506 | F42: 111698.24 | G42: 220.75 | H42: 222.88 | I42: 2.13
A43: 广州弘运 | B43: 三水新港 | C43: 0 | D43: 0 | E43: 22 | F43: 745.9 | G43: 33.9 | H43: 33.9 | I43: 0
A44: 广州弘运 | B44: 江门李锦记 | C44: 8 | D44: 311.42 | E44: 15 | F44: 1364.63 | G44: 90.98 | H44: 150.46 | I44: 59.48
A45: 广州弘运 | B45: 江门双水 | C45: 8 | D45: 354.67 | E45: 52 | F45: 16042.27 | G45: 308.51 | H45: 356.54 | I45: 48.03
A46: 广州弘运 | B46: 江门天马港 | C46: 0 | D46: 0 | E46: 0 | F46: 0 | G46: #DIV/0! | H46: #DIV/0! | I46: #DIV/0!
A47: 广州弘运 | B47: 江门鹤山 | C47: 1 | D47: 102.59 | E47: 39 | F47: 9405.25 | G47: 241.16 | H47: 244.81 | I47: 3.65
A48: 广州弘运 | B48: 南沙一期弘运 | C48: 13 | D48: 898.4 | E48: 75 | F48: 6435.43 | G48: 85.81 | H48: 89.31 | I48: 3.5
A49: 广州弘运 | B49: 云浮新港 | C49: 1 | D49: 31.51 | E49: 45 | F49: 19251.91 | G49: 427.82 | H49: 436.83 | I49: 9.01
A50: 广州弘运 | B50: 新会新港 | C50: 5 | D50: 315.1 | E50: 106 | F50: 26064.12 | G50: 245.89 | H50: 254.94 | I50: 9.05
A51: 广州弘运 | B51: 广西钦州外堆场弘运 | C51: 0 | D51: 0 | E51: 12 | F51: 4819.97 | G51: 401.66 | H51: 401.66 | I51: 0
A52: 广州弘运 | B52: 高明珠江码头外包 | C52: 0 | D52: 0 | E52: 3 | F52: 298.41 | G52: 99.47 | H52: 99.47 | I52: 0
A53: 浚得兴 | B53: 江门奔达码头 | C53: 0 | D53: 0 | E53: 51 | F53: 16048.01 | G53: 314.67 | H53: 314.67 | I53: 0
A54: 广州弘运 | B54: 黄埔集司 | C54: 0 | D54: 0 | E54: 0 | F54: 0 | G54: #DIV/0! | H54: #DIV/0! | I54: #DIV/0!
A55: 广州弘运 | B55: 肇庆三榕 | C55: 0 | D55: 0 | E55: 29 | F55: 6192.24 | G55: 213.53 | H55: 213.53 | I55: 0
A56: 广州弘运 | B56: 新会亚太 | C56: 0 | D56: 0 | E56: 5 | F56: 1067.03 | G56: 213.41 | H56: 213.41 | I56: 0
A57: 广州弘运 | B57: 防城港 | C57: 0 | D57: 0 | E57: 0 | F57: 0 | G57: #DIV/0! | H57: #DIV/0! | I57: #DIV/0!
A58: 广州弘运 | B58: 乐平码头弘运 | C58: 0 | D58: 0 | E58: 29 | F58: 9149.55 | G58: 315.5 | H58: 315.5 | I58: 0
A59: 广州弘运 | B59: 南沙二期弘运 | C59: 2 | D59: 126.04 | E59: 24 | F59: 2866.9 | G59: 119.45 | H59: 124.58 | I59: 5.13
A60: 钦州弘运 | B60: 北海港 | C60: 0 | D60: 0 | E60: 0 | F60: 0 | G60: #DIV/0! | H60: #DIV/0! | I60: #DIV/0!
A61: 钦州弘运 | B61: 铁山东岸港 | C61: 0 | D61: 0 | E61: 0 | F61: 0 | G61: #DIV/0! | H61: #DIV/0! | I61: #DIV/0!
A62: 钦州弘运 | B62: 广西钦州港外包 | C62: 0 | D62: 0 | E62: 108 | F62: 35445.27 | G62: 328.2 | H62: 328.2 | I62: 0
A63: 钦州弘运 | B63: 防城港钦州弘运 | C63: 0 | D63: 0 | E63: 151 | F63: 38429.82 | G63: 254.5 | H63: 254.5 | I63: 0
A64: 钦州弘运 | B64: 广西铁山港 | C64: 29 | D64: 1039.83 | E64: 238 | F64: 32655.5 | G64: 137.21 | H64: 151.27 | I64: 14.06
A65: 钦州弘运 | B65: 广西铁山港外堆场 | C65: 0 | D65: 0 | E65: 218 | F65: 56202.46 | G65: 257.81 | H65: 257.81 | I65: 0
A66: 弘运天浩 | B66: 江门三埠港 | C66: 6 | D66: 189.06 | E66: 58 | F66: 16033.6 | G66: 276.44 | H66: 304.7 | I66: 28.26
A67: 万建达 | B67: 防城港万建达堆场 | C67: 0 | D67: 0 | E67: 329 | F67: 104072.59 | G67: 316.33 | H67: 316.33 | I67: 0
A68: 弘运天浩 | B68: 江门公益港 | C68: 0 | D68: 0 | E68: 0 | F68: 0 | G68: #DIV/0! | H68: #DIV/0! | I68: #DIV/0!
A69: 弘运天浩 | B69: 清远港 | C69: 0 | D69: 0 | E69: 18 | F69: 379.78 | G69: 21.1 | H69: 21.1 | I69: 0
A70: 弘运天浩 | B70: 顺德勒流 | C70: 0 | D70: 0 | E70: 0 | F70: 0 | G70: #DIV/0! | H70: #DIV/0! | I70: #DIV/0!
A71: 弘运天浩 | B71: 顺德容奇 | C71: 0 | D71: 0 | E71: 0 | F71: 0 | G71: #DIV/0! | H71: #DIV/0! | I71: #DIV/0!
A72: 弘运天浩 | B72: 顺德颐德 | C72: 72 | D72: 2993.45 | E72: 389 | F72: 37055.05 | G72: 95.26 | H72: 107.45 | I72: 12.19
A73: 弘运天浩 | B73: 莲花山 | C73: 0 | D73: 0 | E73: 0 | F73: 0 | G73: #DIV/0! | H73: #DIV/0! | I73: #DIV/0!
A74: 弘运天浩 | B74: 肇庆马房(四会) | C74: 0 | D74: 0 | E74: 0 | F74: 0 | G74: #DIV/0! | H74: #DIV/0! | I74: #DIV/0!
A75: 弘运天浩 | B75: 肇庆马房 | C75: 0 | D75: 0 | E75: 1 | F75: 75.67 | G75: 75.67 | H75: 75.67 | I75: 0
A76: 弘运天浩 | B76: 珠海斗门 | C76: 0 | D76: 0 | E76: 11 | F76: 2580.44 | G76: 234.59 | H76: 234.59 | I76: 0
A77: 弘运天浩 | B77: 佛山南海北村码头 | C77: 0 | D77: 0 | E77: 5 | F77: 736.7 | G77: 147.34 | H77: 147.34 | I77: 0
A78: 广州弘运 | B78: 惠州堆场 | C78: 0 | D78: 0 | E78: 33 | F78: 7767.57 | G78: 235.38 | H78: 235.38 | I78: 0
A79: 万年红 | B79: 中山小榄 | C79: 63 | D79: 2730.36 | E79: 112 | F79: 7775.43 | G79: 69.42 | H79: 102.96 | I79: 33.54
A80: 万年红 | B80: 中山港 | C80: 85 | D80: 3586.17 | E80: 117 | F80: 12859.95 | G80: 109.91 | H80: 289.81 | I80: 179.89
A81: 万年红 | B81: 江门外海外包 | C81: 0 | D81: 0 | E81: 0 | F81: 0 | G81: #DIV/0! | H81: #DIV/0! | I81: #DIV/0!
A82: 万年红 | B82: 珠海洪湾 | C82: 0 | D82: 0 | E82: 0 | F82: 0 | G82: #DIV/0! | H82: #DIV/0! | I82: #DIV/0!
A83: 万年红 | B83: 珠海神湾 | C83: 3 | D83: 189.06 | E83: 7 | F83: 355.1 | G83: 50.73 | H83: 41.51 | I83: -9.22
A84: 万年红 | B84: 珠海西域 | C84: 0 | D84: 0 | E84: 2 | F84: 314.28 | G84: 157.14 | H84: 157.14 | I84: 0
A85: 万年红 | B85: 江门高沙 | C85: 24 | D85: 1512.48 | E85: 29 | F85: 2135.62 | G85: 73.64 | H85: 124.63 | I85: 50.99
A86: 万年红 | B86: 中山黄圃港 | C86: 1 | D86: 15.57 | E86: 22 | F86: 456.89 | G86: 20.77 | H86: 21.02 | I86: 0.25
A87: 万年红 | B87: 中山外运码头 | C87: 2 | D87: 63.02 | E87: 6 | F87: 1091.66 | G87: 181.94 | H87: 257.16 | I87: 75.22
A88: 裕丰 | B88: 广西新龙 | C88: 0 | D88: 0 | E88: 112 | F88: 31488.6 | G88: 281.15 | H88: 281.15 | I88: 0
A89: 裕丰 | B89: 广西武林 | C89: 4 | D89: 126.04 | E89: 14 | F89: 1833.27 | G89: 130.95 | H89: 170.72 | I89: 39.78
A90: 裕丰 | B90: 广西苏湾港 | C90: 21 | D90: 661.71 | E90: 124 | F90: 18518.96 | G90: 149.35 | H90: 173.37 | I90: 24.02
A91: 裕丰 | B91: 广西贵港 | C91: 3 | D91: 126.04 | E91: 63 | F91: 10475.21 | G91: 166.27 | H91: 172.49 | I91: 6.21
A92: 裕丰 | B92: 广西武林通洲码头 | C92: 0 | D92: 0 | E92: 0 | F92: 0 | G92: #DIV/0! | H92: #DIV/0! | I92: #DIV/0!
A93: 裕丰 | B93: 广西武宣 | C93: 0 | D93: 0 | E93: 0 | F93: 0 | G93: #DIV/0! | H93: #DIV/0! | I93: #DIV/0!
A94: 裕丰 | B94: 广西名燕 | C94: 0 | D94: 0 | E94: 0 | F94: 0 | G94: #DIV/0! | H94: #DIV/0! | I94: #DIV/0!
A95: 裕丰 | B95: 广西中储粮 | C95: 0 | D95: 0 | E95: 0 | F95: 0 | G95: #DIV/0! | H95: #DIV/0! | I95: #DIV/0!
A96: 本港 | B96: 炭步新港 | C96: 0 | D96: 0 | E96: 0 | F96: 0 | G96: #DIV/0! | H96: #DIV/0! | I96: #DIV/0!
A97: 广州弘运 | B97: 花都巴江 | C97: 0 | D97: 0 | E97: 100 | F97: 17172.1 | G97: 171.72 | H97: 171.72 | I97: 0
A98: 本港 | B98: 肇庆三榕本港 | C98: 0 | D98: 0 | E98: 13 | F98: 4130.94 | G98: 317.76 | H98: 317.76 | I98: 0
A99: 本港 | B99: 佛山三水南港本港 | C99: 0 | D99: 0 | E99: 5 | F99: 2658.24 | G99: 531.65 | H99: 531.65 | I99: 0
A100: 本港 | B100: 佛山顺乐本港 | C100: 0 | D100: 0 | E100: 0 | F100: 0 | G100: #DIV/0! | H100: #DIV/0! | I100: #DIV/0!
...

Sheet 2025年18周
A1: 单位汇总报表 | X1: 自营箱量完成情况
A2: 业务类型 | C2: 中远海干箱 | J2: 第三方干箱 | P2: 其它费用 | T2: 合计 | X2: 生产周期 | Z2: 18
A3: 部门/单位 | C3: 箱量 | D3: 环比 | E3: 产值 | F3: 环比 | G3: 单箱 | H3: 环比 | I3: 移箱费 | J3: 箱量 | K3: 环比 | L3: 产值 | M3: 环比 | N3: 单箱 | O3: 环比 | P3: 冷箱产值 | Q3: 堆场产值 | R3: 其它 | S3: 现金收费 | T3: 箱量 | U3: 产值 | V3: 人均产出 | W3: 人员数量 | X3: 周目标箱量 | Y3: 完成差额 | Z3: 合计目标箱量 | AA3: 合计完成量 | AB3: 合计完成差额
A4: 自营 | B4: 深圳运营中心 | C4: 496 | D4: 104 | E4: 183152.4 | F4: 0.2271 | G4: 369.26 | H4: -0.0302 | I4: 0 | J4: 131 | K4: -36 | L4: 46704 | M4: -0.2028 | N4: 356.52 | O4: 0.0163 | P4: 0 | Q4: 1152068.1 | R4: 6195 | S4: 0 | T4: 627 | U4: 1388119.4 | V4: 33050 | W4: 42 | X4: 900 | Y4: -273 | Z4: 16200 | AA4: 9816 | AB4: -6384
B5: 广州运营中心 | C5: 2849 | D5: -97 | E5: 431050.03 | F5: -0.107 | G5: 151.3 | H5: -0.0766 | I5: 187871.59 | J5: 148 | K5: -54 | L5: 42843 | M5: -0.0504 | N5: 289.48 | O5: 0.2961 | P5: 6218.94 | Q5: 0 | R5: 9540 | T5: 2997 | U5: 677523.56 | V5: 20531 | W5: 33 | X5: 2500 | Y5: 497 | Z5: 45000 | AA5: 49206 | AB5: 4206
B6: 珠三角运营中心 | C6: 2284 | D6: 134 | E6: 519472.11 | F6: 0.0169 | G6: 227.44 | H6: -0.0428 | I6: 119238.58 | J6: 249 | K6: 113 | L6: 82971 | M6: 0.2888 | N6: 333.22 | O6: -0.2961 | P6: 0 | Q6: 9509 | R6: 0 | T6: 2533 | U6: 731190.69 | V6: 12607 | W6: 58 | X6: 3000 | Y6: -467 | Z6: 54000 | AA6: 37125 | AB6: -16875
B7: 粤西运营中心 | C7: 1331 | D7: 358 | E7: 350404.39 | F7: 0.2509 | G7: 263.26 | H7: -0.0856 | I7: 44859.815 | J7: 43 | K7: 21 | L7: 12247 | M7: 1.8 | N7: 284.81 | O7: 0.4325 | P7: 52532.35 | Q7: 13281.6 | R7: 25922.52 | T7: 1374 | U7: 499247.67 | V7: 23774 | W7: 21 | X7: 1100 | Y7: 274 | Z7: 19800 | AA7: 23252 | AB7: 3452
B8: 北部湾运营中心 | C8: 1957 | D8: -203 | E8: 628333.08 | F8: -0.072 | G8: 321.07 | H8: 0.0243 | I8: 495.0306 | J8: 14 | K8: 6 | L8: 2553 | M8: 0.575 | N8: 182.36 | O8: -0.1 | P8: 0 | Q8: 71280.5 | R8: 7290 | T8: 1971 | U8: 709951.61 | V8: 22186 | W8: 32 | X8: 1500 | Y8: 471 | Z8: 27000 | AA8: 37496 | AB8: 10496
B9: 南岗分公司 | C9: 246 | D9: -36 | E9: 41928.99 | F9: -0.0371 | G9: 170.44 | H9: 0.1037 | I9: 10905.057 | J9: 422 | K9: -492 | L9: 50873 | M9: -0.3272 | N9: 120.55 | O9: 0.4571 | P9: 2689.8 | Q9: 82306 | R9: 46144 | S9: 0 | T9: 668 | U9: 234846.85 | V9: 13047 | W9: 18 | X9: 600 | Y9: 68 | Z9: 10800 | AA9: 11177 | AB9: 377
B10: 自营总计 | C10: 9163 | D10: 260 | E10: 2154341 | F10: 0.005 | G10: 235.11 | H10: -0.0235 | I10: 363370.08 | J10: 1007 | K10: -442 | L10: 238191 | M10: -0.046 | N10: 236.54 | O10: 0.3727 | P10: 61441.09 | Q10: 1328445.1 | R10: 95091.52 | S10: 0 | T10: 10170 | U10: 4240879.8 | V10: 20789 | W10: 204 | X10: 9600 | Y10: 570 | Z10: 172800 | AA10: 168072 | AB10: -4728
A11: 合作供应商 | B11: 广州弘运 | C11: 2512 | D11: -189 | E11: 708298.26 | F11: 0.0515 | G11: 281.97 | H11: 0.1306 | I11: 113431.7 | J11: 20 | K11: 10 | L11: 3620 | M11: 0.5159 | N11: 181 | O11: -0.242 | P11: 21766.6 | T11: 2532 | U11: 847116.56
B12: 钦州弘运 | C12: 698 | D12: 189 | E12: 161514.97 | F12: 0.0605 | G12: 231.4 | H12: -0.2266 | I12: 26456.635 | J12: 4 | K12: 4 | L12: 1988 | M12: #DIV/0! | N12: 497 | O12: #DIV/0! | P12: 0 | T12: 702 | U12: 189959.61
B13: 弘运天浩 | C13: 617 | D13: 155 | E13: 133284.5 | F13: 0.5511 | G13: 216.02 | H13: 0.1615 | I13: 38934.998 | J13: 51 | K13: 30 | L13: 13449 | M13: 1.8451 | N13: 263.71 | O13: 0.1715 | P13: 0 | T13: 668 | U13: 185668.5
B14: 万年红 | C14: 340 | D14: 12 | E14: 49228.17 | F14: 0.3322 | G14: 144.79 | H14: 0.2852 | I14: 22759.451 | J14: 0 | K14: 0 | L14: 0 | M14: #DIV/0! | N14: #DIV/0! | O14: #DIV/0! | P14: 0 | T14: 340 | U14: 71987.62
B15: 裕丰 | C15: 326 | D15: -28 | E15: 75398.21 | F15: 0.0982 | G15: 231.28 | H15: 0.1925 | I15: 18490.873 | J15: 0 | K15: 0 | L15: 0 | M15: #DIV/0! | N15: #DIV/0! | O15: #DIV/0! | P15: 0 | T15: 326 | U15: 93889.08
B16: 本港 | C16: 18 | D16: -2 | E16: 3784.37 | F16: -0.6598 | G16: 210.24 | H16: -0.622 | I16: 1030.0444 | J16: 0 | K16: 0 | L16: 0 | M16: #DIV/0! | N16: #DIV/0! | O16: #DIV/0! | P16: 0 | T16: 18 | U16: 4814.41
B17: 坚迅 | C17: 720 | D17: -162 | E17: 195354.31 | F17: -0.1674 | G17: 271.33 | H17: 0.0199 | I17: 50487.291 | J17: 3 | K17: 0 | L17: 581 | M17: 0.1326 | N17: 193.67 | O17: 0.1326 | P17: 0 | T17: 723 | U17: 246422.6
B18: 浚得兴 | C18: 643 | D18: 79 | E18: 180389.36 | F18: 0.2037 | G18: 280.54 | H18: 0.0558 | I18: 38865.716 | J18: 0 | K18: 0 | L18: 0 | M18: #DIV/0! | N18: #DIV/0! | O18: #DIV/0! | P18: 0 | T18: 643 | U18: 219255.08
B19: 深圳天河 | C19: 5 | D19: 1 | E19: 1694.59 | F19: -0.1101 | G19: 338.92 | H19: -0.2881 | I19: 374.975 | J19: 0 | K19: 0 | L19: 0 | M19: #DIV/0! | N19: #DIV/0! | O19: #DIV/0! | P19: 0 | T19: 5 | U19: 2069.57
B20: 信步 | C20: 783 | D20: -65 | E20: 132815.34 | F20: 0.0053 | G20: 169.62 | H20: 0.0888 | I20: 45846.495 | J20: 11 | K20: -8 | L20: 3474 | M20: -0.4784 | N20: 315.82 | O20: -0.099 | P20: 0 | T20: 794 | U20: 182135.83
B21: 万永联 | C21: 161 | D21: -35 | E21: 28371.25 | F21: -0.0313 | G21: 176.22 | H21: 0.1794 | I21: 0 | J21: 0 | K21: 0 | L21: 0 | M21: #DIV/0! | N21: #DIV/0! | O21: #DIV/0! | P21: 0 | T21: 161 | U21: 28371.25
B22: 辉成 | C22: 197 | D22: -54 | E22: 41730.12 | F22: -0.0637 | G22: 211.83 | H22: 0.1929 | I22: 11175.527 | J22: 0 | K22: 0 | L22: 0 | M22: #DIV/0! | N22: #DIV/0! | O22: #DIV/0! | P22: 0 | T22: 197 | U22: 52905.65
B23: 万建达 | C23: 741 | D23: 112 | E23: 277803.3 | F23: 0.2946 | G23: 374.9 | H23: 0.0989 | I23: 0 | J23: 0 | K23: 0 | L23: 0 | M23: #DIV/0! | N23: #DIV/0! | O23: #DIV/0! | P23: 0 | T23: 741 | U23: 277803.3
B24: 别志 | C24: 5 | D24: 5 | E24: 2145.5 | F24: #DIV/0! | G24: 429.1 | H24: #DIV/0! | I24: 275.017 | J24: 0 | K24: 0 | L24: 0 | M24: #DIV/0! | N24: #DIV/0! | O24: #DIV/0! | P24: 0 | T24: 5 | U24: 2420.52
B25: 泓洋 | C25: 71 | D25: -6 | E25: 19239.45 | F25: -0.5462 | G25: 270.98 | H25: -0.5079 | I25: 3905.2414 | J25: 0 | K25: 0 | L25: 0 | M25: #DIV/0! | N25: #DIV/0! | O25: #DIV/0! | P25: 0 | T25: 71 | U25: 23144.69
B26: 万海通 | C26: 80 | D26: -21 | E26: 32526.3 | F26: -0.2193 | G26: 406.58 | H26: -0.0143 | I26: 4400.272 | J26: 0 | K26: 0 | L26: 0 | M26: #DIV/0! | N26: #DIV/0! | O26: #DIV/0! | P26: 0 | T26: 80 | U26: 36926.57
B27: 华慧良修 | C27: 241 | D27: 55 | E27: 98230.14 | F27: 0.4545 | G27: 407.59 | H27: 0.1226 | I27: 0 | J27: 296 | K27: -98 | L27: 59685 | M27: -0.2291 | N27: 201.64 | O27: 0.0262 | P27: 0 | T27: 537 | U27: 157915.14
B28: 广州一鸣 | C28: 16 | D28: -22 | E28: 3157.37 | F28: -0.5479 | G28: 197.34 | H28: 0.0737 | I28: 880.0544 | J28: 0 | K28: 0 | L28: 0 | M28: #DIV/0! | N28: #DIV/0! | O28: #DIV/0! | P28: 0 | T28: 16 | U28: 4037.42
B29: 凯琪物流 | C29: 197 | D29: 107 | E29: 15304.09 | F29: 1.2594 | G29: 77.69 | H29: 0.0323 | I29: 11055.577 | J29: 0 | K29: 0 | L29: 0 | M29: #DIV/0! | N29: #DIV/0! | O29: #DIV/0! | P29: 0 | T29: 197 | U29: 26359.67
B30: 南宁亿邦 | C30: 449 | D30: -448 | E30: 98497.97 | F30: -0.5783 | G30: 219.37 | H30: -0.1576 | I30: 9405.5814 | J30: 0 | K30: 0 | L30: 0 | M30: #DIV/0! | N30: #DIV/0! | O30: #DIV/0! | P30: 0 | T30: 449 | U30: 107903.55
B31: 星之航 | C31: 32 | D31: 19 | E31: 8568.38 | F31: 2.0744 | G31: 267.76 | H31: 0.249 | I31: 0 | J31: 0 | K31: 0 | L31: 0 | M31: #DIV/0! | N31: #DIV/0! | O31: #DIV/0! | P31: 0 | T31: 32 | U31: 8568.38
B32: 广通 | C32: 0 | D32: 0 | E32: 0 | F32: #DIV/0! | G32: #DIV/0! | H32: #DIV/0! | I32: 0 | J32: 74 | K32: -2 | L32: 14572 | M32: -0.1233 | N32: 196.92 | O32: -0.0996 | P32: 14220.59 | T32: 74 | U32: 28792.59
B33: 汕头裕港 | C33: 0 | D33: 0 | E33: 0 | F33: #DIV/0! | G33: #DIV/0! | H33: #DIV/0! | I33: 0 | J33: 0 | K33: 0 | L33: 0 | M33: #DIV/0! | N33: #DIV/0! | O33: #DIV/0! | P33: 0 | T33: 0 | U33: 0
B34: 港信 | C34: 66 | D34: -14 | E34: 20075.16 | F34: -0.2775 | G34: 304.17 | H34: -0.1242 | I34: 3910.1068 | J34: 0 | K34: 0 | L34: 0 | M34: #DIV/0! | N34: #DIV/0! | O34: #DIV/0! | P34: 0 | T34: 66 | U34: 23985.27
B35: 外包总计 | C35: 8918 | D35: -312 | E35: 2287411.1 | F35: 0.0099 | G35: 256.49 | H35: 0.0452 | I35: 401685.56 | J35: 459 | K35: -64 | L35: 97369 | M35: -0.1012 | N35: 212.13 | O35: 0.0241 | P35: 35987.19 | Q35: 0 | R35: 0 | S35: 0 | T35: 9377 | U35: 2822452.9
A36: 自营外包总计 | C36: 18081 | D36: -52 | E36: 4441752.1 | F36: 0.0075 | G36: 245.66 | H36: 0.0104 | I36: 765055.64 | J36: 1466 | K36: -506 | L36: 335560 | M36: -0.0627 | N36: 228.89 | O36: 0.2608 | P36: 97428.28 | Q36: 1328445.1 | R36: 95091.52 | S36: 0 | T36: 19547 | U36: 7063332.7
O37: 环比增减 | U37: -626154.73 | V37: -558 | W37: -626154.73
C38: 箱量 | D38: 环比 | E38: 产值 | F38: 环比 | Q38: 净值 | U38: 6378639.3
A39: 全部干箱业务 | C39: 19547 | D39: -0.03 | E39: 7063333 | F39: -0.0814 | M39: 56.15363
A40: 中远海自营占比 | C40: 0.925 | E40: 0.6288
A41: 第三方业务占比 | C41: 0.075 | E41: 0.0475
A42: 网点明细报表
A43: 业务类型 | C43: 中远海干箱 | J43: 第三方干箱 | P43: 其它费用 | T43: 合计 | X43: 分网点自营箱量完成情况 | AC43: 网点业务情况备注
A44: 部门/单位 | C44: 箱量 | D44: 环比 | E44: 产值 | F44: 环比 | G44: 单箱 | H44: 环比 | I44: 移箱费 | J44: 箱量 | K44: 环比 | L44: 产值 | M44: 环比 | N44: 单箱 | O44: 环比 | P44: 冷箱产值 | Q44: 堆场产值 | R44: 其它 | S44: 现金收费 | T44: 箱量 | U44: 产值 | V44: 人均产出 | W44: 修理人员数量 | X44: 周目标箱量 | Y44: 完成差额 | Z44: 合计目标箱量 | AA44: 合计完成量 | AB44: 合计完成差额
A45: 南岗分公司 | B45: 南岗堆场 | C45: 71 | D45: 17 | E45: 21111.08 | F45: 0.3762 | G45: 297 | H45: 0.0458 | I45: 0 | J45: 395 | K45: -519 | L45: 48173.43 | M45: -0.3629 | N45: 122 | O45: 0.4699 | P45: 2689.8 | Q45: 82306 | S45: 0 | T45: 466 | U45: 154280 | V45: 13257 | W45: 7 | X45: 600 | Y45: 68 | Z45: 10800 | AA45: 7798 | AB45: -3002
A46: 南岗分公司 | B46: 东江仓码头 | C46: 175 | D46: -53 | E46: 20817.91 | F46: -0.2619 | G46: 119 | H46: -0.0403 | I46: 10905.057 | J46: 27 | K46: 27 | L46: 2699.78 | M46: #DIV/0! | N46: 100 | O46: #DIV/0! | P46: 0 | S46: 0 | T46: 202 | U46: 34423 | Z46: 0 | AA46: 3379 | AB46: 3379
A47: 深圳运营中心 | B47: 深圳大铲湾 | C47: 174 | D47: -31 | E47: 69293.42 | F47: -0.1575 | G47: 398 | H47: -0.0075 | I47: 0 | J47: 1 | K47: -3 | L47: 495.51 | M47: -0.6626 | N47: 496 | O47: 0.3515 | P47: 0 | S47: 0 | T47: 175 | U47: 69789 | V47: 17447 | W47: 4 | X47: 400 | Y47: -225 | Z47: 7200 | AA47: 2476 | AB47: -4724
A48: 华慧良修 | B48: 深圳蛇口堆场 | C48: 241 | D48: 56 | E48: 98230.14 | F48: 0.4619 | G48: 408 | H48: 0.124 | I48: 0 | J48: 255 | K48: -20 | L48: 52209.06 | M48: -0.0104 | N48: 205 | O48: 0.0677 | P48: 0 | Q48: 114325.05 | S48: 0 | T48: 496 | U48: 264764 | V48: 21491 | W48: 7 | X48: 400 | Y48: 96 | Z48: 7200 | AA48: 6712 | AB48: -488
A49: 深圳运营中心 | B49: 汕头广澳 | C49: 0 | D49: 0 | E49: 0 | F49: #DIV/0! | G49: #DIV/0! | H49: #DIV/0! | I49: 0 | J49: 0 | K49: 0 | L49: 0 | M49: #DIV/0! | N49: #DIV/0! | O49: #DIV/0! | P49: 0 | S49: 0 | T49: 0 | U49: 0 | V49: #DIV/0! | W49: 0 | X49: 500 | Y49: -48 | Z49: 9000 | AA49: 7098 | AB49: -1902
A50: 深圳运营中心 | B50: 汕头堆场 | C50: 322 | D50: 135 | E50: 113858.98 | F50: 0.6991 | G50: 354 | H50: -0.0112 | I50: 0 | J50: 130 | K50: -33 | L50: 46208.1 | M50: -0.191 | N50: 355 | O50: 0.0143 | P50: 0 | Q50: 16613 | R50: 1458 | S50: 0 | T50: 452 | U50: 178138 | V50: 16007 | W50: 10
A51: 深圳运营中心 | B51: 汕头国集 | C51: 0 | D51: 0 | E51: 0 | F51: #DIV/0! | G51: #DIV/0! | H51: #DIV/0! | I51: 0 | J51: 0 | K51: 0 | L51: 0 | M51: #DIV/0! | N51: #DIV/0! | O51: #DIV/0! | P51: 0 | S51: 0 | T51: 0 | U51: 0 | V51: #DIV/0! | W51: 0
A52: 广州运营中心 | B52: 黄埔旧港 | C52: 1258 | D52: -75 | E52: 157695.71 | F52: -0.1868 | G52: 125 | H52: -0.1379 | I52: 85567.398 | J52: 0 | K52: -1 | L52: 0 | M52: -1 | N52: #DIV/0! | O52: #DIV/0! | P52: 0 | S52: 0 | T52: 1258 | U52: 243263 | V52: 16150 | W52: 10 | X52: 1100 | Y52: 158 | Z52: 19800 | AA52: 21420 | AB52: 1620
A53: 广州运营中心 | B53: 淡水河码头 | C53: 0 | D53: 0 | E53: 0 | F53: #DIV/0! | G53: #DIV/0! | H53: #DIV/0! | I53: 0 | J53: 0 | K53: 0 | L53: 0 | M53: #DIV/0! | N53: #DIV/0! | O53: #DIV/0! | P53: 0 | S53: 0 | T53: 0 | U53: 0 | AC53: 2023年1月新开，新鱼珠点改名
A54: 广州运营中心 | B54: 新沙港 | C54: 12 | D54: -46 | E54: 3804.46 | F54: -0.798 | G54: 317 | H54: -0.0246 | I54: 660.0408 | J54: 0 | K54: 0 | L54: 0 | M54: #DIV/0! | N54: #DIV/0! | O54: #DIV/0! | P54: 0 | S54: 0 | T54: 12 | U54: 4465 | AC54: 2023年2月新开。
A55: 广州运营中心 | B55: 南沙三期自营 | C55: 0 | D55: 0 | E55: 0 | F55: #DIV/0! | G55: #DIV/0! | H55: #DIV/0! | I55: 0 | J55: 0 | K55: 0 | L55: 0 | M55: #DIV/0! | N55: #DIV/0! | O55: #DIV/0! | P55: 0 | S55: 0 | T55: 0 | U55: 0 | V55: 28581 | W55: 5 | X55: 500 | Y55: 49 | Z55: 9000 | AA55: 8787 | AB55: -213
A56: 广州运营中心 | B56: 南沙一期码头 | C56: 215 | D56: 8 | E56: 44317.3 | F56: 0.0184 | G56: 206 | H56: -0.019 | I56: 15983.984 | J56: 79 | K56: -17 | L56: 23298.01 | M56: 0.0907 | N56: 295 | O56: 0.3229 | P56: 0 | R56: 1050 | S56: 0 | T56: 294 | U56: 84649
A57: 广州运营中心 | B57: 南沙二期 | C57: 196 | D57: -91 | E57: 57180.24 | F57: -0.2881 | G57: 292 | H57: 0.0429 | I57: 14439.129 | J57: 59 | K57: -8 | L57: 18108.46 | M57: 0.0316 | N57: 307 | O57: 0.1718 | P57: 6218.94 | S57: 0 | T57: 255 | U57: 95947
A58: 广州运营中心 | B58: 虎门二期码头 | C58: 467 | D58: -63 | E58: 61263.38 | F58: 0.1283 | G58: 131 | H58: 0.2843 | I58: 29684.908 | J58: 8 | K58: -25 | L58: 1081.01 | M58: -0.7794 | N58: 135 | O58: -0.094 | P58: 0 | S58: 0 | T58: 475 | U58: 92029 | V58: 16708 | W58: 4 | X58: 400 | Y58: 75 | Z58: 7200 | AA58: 9507 | AB58: 2307
A59: 广州运营中心 | B59: 虎门港一期 | C59: 0 | D59: 0 | E59: 0 | F59: #DIV/0! | G59: #DIV/0! | H59: #DIV/0! | I59: 0 | J59: 0 | K59: 0 | L59: 0 | M59: #DIV/0! | N59: #DIV/0! | O59: #DIV/0! | P59: 0 | S59: 0 | T59: 0 | U59: 0
A60: 广州运营中心 | B60: 虎门三期码头 | C60: 80 | D60: -16 | E60: 4486.39 | F60: -0.1656 | G60: 56 | H60: 0 | I60: 5319.8856 | J60: 0 | K60: 0 | L60: 0 | M60: #DIV/0! | N60: #DIV/0! | O60: #DIV/0! | P60: 0 | S60: 0 | T60: 80 | U60: 9806
A61: 广州运营中心 | B61: 惠州龙溪 | C61: 621 | D61: 186 | E61: 102302.55 | F61: 0.1835 | G61: 165 | H61: -0.1709 | I61: 36216.246 | J61: 2 | K61: -3 | L61: 355.9 | M61: -0.7091 | N61: 178 | O61: -0.2735 | P61: 0 | R61: 8490 | S61: 0 | T61: 623 | U61: 147365 | V61: 20532 | W61: 5 | X61: 500 | Y61: 123 | Z61: 9000 | AA61: 9492 | AB61: 492
A62: 珠三角运营中心 | B62: 佛山南庄 | C62: 392 | D62: 126 | E62: 85974.1 | F62: 0.5492 | G62: 219 | H62: 0.0478 | I62: 21601.316 | J62: 18 | K62: 18 | L62: 4726.33 | M62: #DIV/0! | N62: 263 | O62: #DIV/0! | P62: 0 | S62: 0 | T62: 410 | U62: 112302 | V62: 15117 | W62: 6 | X62: 450 | Y62: -40 | Z62: 8100 | AA62: 6180 | AB62: -1920
A63: 珠三角运营中心 | B63: 白坭南拓 | C63: 129 | D63: -61 | E63: 56839.64 | F63: -0.2185 | G63: 441 | H63: 0.1514 | I63: 7095.4386 | J63: 104 | K63: 32 | L63: 38501.51 | M63: -0.0325 | N63: 370 | O63: -0.3309 | P63: 0 | S63: 0 | T63: 233 | U63: 102437 | V63: 11918 | W63: 8 | X63: 300 | Y63: -67 | Z63: 5400 | AA63: 2113 | AB63: -3287
A64: 珠三角运营中心 | B64: 佛山南鲲 | C64: 44 | D64: -24 | E64: 10322.75 | F64: -0.4072 | G64: 235 | H64: -0.082 | I64: 2420.1496 | J64: 63 | K64: 59 | L64: 13649.64 | M64: 19.553 | N64: 217 | O64: 0.3072 | P64: 0 | S64: 0 | T64: 107 | U64: 26393 | V64: 3425 | W64: 7 | X64: 150 | Y64: -43 | Z64: 2700 | AA64: 1288 | AB64: -1412
A65: 珠三角运营中心 | B65: 佛山高明外堆场 | C65: 259 | D65: 107 | E65: 56897.6 | F65: 0.479 | G65: 220 | H65: -0.1304 | I65: 0 | J65: 0 | K65: 0 | L65: 0 | M65: #DIV/0! | N65: #DIV/0! | O65: #DIV/0! | P65: 0 | Q65: 9509 | S65: 0 | T65: 259 | U65: 66407 | V65: 8128 | W65: 7 | X65: 350 | Y65: -83 | Z65: 6300 | AA65: 3757 | AB65: -2543
A66: 珠三角运营中心 | B66: 佛山高明珠江码头 | C66: 0 | D66: 0 | E66: 0 | F66: #DIV/0! | G66: #DIV/0! | H66: #DIV/0! | I66: 0 | J66: 0 | K66: 0 | L66: 0 | M66: #DIV/0! | N66: #DIV/0! | O66: #DIV/0! | P66: 0 | S66: 0 | T66: 0 | U66: 0 | V66: #DIV/0! | W66: 0 | AC66: 优化给弘运高明珠江码头外包
A67: 珠三角运营中心 | B67: 佛山高明战备码头 | C67: 8 | D67: 4 | E67: 462.88 | F67: 0.625 | G67: 58 | H67: -0.1831 | I67: 539.9852 | J67: 0 | K67: 0 | L67: 0 | M67: #DIV/0! | N67: #DIV/0! | O67: #DIV/0! | P67: 0 | S67: 0 | T67: 8 | U67: 1003 | V67: 463 | W67: 1
A68: 珠三角运营中心 | B68: 珠海高栏 | C68: 169 | D68: -35 | E68: 46069.74 | F68: -0.2788 | G68: 273 | H68: -0.1278 | I68: 9855.3394 | J68: 5 | K68: 2 | L68: 8697.26 | M68: 0.6266 | N68: 1739 | O68: -0.0241 | P68: 0 | S68: 0 | T68: 174 | U68: 64622 | V68: 6846 | W68: 8 | X68: 350 | Y68: -176 | Z68: 6300 | AA68: 5652 | AB68: -648
A69: 珠三角运营中心 | B69: 肇庆南江 | C69: 117 | D69: -29 | E69: 39752.85 | F69: 0.3112 | G69: 340 | H69: 0.6346 | I69: 6495.3726 | J69: 0 | K69: 0 | L69: 0 | M69: #DIV/0! | N69: #DIV/0! | O69: #DIV/0! | P69: 0 | S69: 0 | T69: 117 | U69: 46248 | V69: 9938 | W69: 4 | X69: 200 | Y69: -83 | Z69: 3600 | AA69: 2403 | AB69: -1197
A70: 珠三角运营中心 | B70: 肇庆新港 | C70: 98 | D70: 33 | E70: 9981.84 | F70: 0.2976 | G70: 102 | H70: -0.1356 | I70: 5710.1988 | J70: 0 | K70: 0 | L70: 0 | M70: #DIV/0! | N70: #DIV/0! | O70: #DIV/0! | P70: 0 | S70: 0 | T70: 98 | U70: 15692 | V70: 4991 | W70: 2 | X70: 100 | Y70: -2 | Z70: 1800 | AA70: 1378 | AB70: -422
A71: 珠三角运营中心 | B71: 江门外海 | C71: 214 | D71: -21 | E71: 64716.04 | F71: -0.0774 | G71: 302 | H71: 0.0134 | I71: 14549.56 | J71: 47 | K71: 9 | L71: 15088.29 | M71: 0.124 | N71: 321 | O71: -0.0907 | P71: 0 | S71: 0 | T71: 261 | U71: 94354 | V71: 15961 | W71: 5 | X71: 200 | Y71: 61 | Z71: 3600 | AA71: 3253 | AB71: -347
A72: 珠三角运营中心 | B72: 贵阳陆港铁路场 | C72: 5 | D72: 0 | E72: 1855.6 | F72: -0.0525 | G72: 371 | H72: -0.0536 | I72: 275.017 | J72: 0 | K72: 0 | L72: 0 | M72: #DIV/0! | N72: #DIV/0! | O72: #DIV/0! | P72: 0 | S72: 0 | T72: 5 | U72: 2131 | V72: #DIV/0! | W72: 0 | X72: 0 | Y72: 5 | Z72: 0 | AA72: 84 | AB72: 84 | AC72: 优化给坚迅江门九江坚迅
A73: 珠三角运营中心 | B73: 顺德乐从 | C73: 335 | D73: -54 | E73: 51024.51 | F73: -0.1251 | G73: 152 | H73: 0.0133 | I73: 22404.467 | J73: 0 | K73: 0 | L73: 0 | M73: #DIV/0! | N73: #DIV/0! | O73: #DIV/0! | P73: 0 | S73: 0 | T73: 335 | U73: 73429 | V73: 12756 | W73: 4 | X73: 380 | Y73: -45 | Z73: 6840 | AA73: 3446 | AB73: -3394
A74: 珠三角运营中心 | B74: 佛山顺乐自营 | C74: 432 | D74: 42 | E74: 92654.84 | F74: -0.0022 | G74: 214 | H74: -0.1008 | I74: 23781.46 | J74: 0 | K74: 0 | L74: 0 | M74: #DIV/0! | N74: #DIV/0! | O74: #DIV/0! | P74: 0 | S74: 0 | T74: 432 | U74: 116436 | V74: 18531 | W74: 5 | X74: 300 | Y74: 132 | Z74: 5400 | AA74: 6048 | AB74: 648
A75: 珠三角运营中心 | B75: 顺德中储粮 | C75: 0 | D75: 0 | E75: 0 | F75: #DIV/0! | G75: #DIV/0! | H75: #DIV/0! | I75: 0 | J75: 0 | K75: 0 | L75: 0 | M75: #DIV/0! | N75: #DIV/0! | O75: #DIV/0! | P75: 0 | S75: 0 | T75: 0 | U75: 0 | V75: #DIV/0! | W75: 0 | X75: 20 | Y75: -20 | Z75: 360 | AA75: 15 | AB75: -345
A76: 珠三角运营中心 | B76: 高明高荷码头 | C76: 82 | D76: 46 | E76: 2919.72 | F76: 1.2778 | G76: 36 | H76: 0 | I76: 4510.2788 | J76: 12 | K76: -7 | L76: 2307.8 | M76: -0.5517 | N76: 192 | O76: -0.2915 | P76: 0 | S76: 0 | T76: 94 | U76: 9738 | V76: 1743 | W76: 3 | X76: 200 | Y76: -106 | Z76: 3600 | AA76: 1508 | AB76: -2092 | AC76: 2023年9月15号新增高荷场站
A77: 粤西运营中心 | B77: 湛江外堆场 | C77: 627 | D77: 144 | E77: 240416.13 | F77: 0.1952 | G77: 383 | H77: -0.0793 | I77: 0 | J77: 0 | K77: 0 | L77: 0 | M77: #DIV/0! | N77: #DIV/0! | O77: #DIV/0! | P77: 0 | Q77: 13281.6 | R77: 25922.52 | S77: 0 | T77: 627 | U77: 279620 | V77: 18433 | W77: 18 | X77: 1000 | Y77: 240 | Z77: 18000 | AA77: 20495 | AB77: 2495 | AC77: 2023年11月新增湛江外堆场
A78: 粤西运营中心 | B78: 湛江港 | C78: 570 | D78: 153 | E78: 79133.89 | F78: 0.2443 | G78: 139 | H78: -0.0915 | I78: 37369.41 | J78: 43 | K78: 21 | L78: 12247.46 | M78: 1.8 | N78: 285 | O78: 0.4322 | P78: 52532.35 | S78: 0 | T78: 613 | U78: 181283
A79: 粤西运营中心 | B79: 水东 | C79: 134 | D79: 61 | E79: 30854.37 | F79: 1.007 | G79: 230 | H79: 0.09 | I79: 7490.4052 | J79: 0 | K79: 0 | L79: 0 | M79: #DIV/0! | N79: #DIV/0! | O79: #DIV/0! | P79: 0 | S79: 0 | T79: 134 | U79: 38345 | V79: 10285 | W79: 3 | X79: 100 | Y79: 34 | Z79: 1800 | AA79: 2757 | AB79: 957
A80: 北部湾运营中心 | B80: 防城港外堆场 | C80: 743 | D80: -397 | E80: 234108.26 | F80: -0.2436 | G80: 315 | H80: 0.1581 | I80: 0 | J80: 0 | K80: 0 | L80: 0 | M80: #DIV/0! | N80: #DIV/0! | O80: #DIV/0! | P80: 0 | Q80: 30710 | S80: 0 | T80: 743 | U80: 264818 | V80: 13006 | W80: 18 | X80: 800 | Y80: 153 | Z80: 14400 | AA80: 20831 | AB80: 6431
A81: 北部湾运营中心 | B81: 防城港二堆场 | C81: 210 | D81: 200 | E81: 67556.6 | F81: 8.2919 | G81: 322 | H81: -0.5571 | I81: 0 | J81: 0 | K81: 0 | L81: 0 | M81: #DIV/0! | N81: #DIV/0! | O81: #DIV/0! | P81: 0 | Q81: 4939.5 | S81: 0 | T81: 210 | U81: 72496 | V81: 13511 | W81: 5
A82: 北部湾运营中心 | B82: 广西钦州外堆场自营 | C82: 995 | D82: 34 | E82: 322196.34 | F82: -0.0402 | G82: 324 | H82: -0.0716 | I82: 0 | J82: 14 | K82: 6 | L82: 2553.26 | M82: 0.575 | N82: 182 | O82: -0.1034 | P82: 0 | Q82: 35631 | R82: 3510 | S82: 0 | T82: 1009 | U82: 363891 | V82: 23516 | W82: 14 | X82: 700 | Y82: 318 | Z82: 12600 | AA82: 15139 | AB82: 2539
A83: 北部湾运营中心 | B83: 广西钦州港自营 | C83: 9 | D83: -40 | E83: 4471.88 | F83: -0.8181 | G83: 497 | H83: -0.01 | I83: 495.0306 | J83: 0 | K83: 0 | L83: 0 | M83: #DIV/0! | N83: #DIV/0! | O83: #DIV/0! | P83: 0 | S83: 0 | T83: 9 | U83: 4967
A84: 广州弘运 | B84: 东莞石龙 | C84: 313 | D84: -144 | E84: 78875.39 | F84: -0.3326 | G84: 252 | H84: -0.027 | I84: 19095.275 | J84: 0 | K84: 0 | L84: 0 | M84: #DIV/0! | N84: #DIV/0! | O84: #DIV/0! | P84: 0 | S84: 0 | T84: 313 | U84: 97971 | V84: #DIV/0!
A85: 广州弘运 | B85: 南沙弘运外堆场 | C85: 439 | D85: -179 | E85: 105671.96 | F85: -0.3328 | G85: 241 | H85: -0.0586 | I85: 0 | J85: 0 | K85: 0 | L85: 0 | M85: #DIV/0! | N85: #DIV/0! | O85: #DIV/0! | P85: 18560.48 | S85: 0 | T85: 439 | U85: 124232 | V85: #DIV/0! | AC85: 优化为自营佛山顺乐自营
A86: 广州弘运 | B86: 三水新港 | C86: 29 | D86: -15 | E86: 3340.55 | F86: 1.5068 | G86: 115 | H86: 2.8333 | I86: 2114.8802 | J86: 0 | K86: 0 | L86: 0 | M86: #DIV/0! | N86: #DIV/0! | O86: #DIV/0! | P86: 0 | S86: 0 | T86: 29 | U86: 5455 | V86: #DIV/0!
A87: 广州弘运 | B87: 江门李锦记 | C87: 13 | D87: -8 | E87: 1002.55 | F87: -0.8473 | G87: 77 | H87: -0.754 | I87: 775.019 | J87: 0 | K87: 0 | L87: 0 | M87: #DIV/0! | N87: #DIV/0! | O87: #DIV/0! | P87: 0 | S87: 0 | T87: 13 | U87: 1778 | V87: #DIV/0!
A88: 广州弘运 | B88: 江门双水 | C88: 37 | D88: -27 | E88: 11667.54 | F88: -0.2918 | G88: 315 | H88: 0.2257 | I88: 2155.0754 | J88: 0 | K88: 0 | L88: 0 | M88: #DIV/0! | N88: #DIV/0! | O88: #DIV/0! | P88: 0 | S88: 0 | T88: 37 | U88: 13823 | V88: #DIV/0!
A89: 广州弘运 | B89: 江门天马港 | C89: 1 | D89: -20 | E89: 240.28 | F89: -0.8542 | G89: 240 | H89: 2.0769 | I89: 74.995 | J89: 0 | K89: 0 | L89: 0 | M89: #DIV/0! | N89: #DIV/0! | O89: #DIV/0! | P89: 0 | S89: 0 | T89: 1 | U89: 315 | V89: #DIV/0!
A90: 广州弘运 | B90: 江门鹤山 | C90: 5 | D90: -21 | E90: 594 | F90: -0.8923 | G90: 119 | H90: -0.4387 | I90: 334.9918 | J90: 0 | K90: 0 | L90: 0 | M90: #DIV/0! | N90: #DIV/0! | O90: #DIV/0! | P90: 0 | S90: 0 | T90: 5 | U90: 929 | V90: #DIV/0!
A91: 广州弘运 | B91: 南沙一期弘运 | C91: 170 | D91: -11 | E91: 15713.81 | F91: -0.1381 | G91: 92 | H91: -0.0891 | I91: 12729.158 | J91: 0 | K91: 0 | L91: 0 | M91: #DIV/0! | N91: #DIV/0! | O91: #DIV/0! | P91: 2110.97 | S91: 0 | T91: 170 | U91: 30554 | V91: #DIV/0!
A92: 广州弘运 | B92: 云浮新港 | C92: 152 | D92: 42 | E92: 66736.29 | F92: 0.545 | G92: 439 | H92: 0.117 | I92: 8400.5 | J92: 0 | K92: 0 | L92: 0 | M92: #DIV/0! | N92: #DIV/0! | O92: #DIV/0! | P92: 0 | S92: 0 | T92: 152 | U92: 75137 | V92: #DIV/0!
A93: 广州弘运 | B93: 新会新港 | C93: 545 | D93: 173 | E93: 136039.81 | F93: 0.8977 | G93: 250 | H93: 0.2953 | I93: 31436.24 | J93: 0 | K93: 0 | L93: 0 | M93: #DIV/0! | N93: #DIV/0! | O93: #DIV/0! | P93: 0 | S93: 0 | T93: 545 | U93: 167476 | V93: #DIV/0!
A94: 广州弘运 | B94: 广西钦州外堆场弘运 | C94: 81 | D94: 47 | E94: 20876.67 | F94: 0.6821 | G94: 258 | H94: -0.2932 | I94: 0 | J94: 0 | K94: 0 | L94: 0 | M94: #DIV/0! | N94: #DIV/0! | O94: #DIV/0! | P94: 0 | S94: 0 | T94: 81 | U94: 20877 | V94: #DIV/0! | AC94: 流动修箱场
A95: 广州弘运 | B95: 高明珠江码头外包 | C95: 5 | D95: -1 | E95: 346.79 | F95: -0.2134 | G95: 69 | H95: -0.0548 | I95: 295.0086 | J95: 20 | K95: 10 | L95: 3620.2 | M95: 0.5157 | N95: 181 | O95: -0.2427 | P95: 0 | S95: 0 | T95: 25 | U95: 4262 | V95: #DIV/0!
A96: 浚得兴 | B96: 江门奔达码头 | C96: 20 | D96: -10 | E96: 8810.47 | F96: -0.3684 | G96: 441 | H96: -0.0516 | I96: 1100.068 | J96: 0 | K96: 0 | L96: 0 | M96: #DIV/0! | N96: #DIV/0! | O96: #DIV/0! | P96: 0 | S96: 0 | T96: 20 | U96: 9911 | V96: #DIV/0!
A97: 广州弘运 | B97: 黄埔集司 | C97: 0 | D97: 0 | E97: 0 | F97: #DIV/0! | G97: #DIV/0! | H97: #DIV/0! | I97: 0 | J97: 0 | K97: 0 | L97: 0 | M97: #DIV/0! | N97: #DIV/0! | O97: #DIV/0! | P97: 0 | S97: 0 | T97: 0 | U97: 0 | V97: #DIV/0! | AC97: OOCL外包业务
A98: 广州弘运 | B98: 肇庆三榕 | C98: 22 | D98: -24 | E98: 6025.97 | F98: -0.5129 | G98: 274 | H98: 0.0186 | I98: 1230.0664 | J98: 0 | K98: 0 | L98: 0 | M98: #DIV/0! | N98: #DIV/0! | O98: #DIV/0! | P98: 0 | S98: 0 | T98: 22 | U98: 7256 | V98: #DIV/0!
A99: 广州弘运 | B99: 新会亚太 | C99: 1 | D99: 1 | E99: 209.98 | F99: #DIV/0! | G99: 210 | H99: #DIV/0! | I99: 74.995 | J99: 0 | K99: 0 | L99: 0 | M99: #DIV/0! | N99: #DIV/0! | O99: #DIV/0! | P99: 0 | S99: 0 | T99: 1 | U99: 285 | V99: #DIV/0!
A100: 广州弘运 | B100: 防城港 | C100: 0 | D100: 0 | E100: 0 | F100: #DIV/0! | G100: #DIV/0! | H100: #DIV/0! | I100: 0 | J100: 0 | K100: 0 | L100: 0 | M100: #DIV/0! | N100: #DIV/0! | O100: #DIV/0! | P100: 0 | S100: 0 | T100: 0 | U100: 0 | V100: #DIV/0! | AC100: 关停，并给钦州弘运
...

Sheet 2026年第19周
A1: 单位汇总报表 | X1: 自营箱量完成情况
A2: 业务类型 | C2: 中远海干箱 | J2: 第三方干箱 | P2: 其它费用 | T2: 合计 | X2: 生产周期 | Z2: {=MID(_wpsfn.SHEETSNAME(Z2),7,2)} -> 19
A3: 部门/单位 | C3: 箱量 | D3: 环比 | E3: 产值 | F3: 环比 | G3: 单箱 | H3: 环比 | I3: 移箱费 | J3: 箱量 | K3: 环比 | L3: 产值 | M3: 环比 | N3: 单箱 | O3: 环比 | P3: 冷箱产值 | Q3: 堆场产值 | R3: 其它 | S3: 现金收费 | T3: 箱量 | U3: 产值 | V3: 人均产出 | W3: 人员数量 | X3: 周目标箱量 | Y3: 完成差额 | Z3: 合计目标箱量 | AA3: 合计完成量 | AB3: 合计完成差额
A4: 自营 | B4: 深圳运营中心 | C4: {=SUM((LOOKUP(ROW($45:$182),IF($A$45:$A$182<>"",ROW($45:$182)),$A$45:$A$182)=B4)*$C$45:$C$182)} -> 280 | D4: =C4-'2025年18周'!C4 -> -216 | E4: {=SUM((LOOKUP(ROW($45:$182),IF($A$45:$A$182<>"",ROW($45:$182)),$A$45:$A$182)=B4)*$E$45:$E$182)} -> 96025.08 | F4: =(E4-'2025年18周'!E4)/'2025年18周'!E4 -> -0.4757 | G4: =E4/C4 -> 342.95 | H4: =(G4-'2025年18周'!G4)/'2025年18周'!G4 -> -0.0713 | I4: {=SUM((LOOKUP(ROW($45:$182),IF($A$45:$A$182<>"",ROW($45:$182)),$A$45:$A$182)=B4)*$I$45:$I$182)} -> 0 | J4: {=SUM((LOOKUP(ROW($45:$182),IF($A$45:$A$182<>"",ROW($45:$182)),$A$45:$A$182)=B4)*$J$45:$J$182)} -> 64 | K4: =J4-'2025年18周'!J4 -> -67 | L4: {=SUM((LOOKUP(ROW($45:$182),IF($A$45:$A$182<>"",ROW($45:$182)),$A$45:$A$182)=B4)*$L$45:$L$182)} -> 17921 | M4: =(L4-'2025年18周'!L4)/'2025年18周'!L4 -> -0.6163 | N4: =L4/J4 -> 280.02 | O4: =(N4-'2025年18周'!N4)/'2025年18周'!N4 -> -0.2146 | P4: {=SUM((LOOKUP(ROW($45:$182),IF($A$45:$A$182<>"",ROW($45:$182)),$A$45:$A$182)=B4)*$P$45:$P$182)} -> 1190.32 | Q4: =SUMIFS(第19周周填报数据!D:D,第19周周填报数据!B:B,B4,第19周周填报数据!I:I,"堆场仓储板块") -> 101075.4 | R4: =SUMIFS(第19周周填报数据!D:D,第19周周填报数据!B:B,B4,第19周周填报数据!I:I,"<>堆场仓储板块") -> 510 | S4: 0 | T4: =C4+J4 -> 344 | U4: =E4+L4+I4+P4+Q4+R4+S4 -> 216721.8 | V4: =U4/W4 -> 5160 | W4: 42 | X4: 900 | Y4: =T4-X4 -> -556 | Z4: =X4*$Z$2 -> 17100 | AA4: =自营2026周完成情况!BB35 -> 10160 | AB4: =AA4-Z4 -> -6940
B5: 广州运营中心 | C5: {=SUM((LOOKUP(ROW($45:$182),IF($A$45:$A$182<>"",ROW($45:$182)),$A$45:$A$182)=B5)*$C$45:$C$182)} -> 2073 | D5: =C5-'2025年18周'!C5 -> -776 | E5: {=SUM((LOOKUP(ROW($45:$182),IF($A$45:$A$182<>"",ROW($45:$182)),$A$45:$A$182)=B5)*$E$45:$E$182)} -> 296138.23 | F5: =(E5-'2025年18周'!E5)/'2025年18周'!E5 -> -0.313 | G5: =E5/C5 -> 142.85 | H5: =(G5-'2025年18周'!G5)/'2025年18周'!G5 -> -0.0558 | I5: {=SUM((LOOKUP(ROW($45:$182),IF($A$45:$A$182<>"",ROW($45:$182)),$A$45:$A$182)=B5)*$I$45:$I$182)} -> 136132.76 | J5: {=SUM((LOOKUP(ROW($45:$182),IF($A$45:$A$182<>"",ROW($45:$182)),$A$45:$A$182)=B5)*$J$45:$J$182)} -> 66 | K5: =J5-'2025年18周'!J5 -> -82 | L5: {=SUM((LOOKUP(ROW($45:$182),IF($A$45:$A$182<>"",ROW($45:$182)),$A$45:$A$182)=B5)*$L$45:$L$182)} -> 15558 | M5: =(L5-'2025年18周'!L5)/'2025年18周'!L5 -> -0.6369 | N5: =L5/J5 -> 235.73 | O5: =(N5-'2025年18周'!N5)/'2025年18周'!N5 -> -0.1857 | P5: {=SUM((LOOKUP(ROW($45:$182),IF($A$45:$A$182<>"",ROW($45:$182)),$A$45:$A$182)=B5)*$P$45:$P$182)} -> 10865.54 | Q5: =SUMIFS(第19周周填报数据!D:D,第19周周填报数据!B:B,B5,第19周周填报数据!I:I,"堆场仓储板块") -> 0 | R5: =SUMIFS(第19周周填报数据!D:D,第19周周填报数据!B:B,B5,第19周周填报数据!I:I,"<>堆场仓储板块") -> 11120 | T5: =C5+J5 -> 2139 | U5: =E5+L5+I5+P5+Q5+R5+S5 -> 469814.53 | V5: =U5/W5 -> 14237 | W5: 33 | X5: 2500 | Y5: =T5-X5 -> -361 | Z5: =X5*$Z$2 -> 47500 | AA5: =自营2026周完成情况!BB36 -> 51345 | AB5: =AA5-Z5 -> 3845
B6: 珠三角运营中心 | C6: {=SUM((LOOKUP(ROW($45:$182),IF($A$45:$A$182<>"",ROW($45:$182)),$A$45:$A$182)=B6)*$C$45:$C$182)} -> 1431 | D6: =C6-'2025年18周'!C6 -> -853 | E6: {=SUM((LOOKUP(ROW($45:$182),IF($A$45:$A$182<>"",ROW($45:$182)),$A$45:$A$182)=B6)*$E$45:$E$182)} -> 329095.39 | F6: =(E6-'2025年18周'!E6)/'2025年18周'!E6 -> -0.3665 | G6: =E6/C6 -> 229.98 | H6: =(G6-'2025年18周'!G6)/'2025年18周'!G6 -> 0.0112 | I6: {=SUM((LOOKUP(ROW($45:$182),IF($A$45:$A$182<>"",ROW($45:$182)),$A$45:$A$182)=B6)*$I$45:$I$182)} -> 74382.256 | J6: {=SUM((LOOKUP(ROW($45:$182),IF($A$45:$A$182<>"",ROW($45:$182)),$A$45:$A$182)=B6)*$J$45:$J$182)} -> 40 | K6: =J6-'2025年18周'!J6 -> -209 | L6: {=SUM((LOOKUP(ROW($45:$182),IF($A$45:$A$182<>"",ROW($45:$182)),$A$45:$A$182)=B6)*$L$45:$L$182)} -> 15397 | M6: =(L6-'2025年18周'!L6)/'2025年18周'!L6 -> -0.8144 | N6: =L6/J6 -> 384.93 | O6: =(N6-'2025年18周'!N6)/'2025年18周'!N6 -> 0.1552 | P6: {=SUM((LOOKUP(ROW($45:$182),IF($A$45:$A$182<>"",ROW($45:$182)),$A$45:$A$182)=B6)*$P$45:$P$182)} -> 0 | Q6: =SUMIFS(第19周周填报数据!D:D,第19周周填报数据!B:B,B6,第19周周填报数据!I:I,"堆场仓储板块") -> 6882 | R6: =SUMIFS(第19周周填报数据!D:D,第19周周填报数据!B:B,B6,第19周周填报数据!I:I,"<>堆场仓储板块") -> 0 | T6: =C6+J6 -> 1471 | U6: =E6+L6+I6+P6+Q6+R6+S6 -> 425756.65 | V6: =U6/W6 -> 7341 | W6: 58 | X6: 3000 | Y6: =T6-X6 -> -1529 | Z6: =X6*$Z$2 -> 57000 | AA6: =自营2026周完成情况!BB37 -> 38596 | AB6: =AA6-Z6 -> -18404
B7: 粤西运营中心 | C7: {=SUM((LOOKUP(ROW($45:$182),IF($A$45:$A$182<>"",ROW($45:$182)),$A$45:$A$182)=B7)*$C$45:$C$182)} -> 1038 | D7: =C7-'2025年18周'!C7 -> -293 | E7: {=SUM((LOOKUP(ROW($45:$182),IF($A$45:$A$182<>"",ROW($45:$182)),$A$45:$A$182)=B7)*$E$45:$E$182)} -> 215642.55 | F7: =(E7-'2025年18周'!E7)/'2025年18周'!E7 -> -0.3846 | G7: =E7/C7 -> 207.75 | H7: =(G7-'2025年18周'!G7)/'2025年18周'!G7 -> -0.2109 | I7: {=SUM((LOOKUP(ROW($45:$182),IF($A$45:$A$182<>"",ROW($45:$182)),$A$45:$A$182)=B7)*$I$45:$I$182)} -> 47005.053 | J7: {=SUM((LOOKUP(ROW($45:$182),IF($A$45:$A$182<>"",ROW($45:$182)),$A$45:$A$182)=B7)*$J$45:$J$182)} -> 96 | K7: =J7-'2025年18周'!J7 -> 53 | L7: {=SUM((LOOKUP(ROW($45:$182),IF($A$45:$A$182<>"",ROW($45:$182)),$A$45:$A$182)=B7)*$L$45:$L$182)} -> 17220 | M7: =(L7-'2025年18周'!L7)/'2025年18周'!L7 -> 0.4061 | N7: =L7/J7 -> 179.38 | O7: =(N7-'2025年18周'!N7)/'2025年18周'!N7 -> -0.3702 | P7: {=SUM((LOOKUP(ROW($45:$182),IF($A$45:$A$182<>"",ROW($45:$182)),$A$45:$A$182)=B7)*$P$45:$P$182)} -> 749.89 | Q7: =SUMIFS(第19周周填报数据!D:D,第19周周填报数据!B:B,B7,第19周周填报数据!I:I,"堆场仓储板块") -> 7155.66 | R7: =SUMIFS(第19周周填报数据!D:D,第19周周填报数据!B:B,B7,第19周周填报数据!I:I,"<>堆场仓储板块") -> 10505 | T7: =C7+J7 -> 1134 | U7: =E7+L7+I7+P7+Q7+R7+S7 -> 298278.15 | V7: =U7/W7 -> 14204 | W7: 21 | X7: 1100 | Y7: =T7-X7 -> 34 | Z7: =X7*$Z$2 -> 20900 | AA7: =自营2026周完成情况!BB38 -> 24386 | AB7: =AA7-Z7 -> 3486
B8: 北部湾运营中心 | C8: {=SUM((LOOKUP(ROW($45:$182),IF($A$45:$A$182<>"",ROW($45:$182)),$A$45:$A$182)=B8)*$C$45:$C$182)} -> 1535 | D8: =C8-'2025年18周'!C8 -> -422 | E8: {=SUM((LOOKUP(ROW($45:$182),IF($A$45:$A$182<>"",ROW($45:$182)),$A$45:$A$182)=B8)*$E$45:$E$182)} -> 451210.96 | F8: =(E8-'2025年18周'!E8)/'2025年18周'!E8 -> -0.2819 | G8: =E8/C8 -> 293.95 | H8: =(G8-'2025年18周'!G8)/'2025年18周'!G8 -> -0.0845 | I8: {=SUM((LOOKUP(ROW($45:$182),IF($A$45:$A$182<>"",ROW($45:$182)),$A$45:$A$182)=B8)*$I$45:$I$182)} -> 2035.1258 | J8: {=SUM((LOOKUP(ROW($45:$182),IF($A$45:$A$182<>"",ROW($45:$182)),$A$45:$A$182)=B8)*$J$45:$J$182)} -> 15 | K8: =J8-'2025年18周'!J8 -> 1 | L8: {=SUM((LOOKUP(ROW($45:$182),IF($A$45:$A$182<>"",ROW($45:$182)),$A$45:$A$182)=B8)*$L$45:$L$182)} -> 5543 | M8: =(L8-'2025年18周'!L8)/'2025年18周'!L8 -> 1.1712 | N8: =L8/J8 -> 369.53 | O8: =(N8-'2025年18周'!N8)/'2025年18周'!N8 -> 1.0264 | P8: {=SUM((LOOKUP(ROW($45:$182),IF($A$45:$A$182<>"",ROW($45:$182)),$A$45:$A$182)=B8)*$P$45:$P$182)} -> 0 | Q8: =SUMIFS(第19周周填报数据!D:D,第19周周填报数据!B:B,B8,第19周周填报数据!I:I,"堆场仓储板块") -> 69338 | R8: =SUMIFS(第19周周填报数据!D:D,第19周周填报数据!B:B,B8,第19周周填报数据!I:I,"<>堆场仓储板块") -> 10395 | T8: =C8+J8 -> 1550 | U8: =E8+L8+I8+P8+Q8+R8+S8 -> 538522.09 | V8: =U8/W8 -> 16829 | W8: 32 | X8: 1500 | Y8: =T8-X8 -> 50 | Z8: =X8*$Z$2 -> 28500 | AA8: =自营2026周完成情况!BB39 -> 39046 | AB8: =AA8-Z8 -> 10546
B9: 南岗分公司 | C9: {=SUM((LOOKUP(ROW($45:$182),IF($A$45:$A$182<>"",ROW($45:$182)),$A$45:$A$182)=B9)*$C$45:$C$182)} -> 150 | D9: =C9-'2025年18周'!C9 -> -96 | E9: {=SUM((LOOKUP(ROW($45:$182),IF($A$45:$A$182<>"",ROW($45:$182)),$A$45:$A$182)=B9)*$E$45:$E$182)} -> 32503.36 | F9: =(E9-'2025年18周'!E9)/'2025年18周'!E9 -> -0.2248 | G9: =E9/C9 -> 216.69 | H9: =(G9-'2025年18周'!G9)/'2025年18周'!G9 -> 0.2714 | I9: {=SUM((LOOKUP(ROW($45:$182),IF($A$45:$A$182<>"",ROW($45:$182)),$A$45:$A$182)=B9)*$I$45:$I$182)} -> 5689.9952 | J9: {=SUM((LOOKUP(ROW($45:$182),IF($A$45:$A$182<>"",ROW($45:$182)),$A$45:$A$182)=B9)*$J$45:$J$182)} -> 40 | K9: =J9-'2025年18周'!J9 -> -382 | L9: {=SUM((LOOKUP(ROW($45:$182),IF($A$45:$A$182<>"",ROW($45:$182)),$A$45:$A$182)=B9)*$L$45:$L$182)} -> 12625 | M9: =(L9-'2025年18周'!L9)/'2025年18周'!L9 -> -0.7518 | N9: =L9/J9 -> 315.63 | O9: =(N9-'2025年18周'!N9)/'2025年18周'!N9 -> 1.6182 | P9: {=SUM((LOOKUP(ROW($45:$182),IF($A$45:$A$182<>"",ROW($45:$182)),$A$45:$A$182)=B9)*$P$45:$P$182)} -> 728.33 | Q9: =SUMIFS(第19周周填报数据!D:D,第19周周填报数据!B:B,B9,第19周周填报数据!I:I,"堆场仓储板块")+SUMIFS(第19周周填报数据!D:D,第19周周填报数据!B:B,"市场部拆装箱",第19周周填报数据!I:I,"堆场仓储板块") -> 48988 | R9: =SUMIFS(第19周周填报数据!D:D,第19周周填报数据!B:B,B9,第19周周填报数据!I:I,"<>堆场仓储板块")+SUMIFS(第19周周填报数据!D:D,第19周周填报数据!B:B,"市场部拆装箱",第19周周填报数据!I:I,"<>堆场仓储板块") -> 121715 | S9: 0 | T9: =C9+J9 -> 190 | U9: =E9+L9+I9+P9+Q9+R9+S9 -> 222249.69 | V9: =U9/W9 -> 12347 | W9: 18 | X9: 600 | Y9: =T9-X9 -> -410 | Z9: =X9*$Z$2 -> 11400 | AA9: =自营2026周完成情况!BB40 -> 11367 | AB9: =AA9-Z9 -> -33
B10: 自营总计 | C10: =SUM(C4:C9) -> 6507 | D10: =C10-'2025年18周'!C10 -> -2656 | E10: =SUM(E4:E9) -> 1420615.6 | F10: =(E10-'2025年18周'!E10)/'2025年18周'!E10 -> -0.3406 | G10: =E10/C10 -> 218.32 | H10: =(G10-'2025年18周'!G10)/'2025年18周'!G10 -> -0.0714 | I10: =SUM(I4:I9) -> 265245.19 | J10: =SUM(J4:J9) -> 321 | K10: =J10-'2025年18周'!J10 -> -686 | L10: =SUM(L4:L9) -> 84264 | M10: =(L10-'2025年18周'!L10)/'2025年18周'!L10 -> -0.6462 | N10: =L10/J10 -> 262.5 | O10: =(N10-'2025年18周'!N10)/'2025年18周'!N10 -> 0.1097 | P10: =SUM(P4:P9) -> 13534.08 | Q10: =SUM(Q4:Q9) -> 233439.06 | R10: =SUM(R4:R9) -> 154245 | S10: =SUM(S4:S9) -> 0 | T10: =SUM(T4:T9) -> 6828 | U10: =SUM(U4:U9) -> 2171342.9 | V10: =U10/W10 -> 10644 | W10: =SUM(W4:W9) -> 204 | X10: 9600 | Y10: =T10-X10 -> -2772 | Z10: =SUM(Z4:Z9) -> 182400 | AA10: =自营2026周完成情况!BB41 -> 174900 | AB10: =AA10-Z10 -> -7500
A11: 合作供应商 | B11: 广州弘运 | C11: {=SUM((LOOKUP(ROW($45:$182),IF($A$45:$A$182<>"",ROW($45:$182)),$A$45:$A$182)=B11)*$C$45:$C$182)} -> 1360 | D11: =C11-'2025年18周'!C11 -> -1152 | E11: {=SUM((LOOKUP(ROW($45:$182),IF($A$45:$A$182<>"",ROW($45:$182)),$A$45:$A$182)=B11)*$E$45:$E$182)} -> 336980.69 | F11: =(E11-'2025年18周'!E11)/'2025年18周'!E11 -> -0.5242 | G11: =E11/C11 -> 247.78 | H11: =(G11-'2025年18周'!G11)/'2025年18周'!G11 -> -0.1213 | I11: {=SUM((LOOKUP(ROW($45:$182),IF($A$45:$A$182<>"",ROW($45:$182)),$A$45:$A$182)=B11)*$I$45:$I$182)} -> 49615.6 | J11: {=SUM((LOOKUP(ROW($45:$182),IF($A$45:$A$182<>"",ROW($45:$182)),$A$45:$A$182)=B11)*$J$45:$J$182)} -> 0 | K11: =J11-'2025年18周'!J11 -> -20 | L11: {=SUM((LOOKUP(ROW($45:$182),IF($A$45:$A$182<>"",ROW($45:$182)),$A$45:$A$182)=B11)*$L$45:$L$182)} -> 0 | M11: =(L11-'2025年18周'!L11)/'2025年18周'!L11 -> -1 | N11: =L11/J11 -> #DIV/0! | O11: =(N11-'2025年18周'!N11)/'2025年18周'!N11 -> #DIV/0! | P11: {=SUM((LOOKUP(ROW($45:$182),IF($A$45:$A$182<>"",ROW($45:$182)),$A$45:$A$182)=B11)*$P$45:$P$182)} -> 8684.86 | T11: =C11+J11 -> 1360 | U11: =E11+L11+I11+P11+Q11+R11+S11 -> 395281.15
B12: 钦州弘运 | C12: {=SUM((LOOKUP(ROW($45:$182),IF($A$45:$A$182<>"",ROW($45:$182)),$A$45:$A$182)=B12)*$C$45:$C$182)} -> 706 | D12: =C12-'2025年18周'!C12 -> 8 | E12: {=SUM((LOOKUP(ROW($45:$182),IF($A$45:$A$182<>"",ROW($45:$182)),$A$45:$A$182)=B12)*$E$45:$E$182)} -> 180154.38 | F12: =(E12-'2025年18周'!E12)/'2025年18周'!E12 -> 0.1154 | G12: =E12/C12 -> 255.18 | H12: =(G12-'2025年18周'!G12)/'2025年18周'!G12 -> 0.1028 | I12: {=SUM((LOOKUP(ROW($45:$182),IF($A$45:$A$182<>"",ROW($45:$182)),$A$45:$A$182)=B12)*$I$45:$I$182)} -> 27416.656 | J12: {=SUM((LOOKUP(ROW($45:$182),IF($A$45:$A$182<>"",ROW($45:$182)),$A$45:$A$182)=B12)*$J$45:$J$182)} -> 9 | K12: =J12-'2025年18周'!J12 -> 5 | L12: {=SUM((LOOKUP(ROW($45:$182),IF($A$45:$A$182<>"",ROW($45:$182)),$A$45:$A$182)=B12)*$L$45:$L$182)} -> 3734 | M12: =(L12-'2025年18周'!L12)/'2025年18周'!L12 -> 0.8783 | N12: =L12/J12 -> 414.89 | O12: =(N12-'2025年18周'!N12)/'2025年18周'!N12 -> -0.1652 | P12: {=SUM((LOOKUP(ROW($45:$182),IF($A$45:$A$182<>"",ROW($45:$182)),$A$45:$A$182)=B12)*$P$45:$P$182)} -> 158.6 | T12: =C12+J12 -> 715 | U12: =E12+L12+I12+P12+Q12+R12+S12 -> 211463.64
B13: 弘运天浩 | C13: {=SUM((LOOKUP(ROW($45:$182),IF($A$45:$A$182<>"",ROW($45:$182)),$A$45:$A$182)=B13)*$C$45:$C$182)} -> 478 | D13: =C13-'2025年18周'!C13 -> -139 | E13: {=SUM((LOOKUP(ROW($45:$182),IF($A$45:$A$182<>"",ROW($45:$182)),$A$45:$A$182)=B13)*$E$45:$E$182)} -> 63454.18 | F13: =(E13-'2025年18周'!E13)/'2025年18周'!E13 -> -0.5239 | G13: =E13/C13 -> 132.75 | H13: =(G13-'2025年18周'!G13)/'2025年18周'!G13 -> -0.3855 | I13: {=SUM((LOOKUP(ROW($45:$182),IF($A$45:$A$182<>"",ROW($45:$182)),$A$45:$A$182)=B13)*$I$45:$I$182)} -> 30169.996 | J13: {=SUM((LOOKUP(ROW($45:$182),IF($A$45:$A$182<>"",ROW($45:$182)),$A$45:$A$182)=B13)*$J$45:$J$182)} -> 4 | K13: =J13-'2025年18周'!J13 -> -47 | L13: {=SUM((LOOKUP(ROW($45:$182),IF($A$45:$A$182<>"",ROW($45:$182)),$A$45:$A$182)=B13)*$L$45:$L$182)} -> 1039 | M13: =(L13-'2025年18周'!L13)/'2025年18周'!L13 -> -0.9227 | N13: =L13/J13 -> 259.75 | O13: =(N13-'2025年18周'!N13)/'2025年18周'!N13 -> -0.015 | P13: {=SUM((LOOKUP(ROW($45:$182),IF($A$45:$A$182<>"",ROW($45:$182)),$A$45:$A$182)=B13)*$P$45:$P$182)} -> 0 | T13: =C13+J13 -> 482 | U13: =E13+L13+I13+P13+Q13+R13+S13 -> 94663.18
B14: 万年红 | C14: {=SUM((LOOKUP(ROW($45:$182),IF($A$45:$A$182<>"",ROW($45:$182)),$A$45:$A$182)=B14)*$C$45:$C$182)} -> 295 | D14: =C14-'2025年18周'!C14 -> -45 | E14: {=SUM((LOOKUP(ROW($45:$182),IF($A$45:$A$182<>"",ROW($45:$182)),$A$45:$A$182)=B14)*$E$45:$E$182)} -> 28237.5 | F14: =(E14-'2025年18周'!E14)/'2025年18周'!E14 -> -0.4264 | G14: =E14/C14 -> 95.72 | H14: =(G14-'2025年18周'!G14)/'2025年18周'!G14 -> -0.3389 | I14: {=SUM((LOOKUP(ROW($45:$182),IF($A$45:$A$182<>"",ROW($45:$182)),$A$45:$A$182)=B14)*$I$45:$I$182)} -> 18624.995 | J14: {=SUM((LOOKUP(ROW($45:$182),IF($A$45:$A$182<>"",ROW($45:$182)),$A$45:$A$182)=B14)*$J$45:$J$182)} -> 0 | K14: =J14-'2025年18周'!J14 -> 0 | L14: {=SUM((LOOKUP(ROW($45:$182),IF($A$45:$A$182<>"",ROW($45:$182)),$A$45:$A$182)=B14)*$L$45:$L$182)} -> 0 | M14: =(L14-'2025年18周'!L14)/'2025年18周'!L14 -> #DIV/0! | N14: =L14/J14 -> #DIV/0! | O14: =(N14-'2025年18周'!N14)/'2025年18周'!N14 -> #DIV/0! | P14: {=SUM((LOOKUP(ROW($45:$182),IF($A$45:$A$182<>"",ROW($45:$182)),$A$45:$A$182)=B14)*$P$45:$P$182)} -> 0 | T14: =C14+J14 -> 295 | U14: =E14+L14+I14+P14+Q14+R14+S14 -> 46862.5
B15: 裕丰 | C15: {=SUM((LOOKUP(ROW($45:$182),IF($A$45:$A$182<>"",ROW($45:$182)),$A$45:$A$182)=B15)*$C$45:$C$182)} -> 313 | D15: =C15-'2025年18周'!C15 -> -13 | E15: {=SUM((LOOKUP(ROW($45:$182),IF($A$45:$A$182<>"",ROW($45:$182)),$A$45:$A$182)=B15)*$E$45:$E$182)} -> 70417.13 | F15: =(E15-'2025年18周'!E15)/'2025年18周'!E15 -> -0.0661 | G15: =E15/C15 -> 224.97 | H15: =(G15-'2025年18周'!G15)/'2025年18周'!G15 -> -0.0273 | I15: {=SUM((LOOKUP(ROW($45:$182),IF($A$45:$A$182<>"",ROW($45:$182)),$A$45:$A$182)=B15)*$I$45:$I$182)} -> 17575.913 | J15: {=SUM((LOOKUP(ROW($45:$182),IF($A$45:$A$182<>"",ROW($45:$182)),$A$45:$A$182)=B15)*$J$45:$J$182)} -> 0 | K15: =J15-'2025年18周'!J15 -> 0 | L15: {=SUM((LOOKUP(ROW($45:$182),IF($A$45:$A$182<>"",ROW($45:$182)),$A$45:$A$182)=B15)*$L$45:$L$182)} -> 0 | M15: =(L15-'2025年18周'!L15)/'2025年18周'!L15 -> #DIV/0! | N15: =L15/J15 -> #DIV/0! | O15: =(N15-'2025年18周'!N15)/'2025年18周'!N15 -> #DIV/0! | P15: {=SUM((LOOKUP(ROW($45:$182),IF($A$45:$A$182<>"",ROW($45:$182)),$A$45:$A$182)=B15)*$P$45:$P$182)} -> 0 | T15: =C15+J15 -> 313 | U15: =E15+L15+I15+P15+Q15+R15+S15 -> 87993.04
B16: 本港 | C16: {=SUM((LOOKUP(ROW($45:$182),IF($A$45:$A$182<>"",ROW($45:$182)),$A$45:$A$182)=B16)*$C$45:$C$182)} -> 18 | D16: =C16-'2025年18周'!C16 -> 0 | E16: {=SUM((LOOKUP(ROW($45:$182),IF($A$45:$A$182<>"",ROW($45:$182)),$A$45:$A$182)=B16)*$E$45:$E$182)} -> 7671.77 | F16: =(E16-'2025年18周'!E16)/'2025年18周'!E16 -> 1.0272 | G16: =E16/C16 -> 426.21 | H16: =(G16-'2025年18周'!G16)/'2025年18周'!G16 -> 1.0273 | I16: {=SUM((LOOKUP(ROW($45:$182),IF($A$45:$A$182<>"",ROW($45:$182)),$A$45:$A$182)=B16)*$I$45:$I$182)} -> 1090.0192 | J16: {=SUM((LOOKUP(ROW($45:$182),IF($A$45:$A$182<>"",ROW($45:$182)),$A$45:$A$182)=B16)*$J$45:$J$182)} -> 0 | K16: =J16-'2025年18周'!J16 -> 0 | L16: {=SUM((LOOKUP(ROW($45:$182),IF($A$45:$A$182<>"",ROW($45:$182)),$A$45:$A$182)=B16)*$L$45:$L$182)} -> 0 | M16: =(L16-'2025年18周'!L16)/'2025年18周'!L16 -> #DIV/0! | N16: =L16/J16 -> #DIV/0! | O16: =(N16-'2025年18周'!N16)/'2025年18周'!N16 -> #DIV/0! | P16: {=SUM((LOOKUP(ROW($45:$182),IF($A$45:$A$182<>"",ROW($45:$182)),$A$45:$A$182)=B16)*$P$45:$P$182)} -> 0 | T16: =C16+J16 -> 18 | U16: =E16+L16+I16+P16+Q16+R16+S16 -> 8761.79
B17: 坚迅 | C17: {=SUM((LOOKUP(ROW($45:$182),IF($A$45:$A$182<>"",ROW($45:$182)),$A$45:$A$182)=B17)*$C$45:$C$182)} -> 722 | D17: =C17-'2025年18周'!C17 -> 2 | E17: {=SUM((LOOKUP(ROW($45:$182),IF($A$45:$A$182<>"",ROW($45:$182)),$A$45:$A$182)=B17)*$E$45:$E$182)} -> 206348.91 | F17: =(E17-'2025年18周'!E17)/'2025年18周'!E17 -> 0.0563 | G17: =E17/C17 -> 285.8 | H17: =(G17-'2025年18周'!G17)/'2025年18周'!G17 -> 0.0533 | I17: {=SUM((LOOKUP(ROW($45:$182),IF($A$45:$A$182<>"",ROW($45:$182)),$A$45:$A$182)=B17)*$I$45:$I$182)} -> 52706.995 | J17: {=SUM((LOOKUP(ROW($45:$182),IF($A$45:$A$182<>"",ROW($45:$182)),$A$45:$A$182)=B17)*$J$45:$J$182)} -> 0 | K17: =J17-'2025年18周'!J17 -> -3 | L17: {=SUM((LOOKUP(ROW($45:$182),IF($A$45:$A$182<>"",ROW($45:$182)),$A$45:$A$182)=B17)*$L$45:$L$182)} -> 0 | M17: =(L17-'2025年18周'!L17)/'2025年18周'!L17 -> -1 | N17: =L17/J17 -> #DIV/0! | O17: =(N17-'2025年18周'!N17)/'2025年18周'!N17 -> #DIV/0! | P17: {=SUM((LOOKUP(ROW($45:$182),IF($A$45:$A$182<>"",ROW($45:$182)),$A$45:$A$182)=B17)*$P$45:$P$182)} -> 0 | T17: =C17+J17 -> 722 | U17: =E17+L17+I17+P17+Q17+R17+S17 -> 259055.9
B18: 浚得兴 | C18: {=SUM((LOOKUP(ROW($45:$182),IF($A$45:$A$182<>"",ROW($45:$182)),$A$45:$A$182)=B18)*$C$45:$C$182)} -> 576 | D18: =C18-'2025年18周'!C18 -> -67 | E18: {=SUM((LOOKUP(ROW($45:$182),IF($A$45:$A$182<>"",ROW($45:$182)),$A$45:$A$182)=B18)*$E$45:$E$182)} -> 158850.28 | F18: =(E18-'2025年18周'!E18)/'2025年18周'!E18 -> -0.1194 | G18: =E18/C18 -> 275.78 | H18: =(G18-'2025年18周'!G18)/'2025年18周'!G18 -> -0.017 | I18: {=SUM((LOOKUP(ROW($45:$182),IF($A$45:$A$182<>"",ROW($45:$182)),$A$45:$A$182)=B18)*$I$45:$I$182)} -> 34420.808 | J18: {=SUM((LOOKUP(ROW($45:$182),IF($A$45:$A$182<>"",ROW($45:$182)),$A$45:$A$182)=B18)*$J$45:$J$182)} -> 0 | K18: =J18-'2025年18周'!J18 -> 0 | L18: {=SUM((LOOKUP(ROW($45:$182),IF($A$45:$A$182<>"",ROW($45:$182)),$A$45:$A$182)=B18)*$L$45:$L$182)} -> 0 | M18: =(L18-'2025年18周'!L18)/'2025年18周'!L18 -> #DIV/0! | N18: =L18/J18 -> #DIV/0! | O18: =(N18-'2025年18周'!N18)/'2025年18周'!N18 -> #DIV/0! | P18: {=SUM((LOOKUP(ROW($45:$182),IF($A$45:$A$182<>"",ROW($45:$182)),$A$45:$A$182)=B18)*$P$45:$P$182)} -> 0 | T18: =C18+J18 -> 576 | U18: =E18+L18+I18+P18+Q18+R18+S18 -> 193271.09
B19: 深圳天河 | C19: {=SUM((LOOKUP(ROW($45:$182),IF($A$45:$A$182<>"",ROW($45:$182)),$A$45:$A$182)=B19)*$C$45:$C$182)} -> 0 | D19: =C19-'2025年18周'!C19 -> -5 | E19: {=SUM((LOOKUP(ROW($45:$182),IF($A$45:$A$182<>"",ROW($45:$182)),$A$45:$A$182)=B19)*$E$45:$E$182)} -> 0 | F19: =(E19-'2025年18周'!E19)/'2025年18周'!E19 -> -1 | G19: =E19/C19 -> #DIV/0! | H19: =(G19-'2025年18周'!G19)/'2025年18周'!G19 -> #DIV/0! | I19: {=SUM((LOOKUP(ROW($45:$182),IF($A$45:$A$182<>"",ROW($45:$182)),$A$45:$A$182)=B19)*$I$45:$I$182)} -> 0 | J19: {=SUM((LOOKUP(ROW($45:$182),IF($A$45:$A$182<>"",ROW($45:$182)),$A$45:$A$182)=B19)*$J$45:$J$182)} -> 0 | K19: =J19-'2025年18周'!J19 -> 0 | L19: {=SUM((LOOKUP(ROW($45:$182),IF($A$45:$A$182<>"",ROW($45:$182)),$A$45:$A$182)=B19)*$L$45:$L$182)} -> 0 | M19: =(L19-'2025年18周'!L19)/'2025年18周'!L19 -> #DIV/0! | N19: =L19/J19 -> #DIV/0! | O19: =(N19-'2025年18周'!N19)/'2025年18周'!N19 -> #DIV/0! | P19: {=SUM((LOOKUP(ROW($45:$182),IF($A$45:$A$182<>"",ROW($45:$182)),$A$45:$A$182)=B19)*$P$45:$P$182)} -> 0 | T19: =C19+J19 -> 0 | U19: =E19+L19+I19+P19+Q19+R19+S19 -> 0
B20: 信步 | C20: {=SUM((LOOKUP(ROW($45:$182),IF($A$45:$A$182<>"",ROW($45:$182)),$A$45:$A$182)=B20)*$C$45:$C$182)} -> 497 | D20: =C20-'2025年18周'!C20 -> -286 | E20: {=SUM((LOOKUP(ROW($45:$182),IF($A$45:$A$182<>"",ROW($45:$182)),$A$45:$A$182)=B20)*$E$45:$E$182)} -> 84757.71 | F20: =(E20-'2025年18周'!E20)/'2025年18周'!E20 -> -0.3618 | G20: =E20/C20 -> 170.54 | H20: =(G20-'2025年18周'!G20)/'2025年18周'!G20 -> 0.0054 | I20: {=SUM((LOOKUP(ROW($45:$182),IF($A$45:$A$182<>"",ROW($45:$182)),$A$45:$A$182)=B20)*$I$45:$I$182)} -> 28856.051 | J20: {=SUM((LOOKUP(ROW($45:$182),IF($A$45:$A$182<>"",ROW($45:$182)),$A$45:$A$182)=B20)*$J$45:$J$182)} -> 10 | K20: =J20-'2025年18周'!J20 -> -1 | L20: {=SUM((LOOKUP(ROW($45:$182),IF($A$45:$A$182<>"",ROW($45:$182)),$A$45:$A$182)=B20)*$L$45:$L$182)} -> 3100 | M20: =(L20-'2025年18周'!L20)/'2025年18周'!L20 -> -0.1077 | N20: =L20/J20 -> 310 | O20: =(N20-'2025年18周'!N20)/'2025年18周'!N20 -> -0.0184 | P20: {=SUM((LOOKUP(ROW($45:$182),IF($A$45:$A$182<>"",ROW($45:$182)),$A$45:$A$182)=B20)*$P$45:$P$182)} -> 0 | T20: =C20+J20 -> 507 | U20: =E20+L20+I20+P20+Q20+R20+S20 -> 116713.76
B21: 万永联 | C21: {=SUM((LOOKUP(ROW($45:$182),IF($A$45:$A$182<>"",ROW($45:$182)),$A$45:$A$182)=B21)*$C$45:$C$182)} -> 94 | D21: =C21-'2025年18周'!C21 -> -67 | E21: {=SUM((LOOKUP(ROW($45:$182),IF($A$45:$A$182<>"",ROW($45:$182)),$A$45:$A$182)=B21)*$E$45:$E$182)} -> 15637.99 | F21: =(E21-'2025年18周'!E21)/'2025年18周'!E21 -> -0.4488 | G21: =E21/C21 -> 166.36 | H21: =(G21-'2025年18周'!G21)/'2025年18周'!G21 -> -0.056 | I21: {=SUM((LOOKUP(ROW($45:$182),IF($A$45:$A$182<>"",ROW($45:$182)),$A$45:$A$182)=B21)*$I$45:$I$182)} -> 0 | J21: {=SUM((LOOKUP(ROW($45:$182),IF($A$45:$A$182<>"",ROW($45:$182)),$A$45:$A$182)=B21)*$J$45:$J$182)} -> 0 | K21: =J21-'2025年18周'!J21 -> 0 | L21: {=SUM((LOOKUP(ROW($45:$182),IF($A$45:$A$182<>"",ROW($45:$182)),$A$45:$A$182)=B21)*$L$45:$L$182)} -> 0 | M21: =(L21-'2025年18周'!L21)/'2025年18周'!L21 -> #DIV/0! | N21: =L21/J21 -> #DIV/0! | O21: =(N21-'2025年18周'!N21)/'2025年18周'!N21 -> #DIV/0! | P21: {=SUM((LOOKUP(ROW($45:$182),IF($A$45:$A$182<>"",ROW($45:$182)),$A$45:$A$182)=B21)*$P$45:$P$182)} -> 0 | T21: =C21+J21 -> 94 | U21: =E21+L21+I21+P21+Q21+R21+S21 -> 15637.99
B22: 辉成 | C22: {=SUM((LOOKUP(ROW($45:$182),IF($A$45:$A$182<>"",ROW($45:$182)),$A$45:$A$182)=B22)*$C$45:$C$182)} -> 133 | D22: =C22-'2025年18周'!C22 -> -64 | E22: {=SUM((LOOKUP(ROW($45:$182),IF($A$45:$A$182<>"",ROW($45:$182)),$A$45:$A$182)=B22)*$E$45:$E$182)} -> 25832.76 | F22: =(E22-'2025年18周'!E22)/'2025年18周'!E22 -> -0.381 | G22: =E22/C22 -> 194.23 | H22: =(G22-'2025年18周'!G22)/'2025年18周'!G22 -> -0.0831 | I22: {=SUM((LOOKUP(ROW($45:$182),IF($A$45:$A$182<>"",ROW($45:$182)),$A$45:$A$182)=B22)*$I$45:$I$182)} -> 7995.1666 | J22: {=SUM((LOOKUP(ROW($45:$182),IF($A$45:$A$182<>"",ROW($45:$182)),$A$45:$A$182)=B22)*$J$45:$J$182)} -> 0 | K22: =J22-'2025年18周'!J22 -> 0 | L22: {=SUM((LOOKUP(ROW($45:$182),IF($A$45:$A$182<>"",ROW($45:$182)),$A$45:$A$182)=B22)*$L$45:$L$182)} -> 0 | M22: =(L22-'2025年18周'!L22)/'2025年18周'!L22 -> #DIV/0! | N22: =L22/J22 -> #DIV/0! | O22: =(N22-'2025年18周'!N22)/'2025年18周'!N22 -> #DIV/0! | P22: {=SUM((LOOKUP(ROW($45:$182),IF($A$45:$A$182<>"",ROW($45:$182)),$A$45:$A$182)=B22)*$P$45:$P$182)} -> 0 | T22: =C22+J22 -> 133 | U22: =E22+L22+I22+P22+Q22+R22+S22 -> 33827.93
B23: 万建达 | C23: {=SUM((LOOKUP(ROW($45:$182),IF($A$45:$A$182<>"",ROW($45:$182)),$A$45:$A$182)=B23)*$C$45:$C$182)} -> 329 | D23: =C23-'2025年18周'!C23 -> -412 | E23: {=SUM((LOOKUP(ROW($45:$182),IF($A$45:$A$182<>"",ROW($45:$182)),$A$45:$A$182)=B23)*$E$45:$E$182)} -> 117602.03 | F23: =(E23-'2025年18周'!E23)/'2025年18周'!E23 -> -0.5767 | G23: =E23/C23 -> 357.45 | H23: =(G23-'2025年18周'!G23)/'2025年18周'!G23 -> -0.0465 | I23: {=SUM((LOOKUP(ROW($45:$182),IF($A$45:$A$182<>"",ROW($45:$182)),$A$45:$A$182)=B23)*$I$45:$I$182)} -> 0 | J23: {=SUM((LOOKUP(ROW($45:$182),IF($A$45:$A$182<>"",ROW($45:$182)),$A$45:$A$182)=B23)*$J$45:$J$182)} -> 0 | K23: =J23-'2025年18周'!J23 -> 0 | L23: {=SUM((LOOKUP(ROW($45:$182),IF($A$45:$A$182<>"",ROW($45:$182)),$A$45:$A$182)=B23)*$L$45:$L$182)} -> 0 | M23: =(L23-'2025年18周'!L23)/'2025年18周'!L23 -> #DIV/0! | N23: =L23/J23 -> #DIV/0! | O23: =(N23-'2025年18周'!N23)/'2025年18周'!N23 -> #DIV/0! | P23: {=SUM((LOOKUP(ROW($45:$182),IF($A$45:$A$182<>"",ROW($45:$182)),$A$45:$A$182)=B23)*$P$45:$P$182)} -> 0 | T23: =C23+J23 -> 329 | U23: =E23+L23+I23+P23+Q23+R23+S23 -> 117602.03
... B34: 港信 | C34: {=SUM((LOOKUP(ROW($45:$182),IF($A$45:$A$182<>"",ROW($45:$182)),$A$45:$A$182)=B34)*$C$45:$C$182)} -> 46 | D34: =C34-'2025年18周'!C34 -> -20 | E34: {=SUM((LOOKUP(ROW($45:$182),IF($A$45:$A$182<>"",ROW($45:$182)),$A$45:$A$182)=B34)*$E$45:$E$182)} -> 7821.98 | F34: =(E34-'2025年18周'!E34)/'2025年18周'!E34 -> -0.6104 | G34: =E34/C34 -> 170.04 | H34: =(G34-'2025年18周'!G34)/'2025年18周'!G34 -> -0.441 | I34: {=SUM((LOOKUP(ROW($45:$182),IF($A$45:$A$182<>"",ROW($45:$182)),$A$45:$A$182)=B34)*$I$45:$I$182)} -> 2790.0472 | J34: {=SUM((LOOKUP(ROW($45:$182),IF($A$45:$A$182<>"",ROW($45:$182)),$A$45:$A$182)=B34)*$J$45:$J$182)} -> 0 | K34: =J34-'2025年18周'!J34 -> 0 | L34: {=SUM((LOOKUP(ROW($45:$182),IF($A$45:$A$182<>"",ROW($45:$182)),$A$45:$A$182)=B34)*$L$45:$L$182)} -> 0 | M34: =(L34-'2025年18周'!L34)/'2025年18周'!L34 -> #DIV/0! | N34: =L34/J34 -> #DIV/0! | O34: =(N34-'2025年18周'!N34)/'2025年18周'!N34 -> #DIV/0! | P34: {=SUM((LOOKUP(ROW($45:$182),IF($A$45:$A$182<>"",ROW($45:$182)),$A$45:$A$182)=B34)*$P$45:$P$182)} -> 0 | T34: =C34+J34 -> 46 | U34: =E34+L34+I34+P34+Q34+R34+S34 -> 10612.03
B35: 外包总计 | C35: =SUM(C11:C34) -> 6508 | D35: =C35-'2025年18周'!C35 -> -2410 | E35: =SUM(E11:E34) -> 1573497.9 | F35: =(E35-'2025年18周'!E35)/'2025年18周'!E35 -> -0.3121 | G35: =E35/C35 -> 241.78 | H35: =(G35-'2025年18周'!G35)/'2025年18周'!G35 -> -0.0574 | I35: =SUM(I11:I34) -> 293378.59 | J35: =SUM(J11:J34) -> 241 | K35: =J35-'2025年18周'!J35 -> -218 | L35: =SUM(L11:L34) -> 44003 | M35: =(L35-'2025年18周'!L35)/'2025年18周'!L35 -> -0.5481 | N35: =L35/J35 -> 182.59 | O35: =(N35-'2025年18周'!N35)/'2025年18周'!N35 -> -0.1393 | P35: =SUM(P11:P34) -> 15836.79 | Q35: =SUM(Q11:Q34) -> 0 | R35: =SUM(R11:R34) -> 0 | S35: =SUM(S11:S30) -> 0 | T35: =SUM(T11:T34) -> 6749 | U35: =SUM(U11:U34) -> 1926716.3
A36: 自营外包总计 | C36: =C10+C35 -> 13015 | D36: =C36-'2025年18周'!C36 -> -5066 | E36: =E10+E35 -> 2994113.5 | F36: =(E36-'2025年18周'!E36)/'2025年18周'!E36 -> -0.3259 | G36: =E36/C36 -> 230.05 | H36: =(G36-'2025年18周'!G36)/'2025年18周'!G36 -> -0.0635 | I36: =I10+I35 -> 558623.77 | J36: =J10+J35 -> 562 | K36: =J36-'2025年18周'!J36 -> -904 | L36: =L10+L35 -> 128267 | M36: =(L36-'2025年18周'!L36)/'2025年18周'!L36 -> -0.6178 | N36: =L36/J36 -> 228.23 | O36: =(N36-'2025年18周'!N36)/'2025年18周'!N36 -> -0.0029 | P36: =P10+P35 -> 29370.87 | Q36: =Q10+Q35 -> 233439.06 | R36: =R10+R35 -> 154245 | S36: =S10+S35 -> 0 | T36: =T10+T35 -> 13577 | U36: =U10+U35 -> 4098059.2
C37: =IF(C36<>SUMIFS(周检修业务统计数据!E:E,周检修业务统计数据!C:C,"干箱",周检修业务统计数据!D:D,"COS"),"箱量有错","") | J37: =IF(J36<>SUMIFS(周检修业务统计数据!E:E,周检修业务统计数据!C:C,"干箱",周检修业务统计数据!D:D,"<>COS"),"箱量有错","") | O37: 环比增减 | U37: =U36-'2025年18周'!U36 -> -2965273.5 | V37: =T36-'2025年18周'!T36 -> -5970 | W37: =U36-'2025年18周'!U36 -> -2965273.5
C38: 箱量 | D38: 环比 | E38: 产值 | F38: 环比 | Q38: 净值 | U38: =(E36++L36+P36+S36)/1.13+(I36+Q36+R36)/1.06 -> 3681903.8
A39: 全部干箱业务 | C39: =T36 -> 13577 | D39: =(T36-'2025年18周'!T36)/'2025年18周'!T36 -> -0.31 | E39: =U36 -> 4098059 | F39: =(U36-'2025年18周'!U36)/'2025年18周'!U36 -> -0.4198 | M39: =E36/(1.13*7*10000) -> 37.852257
A40: 中远海自营占比 | C40: =C36/C39 -> 0.9586 | E40: =E36/E39 -> 0.7306
A41: 第三方业务占比 | C41: =J36/C39 -> 0.0414 | E41: =L36/E39 -> 0.0313
A42: 网点明细报表
A43: 业务类型 | C43: 中远海干箱 | J43: 第三方干箱 | P43: 其它费用 | T43: 合计 | X43: 分网点自营箱量完成情况 | AC43: 网点业务情况备注
A44: 部门/单位 | C44: 箱量 | D44: 环比 | E44: 产值 | F44: 环比 | G44: 单箱 | H44: 环比 | I44: 移箱费 | J44: 箱量 | K44: 环比 | L44: 产值 | M44: 环比 | N44: 单箱 | O44: 环比 | P44: 冷箱产值 | Q44: 堆场产值 | R44: 其它 | S44: 现金收费 | T44: 箱量 | U44: 产值 | V44: 人均产出 | W44: 修理人员数量 | X44: 周目标箱量 | Y44: 完成差额 | Z44: 合计目标箱量 | AA44: 合计完成量 | AB44: 合计完成差额
A45: 南岗分公司 | B45: 南岗堆场 | C45: =SUMIFS(周检修业务统计数据!E:E,周检修业务统计数据!B:B,B45,周检修业务统计数据!C:C,"干箱",周检修业务统计数据!D:D,"COS") -> 60 | D45: =C45-'2025年18周'!C45 -> -11 | E45: =(SUMIFS(周检修业务统计数据!I:I,周检修业务统计数据!B:B,B45,周检修业务统计数据!C:C,"干箱",周检修业务统计数据!D:D,"COS")+SUMIFS(周检修业务统计数据!J:J,周检修业务统计数据!B:B,B45,周检修业务统计数据!C:C,"干箱",周检修业务统计数据!D:D,"COS"))*1.13 -> 21637 | F45: =(E45-'2025年18周'!E45)/'2025年18周'!E45 -> 0.0249 | G45: =E45/C45 -> 361 | H45: =(G45-'2025年18周'!G45)/'2025年18周'!G45 -> 0.2155 | I45: =SUMIFS(周检修业务统计数据!L:L,周检修业务统计数据!B:B,B45,周检修业务统计数据!C:C,"干箱",周检修业务统计数据!D:D,"COS")*1.06 -> 0 | J45: =SUMIFS(周检修业务统计数据!E:E,周检修业务统计数据!B:B,B45,周检修业务统计数据!C:C,"干箱",周检修业务统计数据!D:D,"<>COS") -> 40 | K45: =J45-'2025年18周'!J45 -> -355 | L45: =(SUMIFS(周检修业务统计数据!I:I,周检修业务统计数据!B:B,B45,周检修业务统计数据!C:C,"干箱",周检修业务统计数据!D:D,"<>COS")+SUMIFS(周检修业务统计数据!J:J,周检修业务统计数据!B:B,B45,周检修业务统计数据!C:C,"干箱",周检修业务统计数据!D:D,"<>COS"))*1.13++SUMIFS(周检修业务统计数据!L:L,周检修业务统计数据!B:B,B45,周检修业务统计数据!C:C,"干箱",周检修业务统计数据!D:D,"<>COS")*1.06 -> 12624.93 | M45: =(L45-'2025年18周'!L45)/'2025年18周'!L45 -> -0.7379 | N45: =L45/J45 -> 316 | O45: =(N45-'2025年18周'!N45)/'2025年18周'!N45 -> 1.5902 | P45: =(SUMIFS(周检修业务统计数据!I:I,周检修业务统计数据!B:B,B45,周检修业务统计数据!C:C,"<>干箱")+SUMIFS(周检修业务统计数据!J:J,周检修业务统计数据!B:B,B45,周检修业务统计数据!C:C,"<>干箱"))*1.13++SUMIFS(周检修业务统计数据!L:L,周检修业务统计数据!B:B,B45,周检修业务统计数据!C:C,"<>干箱")*1.06 -> 728.33 | Q45: 48988 | S45: =S188 -> 0 | T45: =C45+J45 -> 100 | U45: =E45+L45+I45+P45+Q45+R45+S45 -> 83978 | V45: =(E45+L45+E46+L46)/W45 -> 6447 | W45: 7 | X45: 600 | Y45: =SUM(T45:T46)-X45 -> -410 | Z45: =X45*$Z$2 -> 11400 | AA45: =自营2026周完成情况!BB55 -> 7898 | AB45: =AA45-Z45 -> -3502
A46: 南岗分公司 | B46: 东江仓码头 | C46: =SUMIFS(周检修业务统计数据!E:E,周检修业务统计数据!B:B,B46,周检修业务统计数据!C:C,"干箱",周检修业务统计数据!D:D,"COS") -> 90 | D46: =C46-'2025年18周'!C46 -> -85 | E46: =(SUMIFS(周检修业务统计数据!I:I,周检修业务统计数据!B:B,B46,周检修业务统计数据!C:C,"干箱",周检修业务统计数据!D:D,"COS")+SUMIFS(周检修业务统计数据!J:J,周检修业务统计数据!B:B,B46,周检修业务统计数据!C:C,"干箱",周检修业务统计数据!D:D,"COS"))*1.13 -> 10866.36 | F46: =(E46-'2025年18周'!E46)/'2025年18周'!E46 -> -0.478 | G46: =E46/C46 -> 121 | H46: =(G46-'2025年18周'!G46)/'2025年18周'!G46 -> 0.0168 | I46: =SUMIFS(周检修业务统计数据!L:L,周检修业务统计数据!B:B,B46,周检修业务统计数据!C:C,"干箱",周检修业务统计数据!D:D,"COS")*1.06 -> 5689.9952 | J46: =SUMIFS(周检修业务统计数据!E:E,周检修业务统计数据!B:B,B46,周检修业务统计数据!C:C,"干箱",周检修业务统计数据!D:D,"<>COS") -> 0 | K46: =J46-'2025年18周'!J46 -> -27 | L46: =(SUMIFS(周检修业务统计数据!I:I,周检修业务统计数据!B:B,B46,周检修业务统计数据!C:C,"干箱",周检修业务统计数据!D:D,"<>COS")+SUMIFS(周检修业务统计数据!J:J,周检修业务统计数据!B:B,B46,周检修业务统计数据!C:C,"干箱",周检修业务统计数据!D:D,"<>COS"))*1.13++SUMIFS(周检修业务统计数据!L:L,周检修业务统计数据!B:B,B46,周检修业务统计数据!C:C,"干箱",周检修业务统计数据!D:D,"<>COS")*1.06 -> 0 | M46: =(L46-'2025年18周'!L46)/'2025年18周'!L46 -> -1 | N46: =L46/J46 -> #DIV/0! | O46: =(N46-'2025年18周'!N46)/'2025年18周'!N46 -> #DIV/0! | P46: =(SUMIFS(周检修业务统计数据!I:I,周检修业务统计数据!B:B,B46,周检修业务统计数据!C:C,"<>干箱")+SUMIFS(周检修业务统计数据!J:J,周检修业务统计数据!B:B,B46,周检修业务统计数据!C:C,"<>干箱"))*1.13++SUMIFS(周检修业务统计数据!L:L,周检修业务统计数据!B:B,B46,周检修业务统计数据!C:C,"<>干箱")*1.06 -> 0 | S46: =S189 -> 0 | T46: =C46+J46 -> 90 | U46: =E46+L46+I46+P46+Q46+R46+S46 -> 16556 | Z46: =X46*$Z$2 -> 0 | AA46: =自营2026周完成情况!BB56 -> 3469 | AB46: =AA46-Z46 -> 3469
A47: 深圳运营中心 | B47: 深圳大铲湾 | C47: =SUMIFS(周检修业务统计数据!E:E,周检修业务统计数据!B:B,B47,周检修业务统计数据!C:C,"干箱",周检修业务统计数据!D:D,"COS") -> 102 | D47: =C47-'2025年18周'!C47 -> -72 | E47: =(SUMIFS(周检修业务统计数据!I:I,周检修业务统计数据!B:B,B47,周检修业务统计数据!C:C,"干箱",周检修业务统计数据!D:D,"COS")+SUMIFS(周检修业务统计数据!J:J,周检修业务统计数据!B:B,B47,周检修业务统计数据!C:C,"干箱",周检修业务统计数据!D:D,"COS"))*1.13 -> 42053.97 | F47: =(E47-'2025年18周'!E47)/'2025年18周'!E47 -> -0.3931 | G47: =E47/C47 -> 412 | H47: =(G47-'2025年18周'!G47)/'2025年18周'!G47 -> 0.0352 | I47: =SUMIFS(周检修业务统计数据!L:L,周检修业务统计数据!B:B,B47,周检修业务统计数据!C:C,"干箱",周检修业务统计数据!D:D,"COS")*1.06 -> 0 | J47: =SUMIFS(周检修业务统计数据!E:E,周检修业务统计数据!B:B,B47,周检修业务统计数据!C:C,"干箱",周检修业务统计数据!D:D,"<>COS") -> 0 | K47: =J47-'2025年18周'!J47 -> -1 | L47: =(SUMIFS(周检修业务统计数据!I:I,周检修业务统计数据!B:B,B47,周检修业务统计数据!C:C,"干箱",周检修业务统计数据!D:D,"<>COS")+SUMIFS(周检修业务统计数据!J:J,周检修业务统计数据!B:B,B47,周检修业务统计数据!C:C,"干箱",周检修业务统计数据!D:D,"<>COS"))*1.13++SUMIFS(周检修业务统计数据!L:L,周检修业务统计数据!B:B,B47,周检修业务统计数据!C:C,"干箱",周检修业务统计数据!D:D,"<>COS")*1.06 -> 0 | M47: =(L47-'2025年18周'!L47)/'2025年18周'!L47 -> -1 | N47: =L47/J47 -> #DIV/0! | O47: =(N47-'2025年18周'!N47)/'2025年18周'!N47 -> #DIV/0! | P47: =(SUMIFS(周检修业务统计数据!I:I,周检修业务统计数据!B:B,B47,周检修业务统计数据!C:C,"<>干箱")+SUMIFS(周检修业务统计数据!J:J,周检修业务统计数据!B:B,B47,周检修业务统计数据!C:C,"<>干箱"))*1.13++SUMIFS(周检修业务统计数据!L:L,周检修业务统计数据!B:B,B47,周检修业务统计数据!C:C,"<>干箱")*1.06 -> 0 | S47: =S190 -> 0 | T47: =C47+J47 -> 102 | U47: =E47+L47+I47+P47+Q47+R47+S47 -> 42054 | V47: =(E47+L47)/W47 -> 10513 | W47: 4 | X47: 400 | Y47: =T47-X47 -> -298 | Z47: =X47*$Z$2 -> 7600 | AA47: =自营2026周完成情况!BB57 -> 2578 | AB47: =AA47-Z47 -> -5022
A48: 华慧良修 | B48: 深圳蛇口堆场 | C48: =SUMIFS(周检修业务统计数据!E:E,周检修业务统计数据!B:B,B48,周检修业务统计数据!C:C,"干箱",周检修业务统计数据!D:D,"COS") -> 174 | D48: =C48-'2025年18周'!C48 -> -67 | E48: =(SUMIFS(周检修业务统计数据!I:I,周检修业务统计数据!B:B,B48,周检修业务统计数据!C:C,"干箱",周检修业务统计数据!D:D,"COS")+SUMIFS(周检修业务统计数据!J:J,周检修业务统计数据!B:B,B48,周检修业务统计数据!C:C,"干箱",周检修业务统计数据!D:D,"COS"))*1.13 -> 74503.25 | F48: =(E48-'2025年18周'!E48)/'2025年18周'!E48 -> -0.2415 | G48: =E48/C48 -> 428 | H48: =(G48-'2025年18周'!G48)/'2025年18周'!G48 -> 0.049 | I48: =SUMIFS(周检修业务统计数据!L:L,周检修业务统计数据!B:B,B48,周检修业务统计数据!C:C,"干箱",周检修业务统计数据!D:D,"COS")*1.06 -> 0 | J48: =SUMIFS(周检修业务统计数据!E:E,周检修业务统计数据!B:B,B48,周检修业务统计数据!C:C,"干箱",周检修业务统计数据!D:D,"<>COS") -> 147 | K48: =J48-'2025年18周'!J48 -> -108 | L48: =(SUMIFS(周检修业务统计数据!I:I,周检修业务统计数据!B:B,B48,周检修业务统计数据!C:C,"干箱",周检修业务统计数据!D:D,"<>COS")+SUMIFS(周检修业务统计数据!J:J,周检修业务统计数据!B:B,B48,周检修业务统计数据!C:C,"干箱",周检修业务统计数据!D:D,"<>COS"))*1.13++SUMIFS(周检修业务统计数据!L:L,周检修业务统计数据!B:B,B48,周检修业务统计数据!C:C,"干箱",周检修业务统计数据!D:D,"<>COS")*1.06 -> 23804.4 | M48: =(L48-'2025年18周'!L48)/'2025年18周'!L48 -> -0.5441 | N48: =L48/J48 -> 162 | O48: =(N48-'2025年18周'!N48)/'2025年18周'!N48 -> -0.2098 | P48: =(SUMIFS(周检修业务统计数据!I:I,周检修业务统计数据!B:B,B48,周检修业务统计数据!C:C,"<>干箱")+SUMIFS(周检修业务统计数据!J:J,周检修业务统计数据!B:B,B48,周检修业务统计数据!C:C,"<>干箱"))*1.13++SUMIFS(周检修业务统计数据!L:L,周检修业务统计数据!B:B,B48,周检修业务统计数据!C:C,"<>干箱")*1.06 -> 0 | Q48: 78519.5 | S48: =S191 -> 0 | T48: =C48+J48 -> 321 | U48: =E48+L48+I48+P48+Q48+R48+S48 -> 176827 | V48: =(E48+L48)/W48 -> 14044 | W48: 7 | X48: 400 | Y48: =T48-X48 -> -79 | Z48: =X48*$Z$2 -> 7600 | AA48: =自营2026周完成情况!BB58 -> 7033 | AB48: =AA48-Z48 -> -567
A49: 深圳运营中心 | B49: 汕头广澳 | C49: =SUMIFS(周检修业务统计数据!E:E,周检修业务统计数据!B:B,B49,周检修业务统计数据!C:C,"干箱",周检修业务统计数据!D:D,"COS") -> 0 | D49: =C49-'2025年18周'!C49 -> 0 | E49: =(SUMIFS(周检修业务统计数据!I:I,周检修业务统计数据!B:B,B49,周检修业务统计数据!C:C,"干箱",周检修业务统计数据!D:D,"COS")+SUMIFS(周检修业务统计数据!J:J,周检修业务统计数据!B:B,B49,周检修业务统计数据!C:C,"干箱",周检修业务统计数据!D:D,"COS"))*1.13 -> 0 | F49: =(E49-'2025年18周'!E49)/'2025年18周'!E49 -> #DIV/0! | G49: =E49/C49 -> #DIV/0! | H49: =(G49-'2025年18周'!G49)/'2025年18周'!G49 -> #DIV/0! | I49: =SUMIFS(周检修业务统计数据!L:L,周检修业务统计数据!B:B,B49,周检修业务统计数据!C:C,"干箱",周检修业务统计数据!D:D,"COS")*1.06 -> 0 | J49: =SUMIFS(周检修业务统计数据!E:E,周检修业务统计数据!B:B,B49,周检修业务统计数据!C:C,"干箱",周检修业务统计数据!D:D,"<>COS") -> 0 | K49: =J49-'2025年18周'!J49 -> 0 | L49: =(SUMIFS(周检修业务统计数据!I:I,周检修业务统计数据!B:B,B49,周检修业务统计数据!C:C,"干箱",周检修业务统计数据!D:D,"<>COS")+SUMIFS(周检修业务统计数据!J:J,周检修业务统计数据!B:B,B49,周检修业务统计数据!C:C,"干箱",周检修业务统计数据!D:D,"<>COS"))*1.13++SUMIFS(周检修业务统计数据!L:L,周检修业务统计数据!B:B,B49,周检修业务统计数据!C:C,"干箱",周检修业务统计数据!D:D,"<>COS")*1.06 -> 0 | M49: =(L49-'2025年18周'!L49)/'2025年18周'!L49 -> #DIV/0! | N49: =L49/J49 -> #DIV/0! | O49: =(N49-'2025年18周'!N49)/'2025年18周'!N49 -> #DIV/0! | P49: =(SUMIFS(周检修业务统计数据!I:I,周检修业务统计数据!B:B,B49,周检修业务统计数据!C:C,"<>干箱")+SUMIFS(周检修业务统计数据!J:J,周检修业务统计数据!B:B,B49,周检修业务统计数据!C:C,"<>干箱"))*1.13++SUMIFS(周检修业务统计数据!L:L,周检修业务统计数据!B:B,B49,周检修业务统计数据!C:C,"<>干箱")*1.06 -> 0 | S49: =S192 -> 0 | T49: =C49+J49 -> 0 | U49: =E49+L49+I49+P49+Q49+R49+S49 -> 0 | V49: =(E49+L49)/W49 -> #DIV/0! | W49: 0 | X49: 500 | Y49: =SUM(T49:T51)-X49 -> -258 | Z49: =X49*$Z$2 -> 9500 | AA49: =SUM(自营2026周完成情况!BB59:BB61) -> 7340 | AB49: =AA49-Z49 -> -2160
A50: 深圳运营中心 | B50: 汕头堆场 | C50: =SUMIFS(周检修业务统计数据!E:E,周检修业务统计数据!B:B,B50,周检修业务统计数据!C:C,"干箱",周检修业务统计数据!D:D,"COS") -> 178 | D50: =C50-'2025年18周'!C50 -> -144 | E50: =(SUMIFS(周检修业务统计数据!I:I,周检修业务统计数据!B:B,B50,周检修业务统计数据!C:C,"干箱",周检修业务统计数据!D:D,"COS")+SUMIFS(周检修业务统计数据!J:J,周检修业务统计数据!B:B,B50,周检修业务统计数据!C:C,"干箱",周检修业务统计数据!D:D,"COS"))*1.13 -> 53971.11 | F50: =(E50-'2025年18周'!E50)/'2025年18周'!E50 -> -0.526 | G50: =E50/C50 -> 303 | H50: =(G50-'2025年18周'!G50)/'2025年18周'!G50 -> -0.1441 | I50: =SUMIFS(周检修业务统计数据!L:L,周检修业务统计数据!B:B,B50,周检修业务统计数据!C:C,"干箱",周检修业务统计数据!D:D,"COS")*1.06 -> 0 | J50: =SUMIFS(周检修业务统计数据!E:E,周检修业务统计数据!B:B,B50,周检修业务统计数据!C:C,"干箱",周检修业务统计数据!D:D,"<>COS") -> 64 | K50: =J50-'2025年18周'!J50 -> -66 | L50: =(SUMIFS(周检修业务统计数据!I:I,周检修业务统计数据!B:B,B50,周检修业务统计数据!C:C,"干箱",周检修业务统计数据!D:D,"<>COS")+SUMIFS(周检修业务统计数据!J:J,周检修业务统计数据!B:B,B50,周检修业务统计数据!C:C,"干箱",周检修业务统计数据!D:D,"<>COS"))*1.13++SUMIFS(周检修业务统计数据!L:L,周检修业务统计数据!B:B,B50,周检修业务统计数据!C:C,"干箱",周检修业务统计数据!D:D,"<>COS")*1.06 -> 17920.62 | M50: =(L50-'2025年18周'!L50)/'2025年18周'!L50 -> -0.6122 | N50: =L50/J50 -> 280 | O50: =(N50-'2025年18周'!N50)/'2025年18周'!N50 -> -0.2113 | P50: =(SUMIFS(周检修业务统计数据!I:I,周检修业务统计数据!B:B,B50,周检修业务统计数据!C:C,"<>干箱")+SUMIFS(周检修业务统计数据!J:J,周检修业务统计数据!B:B,B50,周检修业务统计数据!C:C,"<>干箱"))*1.13++SUMIFS(周检修业务统计数据!L:L,周检修业务统计数据!B:B,B50,周检修业务统计数据!C:C,"<>干箱")*1.06 -> 1190.32 | Q50: 14189.5 | R50: 120 | S50: =S193 -> 0 | T50: =C50+J50 -> 242 | U50: =E50+L50+I50+P50+Q50+R50+S50 -> 87392 | V50: =(E50+L50)/W50 -> 7189 | W50: 10
A51: 深圳运营中心 | B51: 汕头国集 | C51: =SUMIFS(周检修业务统计数据!E:E,周检修业务统计数据!B:B,B51,周检修业务统计数据!C:C,"干箱",周检修业务统计数据!D:D,"COS") -> 0 | D51: =C51-'2025年18周'!C51 -> 0 | E51: =(SUMIFS(周检修业务统计数据!I:I,周检修业务统计数据!B:B,B51,周检修业务统计数据!C:C,"干箱",周检修业务统计数据!D:D,"COS")+SUMIFS(周检修业务统计数据!J:J,周检修业务统计数据!B:B,B51,周检修业务统计数据!C:C,"干箱",周检修业务统计数据!D:D,"COS"))*1.13 -> 0 | F51: =(E51-'2025年18周'!E51)/'2025年18周'!E51 -> #DIV/0! | G51: =E51/C51 -> #DIV/0! | H51: =(G51-'2025年18周'!G51)/'2025年18周'!G51 -> #DIV/0! | I51: =SUMIFS(周检修业务统计数据!L:L,周检修业务统计数据!B:B,B51,周检修业务统计数据!C:C,"干箱",周检修业务统计数据!D:D,"COS")*1.06 -> 0 | J51: =SUMIFS(周检修业务统计数据!E:E,周检修业务统计数据!B:B,B51,周检修业务统计数据!C:C,"干箱",周检修业务统计数据!D:D,"<>COS") -> 0 | K51: =J51-'2025年18周'!J51 -> 0 | L51: =(SUMIFS(周检修业务统计数据!I:I,周检修业务统计数据!B:B,B51,周检修业务统计数据!C:C,"干箱",周检修业务统计数据!D:D,"<>COS")+SUMIFS(周检修业务统计数据!J:J,周检修业务统计数据!B:B,B51,周检修业务统计数据!C:C,"干箱",周检修业务统计数据!D:D,"<>COS"))*1.13++SUMIFS(周检修业务统计数据!L:L,周检修业务统计数据!B:B,B51,周检修业务统计数据!C:C,"干箱",周检修业务统计数据!D:D,"<>COS")*1.06 -> 0 | M51: =(L51-'2025年18周'!L51)/'2025年18周'!L51 -> #DIV/0! | N51: =L51/J51 -> #DIV/0! | O51: =(N51-'2025年18周'!N51)/'2025年18周'!N51 -> #DIV/0! | P51: =(SUMIFS(周检修业务统计数据!I:I,周检修业务统计数据!B:B,B51,周检修业务统计数据!C:C,"<>干箱")+SUMIFS(周检修业务统计数据!J:J,周检修业务统计数据!B:B,B51,周检修业务统计数据!C:C,"<>干箱"))*1.13++SUMIFS(周检修业务统计数据!L:L,周检修业务统计数据!B:B,B51,周检修业务统计数据!C:C,"<>干箱")*1.06 -> 0 | S51: =S194 -> 0 | T51: =C51+J51 -> 0 | U51: =E51+L51+I51+P51+Q51+R51+S51 -> 0 | V51: =(E51+L51)/W51 -> #DIV/0! | W51: 0
A52: 广州运营中心 | B52: 黄埔旧港 | C52: =SUMIFS(周检修业务统计数据!E:E,周检修业务统计数据!B:B,B52,周检修业务统计数据!C:C,"干箱",周检修业务统计数据!D:D,"COS") -> 1115 | D52: =C52-'2025年18周'!C52 -> -143 | E52: =(SUMIFS(周检修业务统计数据!I:I,周检修业务统计数据!B:B,B52,周检修业务统计数据!C:C,"干箱",周检修业务统计数据!D:D,"COS")+SUMIFS(周检修业务统计数据!J:J,周检修业务统计数据!B:B,B52,周检修业务统计数据!C:C,"干箱",周检修业务统计数据!D:D,"COS"))*1.13 -> 137277.99 | F52: =(E52-'2025年18周'!E52)/'2025年18周'!E52 -> -0.1295 | G52: =E52/C52 -> 123 | H52: =(G52-'2025年18周'!G52)/'2025年18周'!G52 -> -0.016 | I52: =SUMIFS(周检修业务统计数据!L:L,周检修业务统计数据!B:B,B52,周检修业务统计数据!C:C,"干箱",周检修业务统计数据!D:D,"COS")*1.06 -> 74163.398 | J52: =SUMIFS(周检修业务统计数据!E:E,周检修业务统计数据!B:B,B52,周检修业务统计数据!C:C,"干箱",周检修业务统计数据!D:D,"<>COS") -> 13 | K52: =J52-'2025年18周'!J52 -> 13 | L52: =(SUMIFS(周检修业务统计数据!I:I,周检修业务统计数据!B:B,B52,周检修业务统计数据!C:C,"干箱",周检修业务统计数据!D:D,"<>COS")+SUMIFS(周检修业务统计数据!J:J,周检修业务统计数据!B:B,B52,周检修业务统计数据!C:C,"干箱",周检修业务统计数据!D:D,"<>COS"))*1.13++SUMIFS(周检修业务统计数据!L:L,周检修业务统计数据!B:B,B52,周检修业务统计数据!C:C,"干箱",周检修业务统计数据!D:D,"<>COS")*1.06 -> 1010.1 | M52: =(L52-'2025年18周'!L52)/'2025年18周'!L52 -> #DIV/0! | N52: =L52/J52 -> 78 | O52: =(N52-'2025年18周'!N52)/'2025年18周'!N52 -> #DIV/0! | P52: =(SUMIFS(周检修业务统计数据!I:I,周检修业务统计数据!B:B,B52,周检修业务统计数据!C:C,"<>干箱")+SUMIFS(周检修业务统计数据!J:J,周检修业务统计数据!B:B,B52,周检修业务统计数据!C:C,"<>干箱"))*1.13++SUMIFS(周检修业务统计数据!L:L,周检修业务统计数据!B:B,B52,周检修业务统计数据!C:C,"<>干箱")*1.06 -> 0 | S52: =S195 -> 0 | T52: =C52+J52 -> 1128 | U52: =E52+L52+I52+P52+Q52+R52+S52 -> 212451 | V52: =(E52+L52+E53+L53+E54+L54)/W52 -> 14096 | W52: 10 | X52: 1100 | Y52: =T52-X52 -> 28 | Z52: =X52*$Z$2 -> 20900 | AA52: =SUM(自营2026周完成情况!BB62:BB64) -> 22557 | AB52: =AA52-Z52 -> 1657
A53: 广州运营中心 | B53: 淡水河码头 | C53: =SUMIFS(周检修业务统计数据!E:E,周检修业务统计数据!B:B,B53,周检修业务统计数据!C:C,"干箱",周检修业务统计数据!D:D,"COS") -> 0 | D53: =C53-'2025年18周'!C53 -> 0 | E53: =(SUMIFS(周检修业务统计数据!I:I,周检修业务统计数据!B:B,B53,周检修业务统计数据!C:C,"干箱",周检修业务统计数据!D:D,"COS")+SUMIFS(周检修业务统计数据!J:J,周检修业务统计数据!B:B,B53,周检修业务统计数据!C:C,"干箱",周检修业务统计数据!D:D,"COS"))*1.13 -> 0 | F53: =(E53-'2025年18周'!E53)/'2025年18周'!E53 -> #DIV/0! | G53: =E53/C53 -> #DIV/0! | H53: =(G53-'2025年18周'!G53)/'2025年18周'!G53 -> #DIV/0! | I53: =SUMIFS(周检修业务统计数据!L:L,周检修业务统计数据!B:B,B53,周检修业务统计数据!C:C,"干箱",周检修业务统计数据!D:D,"COS")*1.06 -> 0 | J53: =SUMIFS(周检修业务统计数据!E:E,周检修业务统计数据!B:B,B53,周检修业务统计数据!C:C,"干箱",周检修业务统计数据!D:D,"<>COS") -> 0 | K53: =J53-'2025年18周'!J53 -> 0 | L53: =(SUMIFS(周检修业务统计数据!I:I,周检修业务统计数据!B:B,B53,周检修业务统计数据!C:C,"干箱",周检修业务统计数据!D:D,"<>COS")+SUMIFS(周检修业务统计数据!J:J,周检修业务统计数据!B:B,B53,周检修业务统计数据!C:C,"干箱",周检修业务统计数据!D:D,"<>COS"))*1.13++SUMIFS(周检修业务统计数据!L:L,周检修业务统计数据!B:B,B53,周检修业务统计数据!C:C,"干箱",周检修业务统计数据!D:D,"<>COS")*1.06 -> 0 | M53: =(L53-'2025年18周'!L53)/'2025年18周'!L53 -> #DIV/0! | N53: =L53/J53 -> #DIV/0! | O53: =(N53-'2025年18周'!N53)/'2025年18周'!N53 -> #DIV/0! | P53: =(SUMIFS(周检修业务统计数据!I:I,周检修业务统计数据!B:B,B53,周检修业务统计数据!C:C,"<>干箱")+SUMIFS(周检修业务统计数据!J:J,周检修业务统计数据!B:B,B53,周检修业务统计数据!C:C,"<>干箱"))*1.13++SUMIFS(周检修业务统计数据!L:L,周检修业务统计数据!B:B,B53,周检修业务统计数据!C:C,"<>干箱")*1.06 -> 0 | S53: =S196 -> 0 | T53: =C53+J53 -> 0 | U53: =E53+L53+I53+P53+Q53+R53+S53 -> 0 | AC53: 2023年1月新开，新鱼珠点改名
A54: 广州运营中心 | B54: 新沙港 | C54: =SUMIFS(周检修业务统计数据!E:E,周检修业务统计数据!B:B,B54,周检修业务统计数据!C:C,"干箱",周检修业务统计数据!D:D,"COS") -> 9 | D54: =C54-'2025年18周'!C54 -> -3 | E54: =(SUMIFS(周检修业务统计数据!I:I,周检修业务统计数据!B:B,B54,周检修业务统计数据!C:C,"干箱",周检修业务统计数据!D:D,"COS")+SUMIFS(周检修业务统计数据!J:J,周检修业务统计数据!B:B,B54,周检修业务统计数据!C:C,"干箱",周检修业务统计数据!D:D,"COS"))*1.13 -> 2676.41 | F54: =(E54-'2025年18周'!E54)/'2025年18周'!E54 -> -0.2965 | G54: =E54/C54 -> 297 | H54: =(G54-'2025年18周'!G54)/'2025年18周'!G54 -> -0.0631 | I54: =SUMIFS(周检修业务统计数据!L:L,周检修业务统计数据!B:B,B54,周检修业务统计数据!C:C,"干箱",周检修业务统计数据!D:D,"COS")*1.06 -> 495.0306 | J54: =SUMIFS(周检修业务统计数据!E:E,周检修业务统计数据!B:B,B54,周检修业务统计数据!C:C,"干箱",周检修业务统计数据!D:D,"<>COS") -> 0 | K54: =J54-'2025年18周'!J54 -> 0 | L54: =(SUMIFS(周检修业务统计数据!I:I,周检修业务统计数据!B:B,B54,周检修业务统计数据!C:C,"干箱",周检修业务统计数据!D:D,"<>COS")+SUMIFS(周检修业务统计数据!J:J,周检修业务统计数据!B:B,B54,周检修业务统计数据!C:C,"干箱",周检修业务统计数据!D:D,"<>COS"))*1.13++SUMIFS(周检修业务统计数据!L:L,周检修业务统计数据!B:B,B54,周检修业务统计数据!C:C,"干箱",周检修业务统计数据!D:D,"<>COS")*1.06 -> 0 | M54: =(L54-'2025年18周'!L54)/'2025年18周'!L54 -> #DIV/0! | N54: =L54/J54 -> #DIV/0! | O54: =(N54-'2025年18周'!N54)/'2025年18周'!N54 -> #DIV/0! | P54: =(SUMIFS(周检修业务统计数据!I:I,周检修业务统计数据!B:B,B54,周检修业务统计数据!C:C,"<>干箱")+SUMIFS(周检修业务统计数据!J:J,周检修业务统计数据!B:B,B54,周检修业务统计数据!C:C,"<>干箱"))*1.13++SUMIFS(周检修业务统计数据!L:L,周检修业务统计数据!B:B,B54,周检修业务统计数据!C:C,"<>干箱")*1.06 -> 0 | S54: =S197 -> 0 | T54: =C54+J54 -> 9 | U54: =E54+L54+I54+P54+Q54+R54+S54 -> 3171 | AC54: 2023年2月新开。
A55: 广州运营中心 | B55: 南沙三期自营 | C55: =SUMIFS(周检修业务统计数据!E:E,周检修业务统计数据!B:B,B55,周检修业务统计数据!C:C,"干箱",周检修业务统计数据!D:D,"COS") -> 0 | D55: =C55-'2025年18周'!C55 -> 0 | E55: =(SUMIFS(周检修业务统计数据!I:I,周检修业务统计数据!B:B,B55,周检修业务统计数据!C:C,"干箱",周检修业务统计数据!D:D,"COS")+SUMIFS(周检修业务统计数据!J:J,周检修业务统计数据!B:B,B55,周检修业务统计数据!C:C,"干箱",周检修业务统计数据!D:D,"COS"))*1.13 -> 0 | F55: =(E55-'2025年18周'!E55)/'2025年18周'!E55 -> #DIV/0! | G55: =E55/C55 -> #DIV/0! | H55: =(G55-'2025年18周'!G55)/'2025年18周'!G55 -> #DIV/0! | I55: =SUMIFS(周检修业务统计数据!L:L,周检修业务统计数据!B:B,B55,周检修业务统计数据!C:C,"干箱",周检修业务统计数据!D:D,"COS")*1.06 -> 0 | J55: =SUMIFS(周检修业务统计数据!E:E,周检修业务统计数据!B:B,B55,周检修业务统计数据!C:C,"干箱",周检修业务统计数据!D:D,"<>COS") -> 0 | K55: =J55-'2025年18周'!J55 -> 0 | L55: =(SUMIFS(周检修业务统计数据!I:I,周检修业务统计数据!B:B,B55,周检修业务统计数据!C:C,"干箱",周检修业务统计数据!D:D,"<>COS")+SUMIFS(周检修业务统计数据!J:J,周检修业务统计数据!B:B,B55,周检修业务统计数据!C:C,"干箱",周检修业务统计数据!D:D,"<>COS"))*1.13++SUMIFS(周检修业务统计数据!L:L,周检修业务统计数据!B:B,B55,周检修业务统计数据!C:C,"干箱",周检修业务统计数据!D:D,"<>COS")*1.06 -> 0 | M55: =(L55-'2025年18周'!L55)/'2025年18周'!L55 -> #DIV/0! | N55: =L55/J55 -> #DIV/0! | O55: =(N55-'2025年18周'!N55)/'2025年18周'!N55 -> #DIV/0! | P55: =(SUMIFS(周检修业务统计数据!I:I,周检修业务统计数据!B:B,B55,周检修业务统计数据!C:C,"<>干箱")+SUMIFS(周检修业务统计数据!J:J,周检修业务统计数据!B:B,B55,周检修业务统计数据!C:C,"<>干箱"))*1.13++SUMIFS(周检修业务统计数据!L:L,周检修业务统计数据!B:B,B55,周检修业务统计数据!C:C,"<>干箱")*1.06 -> 0 | R55: 2400 | S55: =S198 -> 0 | T55: =C55+J55 -> 0 | U55: =E55+L55+I55+P55+Q55+R55+S55 -> 2400 | V55: =(E55+L55+E56+L56+E57+L57)/W55 -> 17038 | W55: 5 | X55: 500 | Y55: =SUM(T55:T57)-X55 -> -174 | Z55: =X55*$Z$2 -> 9500 | AA55: =SUM(自营2026周完成情况!BB65:BB67) -> 9113 | AB55: =AA55-Z55 -> -387
A56: 广州运营中心 | B56: 南沙一期码头 | C56: =SUMIFS(周检修业务统计数据!E:E,周检修业务统计数据!B:B,B56,周检修业务统计数据!C:C,"干箱",周检修业务统计数据!D:D,"COS") -> 115 | D56: =C56-'2025年18周'!C56 -> -100 | E56: =(SUMIFS(周检修业务统计数据!I:I,周检修业务统计数据!B:B,B56,周检修业务统计数据!C:C,"干箱",周检修业务统计数据!D:D,"COS")+SUMIFS(周检修业务统计数据!J:J,周检修业务统计数据!B:B,B56,周检修业务统计数据!C:C,"干箱",周检修业务统计数据!D:D,"COS"))*1.13 -> 24853.13 | F56: =(E56-'2025年18周'!E56)/'2025年18周'!E56 -> -0.4392 | G56: =E56/C56 -> 216 | H56: =(G56-'2025年18周'!G56)/'2025年18周'!G56 -> 0.0485 | I56: =SUMIFS(周检修业务统计数据!L:L,周检修业务统计数据!B:B,B56,周检修业务统计数据!C:C,"干箱",周检修业务统计数据!D:D,"COS")*1.06 -> 8564.4502 | J56: =SUMIFS(周检修业务统计数据!E:E,周检修业务统计数据!B:B,B56,周检修业务统计数据!C:C,"干箱",周检修业务统计数据!D:D,"<>COS") -> 20 | K56: =J56-'2025年18周'!J56 -> -59 | L56: =(SUMIFS(周检修业务统计数据!I:I,周检修业务统计数据!B:B,B56,周检修业务统计数据!C:C,"干箱",周检修业务统计数据!D:D,"<>COS")+SUMIFS(周检修业务统计数据!J:J,周检修业务统计数据!B:B,B56,周检修业务统计数据!C:C,"干箱",周检修业务统计数据!D:D,"<>COS"))*1.13++SUMIFS(周检修业务统计数据!L:L,周检修业务统计数据!B:B,B56,周检修业务统计数据!C:C,"干箱",周检修业务统计数据!D:D,"<>COS")*1.06 -> 5808.43 | M56: =(L56-'2025年18周'!L56)/'2025年18周'!L56 -> -0.7507 | N56: =L56/J56 -> 290 | O56: =(N56-'2025年18周'!N56)/'2025年18周'!N56 -> -0.0169 | P56: =(SUMIFS(周检修业务统计数据!I:I,周检修业务统计数据!B:B,B56,周检修业务统计数据!C:C,"<>干箱")+SUMIFS(周检修业务统计数据!J:J,周检修业务统计数据!B:B,B56,周检修业务统计数据!C:C,"<>干箱"))*1.13++SUMIFS(周检修业务统计数据!L:L,周检修业务统计数据!B:B,B56,周检修业务统计数据!C:C,"<>干箱")*1.06 -> 0 | R56: 1230 | S56: =S199 -> 0 | T56: =C56+J56 -> 135 | U56: =E56+L56+I56+P56+Q56+R56+S56 -> 40456
A57: 广州运营中心 | B57: 南沙二期 | C57: =SUMIFS(周检修业务统计数据!E:E,周检修业务统计数据!B:B,B57,周检修业务统计数据!C:C,"干箱",周检修业务统计数据!D:D,"COS") -> 160 | D57: =C57-'2025年18周'!C57 -> -36 | E57: =(SUMIFS(周检修业务统计数据!I:I,周检修业务统计数据!B:B,B57,周检修业务统计数据!C:C,"干箱",周检修业务统计数据!D:D,"COS")+SUMIFS(周检修业务统计数据!J:J,周检修业务统计数据!B:B,B57,周检修业务统计数据!C:C,"干箱",周检修业务统计数据!D:D,"COS"))*1.13 -> 46341.42 | F57: =(E57-'2025年18周'!E57)/'2025年18周'!E57 -> -0.1896 | G57: =E57/C57 -> 290 | H57: =(G57-'2025年18周'!G57)/'2025年18周'!G57 -> -0.0068 | I57: =SUMIFS(周检修业务统计数据!L:L,周检修业务统计数据!B:B,B57,周检修业务统计数据!C:C,"干箱",周检修业务统计数据!D:D,"COS")*1.06 -> 11559.385 | J57: =SUMIFS(周检修业务统计数据!E:E,周检修业务统计数据!B:B,B57,周检修业务统计数据!C:C,"干箱",周检修业务统计数据!D:D,"<>COS") -> 31 | K57: =J57-'2025年18周'!J57 -> -28 | L57: =(SUMIFS(周检修业务统计数据!I:I,周检修业务统计数据!B:B,B57,周检修业务统计数据!C:C,"干箱",周检修业务统计数据!D:D,"<>COS")+SUMIFS(周检修业务统计数据!J:J,周检修业务统计数据!B:B,B57,周检修业务统计数据!C:C,"干箱",周检修业务统计数据!D:D,"<>COS"))*1.13++SUMIFS(周检修业务统计数据!L:L,周检修业务统计数据!B:B,B57,周检修业务统计数据!C:C,"干箱",周检修业务统计数据!D:D,"<>COS")*1.06 -> 8188.05 | M57: =(L57-'2025年18周'!L57)/'2025年18周'!L57 -> -0.5478 | N57: =L57/J57 -> 264 | O57: =(N57-'2025年18周'!N57)/'2025年18周'!N57 -> -0.1401 | P57: =(SUMIFS(周检修业务统计数据!I:I,周检修业务统计数据!B:B,B57,周检修业务统计数据!C:C,"<>干箱")+SUMIFS(周检修业务统计数据!J:J,周检修业务统计数据!B:B,B57,周检修业务统计数据!C:C,"<>干箱"))*1.13++SUMIFS(周检修业务统计数据!L:L,周检修业务统计数据!B:B,B57,周检修业务统计数据!C:C,"<>干箱")*1.06 -> 10865.54 | S57: =S200 -> 0 | T57: =C57+J57 -> 191 | U57: =E57+L57+I57+P57+Q57+R57+S57 -> 76954
A58: 广州运营中心 | B58: 虎门二期码头 | C58: =SUMIFS(周检修业务统计数据!E:E,周检修业务统计数据!B:B,B58,周检修业务统计数据!C:C,"干箱",周检修业务统计数据!D:D,"COS") -> 324 | D58: =C58-'2025年18周'!C58 -> -143 | E58: =(SUMIFS(周检修业务统计数据!I:I,周检修业务统计数据!B:B,B58,周检修业务统计数据!C:C,"干箱",周检修业务统计数据!D:D,"COS")+SUMIFS(周检修业务统计数据!J:J,周检修业务统计数据!B:B,B58,周检修业务统计数据!C:C,"干箱",周检修业务统计数据!D:D,"COS"))*1.13 -> 40046.88 | F58: =(E58-'2025年18周'!E58)/'2025年18周'!E58 -> -0.3463 | G58: =E58/C58 -> 124 | H58: =(G58-'2025年18周'!G58)/'2025年18周'!G58 -> -0.0534 | I58: =SUMIFS(周检修业务统计数据!L:L,周检修业务统计数据!B:B,B58,周检修业务统计数据!C:C,"干箱",周检修业务统计数据!D:D,"COS")*1.06 -> 20160.119 | J58: =SUMIFS(周检修业务统计数据!E:E,周检修业务统计数据!B:B,B58,周检修业务统计数据!C:C,"干箱",周检修业务统计数据!D:D,"<>COS") -> 1 | K58: =J58-'2025年18周'!J58 -> -7 | L58: =(SUMIFS(周检修业务统计数据!I:I,周检修业务统计数据!B:B,B58,周检修业务统计数据!C:C,"干箱",周检修业务统计数据!D:D,"<>COS")+SUMIFS(周检修业务统计数据!J:J,周检修业务统计数据!B:B,B58,周检修业务统计数据!C:C,"干箱",周检修业务统计数据!D:D,"<>COS"))*1.13++SUMIFS(周检修业务统计数据!L:L,周检修业务统计数据!B:B,B58,周检修业务统计数据!C:C,"干箱",周检修业务统计数据!D:D,"<>COS")*1.06 -> 143.41 | M58: =(L58-'2025年18周'!L58)/'2025年18周'!L58 -> -0.8673 | N58: =L58/J58 -> 143 | O58: =(N58-'2025年18周'!N58)/'2025年18周'!N58 -> 0.0593 | P58: =(SUMIFS(周检修业务统计数据!I:I,周检修业务统计数据!B:B,B58,周检修业务统计数据!C:C,"<>干箱")+SUMIFS(周检修业务统计数据!J:J,周检修业务统计数据!B:B,B58,周检修业务统计数据!C:C,"<>干箱"))*1.13++SUMIFS(周检修业务统计数据!L:L,周检修业务统计数据!B:B,B58,周检修业务统计数据!C:C,"<>干箱")*1.06 -> 0 | S58: =S201 -> 0 | T58: =C58+J58 -> 325 | U58: =E58+L58+I58+P58+Q58+R58+S58 -> 60350 | V58: =(E58+L58+E59+L59+E60+L60)/W58 -> 10484 | W58: 4 | X58: 400 | Y58: =T58-X58 -> -75 | Z58: =X58*$Z$2 -> 7600 | AA58: =SUM(自营2026周完成情况!BB68:BB70) -> 9874 | AB58: =AA58-Z58 -> 2274
A59: 广州运营中心 | B59: 虎门港一期 | C59: =SUMIFS(周检修业务统计数据!E:E,周检修业务统计数据!B:B,B59,周检修业务统计数据!C:C,"干箱",周检修业务统计数据!D:D,"COS") -> 0 | D59: =C59-'2025年18周'!C59 -> 0 | E59: =(SUMIFS(周检修业务统计数据!I:I,周检修业务统计数据!B:B,B59,周检修业务统计数据!C:C,"干箱",周检修业务统计数据!D:D,"COS")+SUMIFS(周检修业务统计数据!J:J,周检修业务统计数据!B:B,B59,周检修业务统计数据!C:C,"干箱",周检修业务统计数据!D:D,"COS"))*1.13 -> 0 | F59: =(E59-'2025年18周'!E59)/'2025年18周'!E59 -> #DIV/0! | G59: =E59/C59 -> #DIV/0! | H59: =(G59-'2025年18周'!G59)/'2025年18周'!G59 -> #DIV/0! | I59: =SUMIFS(周检修业务统计数据!L:L,周检修业务统计数据!B:B,B59,周检修业务统计数据!C:C,"干箱",周检修业务统计数据!D:D,"COS")*1.06 -> 0 | J59: =SUMIFS(周检修业务统计数据!E:E,周检修业务统计数据!B:B,B59,周检修业务统计数据!C:C,"干箱",周检修业务统计数据!D:D,"<>COS") -> 0 | K59: =J59-'2025年18周'!J59 -> 0 | L59: =(SUMIFS(周检修业务统计数据!I:I,周检修业务统计数据!B:B,B59,周检修业务统计数据!C:C,"干箱",周检修业务统计数据!D:D,"<>COS")+SUMIFS(周检修业务统计数据!J:J,周检修业务统计数据!B:B,B59,周检修业务统计数据!C:C,"干箱",周检修业务统计数据!D:D,"<>COS"))*1.13++SUMIFS(周检修业务统计数据!L:L,周检修业务统计数据!B:B,B59,周检修业务统计数据!C:C,"干箱",周检修业务统计数据!D:D,"<>COS")*1.06 -> 0 | M59: =(L59-'2025年18周'!L59)/'2025年18周'!L59 -> #DIV/0! | N59: =L59/J59 -> #DIV/0! | O59: =(N59-'2025年18周'!N59)/'2025年18周'!N59 -> #DIV/0! | P59: =(SUMIFS(周检修业务统计数据!I:I,周检修业务统计数据!B:B,B59,周检修业务统计数据!C:C,"<>干箱")+SUMIFS(周检修业务统计数据!J:J,周检修业务统计数据!B:B,B59,周检修业务统计数据!C:C,"<>干箱"))*1.13++SUMIFS(周检修业务统计数据!L:L,周检修业务统计数据!B:B,B59,周检修业务统计数据!C:C,"<>干箱")*1.06 -> 0 | S59: =S202 -> 0 | T59: =C59+J59 -> 0 | U59: =E59+L59+I59+P59+Q59+R59+S59 -> 0
A60: 广州运营中心 | B60: 虎门三期码头 | C60: =SUMIFS(周检修业务统计数据!E:E,周检修业务统计数据!B:B,B60,周检修业务统计数据!C:C,"干箱",周检修业务统计数据!D:D,"COS") -> 42 | D60: =C60-'2025年18周'!C60 -> -38 | E60: =(SUMIFS(周检修业务统计数据!I:I,周检修业务统计数据!B:B,B60,周检修业务统计数据!C:C,"干箱",周检修业务统计数据!D:D,"COS")+SUMIFS(周检修业务统计数据!J:J,周检修业务统计数据!B:B,B60,周检修业务统计数据!C:C,"干箱",周检修业务统计数据!D:D,"COS"))*1.13 -> 1744.71 | F60: =(E60-'2025年18周'!E60)/'2025年18周'!E60 -> -0.6111 | G60: =E60/C60 -> 42 | H60: =(G60-'2025年18周'!G60)/'2025年18周'!G60 -> -0.25 | I60: =SUMIFS(周检修业务统计数据!L:L,周检修业务统计数据!B:B,B60,周检修业务统计数据!C:C,"干箱",周检修业务统计数据!D:D,"COS")*1.06 -> 2450.084 | J60: =SUMIFS(周检修业务统计数据!E:E,周检修业务统计数据!B:B,B60,周检修业务统计数据!C:C,"干箱",周检修业务统计数据!D:D,"<>COS") -> 0 | K60: =J60-'2025年18周'!J60 -> 0 | L60: =(SUMIFS(周检修业务统计数据!I:I,周检修业务统计数据!B:B,B60,周检修业务统计数据!C:C,"干箱",周检修业务统计数据!D:D,"<>COS")+SUMIFS(周检修业务统计数据!J:J,周检修业务统计数据!B:B,B60,周检修业务统计数据!C:C,"干箱",周检修业务统计数据!D:D,"<>COS"))*1.13++SUMIFS(周检修业务统计数据!L:L,周检修业务统计数据!B:B,B60,周检修业务统计数据!C:C,"干箱",周检修业务统计数据!D:D,"<>COS")*1.06 -> 0 | M60: =(L60-'2025年18周'!L60)/'2025年18周'!L60 -> #DIV/0! | N60: =L60/J60 -> #DIV/0! | O60: =(N60-'2025年18周'!N60)/'2025年18周'!N60 -> #DIV/0! | P60: =(SUMIFS(周检修业务统计数据!I:I,周检修业务统计数据!B:B,B60,周检修业务统计数据!C:C,"<>干箱")+SUMIFS(周检修业务统计数据!J:J,周检修业务统计数据!B:B,B60,周检修业务统计数据!C:C,"<>干箱"))*1.13++SUMIFS(周检修业务统计数据!L:L,周检修业务统计数据!B:B,B60,周检修业务统计数据!C:C,"<>干箱")*1.06 -> 0 | S60: =S203 -> 0 | T60: =C60+J60 -> 42 | U60: =E60+L60+I60+P60+Q60+R60+S60 -> 4195
A61: 广州运营中心 | B61: 惠州龙溪 | C61: =SUMIFS(周检修业务统计数据!E:E,周检修业务统计数据!B:B,B61,周检修业务统计数据!C:C,"干箱",周检修业务统计数据!D:D,"COS") -> 308 | D61: =C61-'2025年18周'!C61 -> -313 | E61: =(SUMIFS(周检修业务统计数据!I:I,周检修业务统计数据!B:B,B61,周检修业务统计数据!C:C,"干箱",周检修业务统计数据!D:D,"COS")+SUMIFS(周检修业务统计数据!J:J,周检修业务统计数据!B:B,B61,周检修业务统计数据!C:C,"干箱",周检修业务统计数据!D:D,"COS"))*1.13 -> 43197.69 | F61: =(E61-'2025年18周'!E61)/'2025年18周'!E61 -> -0.5777 | G61: =E61/C61 -> 140 | H61: =(G61-'2025年18周'!G61)/'2025年18周'!G61 -> -0.1515 | I61: =SUMIFS(周检修业务统计数据!L:L,周检修业务统计数据!B:B,B61,周检修业务统计数据!C:C,"干箱",周检修业务统计数据!D:D,"COS")*1.06 -> 18740.291 | J61: =SUMIFS(周检修业务统计数据!E:E,周检修业务统计数据!B:B,B61,周检修业务统计数据!C:C,"干箱",周检修业务统计数据!D:D,"<>COS") -> 1 | K61: =J61-'2025年18周'!J61 -> -1 | L61: =(SUMIFS(周检修业务统计数据!I:I,周检修业务统计数据!B:B,B61,周检修业务统计数据!C:C,"干箱",周检修业务统计数据!D:D,"<>COS")+SUMIFS(周检修业务统计数据!J:J,周检修业务统计数据!B:B,B61,周检修业务统计数据!C:C,"干箱",周检修业务统计数据!D:D,"<>COS"))*1.13++SUMIFS(周检修业务统计数据!L:L,周检修业务统计数据!B:B,B61,周检修业务统计数据!C:C,"干箱",周检修业务统计数据!D:D,"<>COS")*1.06 -> 407.7 | M61: =(L61-'2025年18周'!L61)/'2025年18周'!L61 -> 0.1455 | N61: =L61/J61 -> 408 | O61: =(N61-'2025年18周'!N61)/'2025年18周'!N61 -> 1.2921 | P61: =(SUMIFS(周检修业务统计数据!I:I,周检修业务统计数据!B:B,B61,周检修业务统计数据!C:C,"<>干箱")+SUMIFS(周检修业务统计数据!J:J,周检修业务统计数据!B:B,B61,周检修业务统计数据!C:C,"<>干箱"))*1.13++SUMIFS(周检修业务统计数据!L:L,周检修业务统计数据!B:B,B61,周检修业务统计数据!C:C,"<>干箱")*1.06 -> 0 | R61: 7490 | S61: =S204 -> 0 | T61: =C61+J61 -> 309 | U61: =E61+L61+I61+P61+Q61+R61+S61 -> 69836 | V61: =(E61+L61)/W61 -> 8721 | W61: 5 | X61: 500 | Y61: =T61-X61 -> -191 | Z61: =X61*$Z$2 -> 9500 | AA61: =自营2026周完成情况!BB71 -> 9801 | AB61: =AA61-Z61 -> 301
A62: 珠三角运营中心 | B62: 佛山南庄 | C62: =SUMIFS(周检修业务统计数据!E:E,周检修业务统计数据!B:B,B62,周检修业务统计数据!C:C,"干箱",周检修业务统计数据!D:D,"COS") -> 232 | D62: =C62-'2025年18周'!C62 -> -160 | E62: =(SUMIFS(周检修业务统计数据!I:I,周检修业务统计数据!B:B,B62,周检修业务统计数据!C:C,"干箱",周检修业务统计数据!D:D,"COS")+SUMIFS(周检修业务统计数据!J:J,周检修业务统计数据!B:B,B62,周检修业务统计数据!C:C,"干箱",周检修业务统计数据!D:D,"COS"))*1.13 -> 49098.23 | F62: =(E62-'2025年18周'!E62)/'2025年18周'!E62 -> -0.4289 | G62: =E62/C62 -> 212 | H62: =(G62-'2025年18周'!G62)/'2025年18周'!G62 -> -0.032 | I62: =SUMIFS(周检修业务统计数据!L:L,周检修业务统计数据!B:B,B62,周检修业务统计数据!C:C,"干箱",周检修业务统计数据!D:D,"COS")*1.06 -> 12800.772 | J62: =SUMIFS(周检修业务统计数据!E:E,周检修业务统计数据!B:B,B62,周检修业务统计数据!C:C,"干箱",周检修业务统计数据!D:D,"<>COS") -> 0 | K62: =J62-'2025年18周'!J62 -> -18 | L62: =(SUMIFS(周检修业务统计数据!I:I,周检修业务统计数据!B:B,B62,周检修业务统计数据!C:C,"干箱",周检修业务统计数据!D:D,"<>COS")+SUMIFS(周检修业务统计数据!J:J,周检修业务统计数据!B:B,B62,周检修业务统计数据!C:C,"干箱",周检修业务统计数据!D:D,"<>COS"))*1.13++SUMIFS(周检修业务统计数据!L:L,周检修业务统计数据!B:B,B62,周检修业务统计数据!C:C,"干箱",周检修业务统计数据!D:D,"<>COS")*1.06 -> 0 | M62: =(L62-'2025年18周'!L62)/'2025年18周'!L62 -> -1 | N62: =L62/J62 -> #DIV/0! | O62: =(N62-'2025年18周'!N62)/'2025年18周'!N62 -> #DIV/0! | P62: =(SUMIFS(周检修业务统计数据!I:I,周检修业务统计数据!B:B,B62,周检修业务统计数据!C:C,"<>干箱")+SUMIFS(周检修业务统计数据!J:J,周检修业务统计数据!B:B,B62,周检修业务统计数据!C:C,"<>干箱"))*1.13++SUMIFS(周检修业务统计数据!L:L,周检修业务统计数据!B:B,B62,周检修业务统计数据!C:C,"<>干箱")*1.06 -> 0 | S62: =S205 -> 0 | T62: =C62+J62 -> 232 | U62: =E62+L62+I62+P62+Q62+R62+S62 -> 61899 | V62: =(E62+L62)/W62 -> 8183 | W62: 6 | X62: 450 | Y62: =T62-X62 -> -218 | Z62: =X62*$Z$2 -> 8550 | AA62: =自营2026周完成情况!BB72 -> 6412 | AB62: =AA62-Z62 -> -2138
A63: 珠三角运营中心 | B63: 白坭南拓 | C63: =SUMIFS(周检修业务统计数据!E:E,周检修业务统计数据!B:B,B63,周检修业务统计数据!C:C,"干箱",周检修业务统计数据!D:D,"COS") -> 53 | D63: =C63-'2025年18周'!C63 -> -76 | E63: =(SUMIFS(周检修业务统计数据!I:I,周检修业务统计数据!B:B,B63,周检修业务统计数据!C:C,"干箱",周检修业务统计数据!D:D,"COS")+SUMIFS(周检修业务统计数据!J:J,周检修业务统计数据!B:B,B63,周检修业务统计数据!C:C,"干箱",周检修业务统计数据!D:D,"COS"))*1.13 -> 12076.5 | F63: =(E63-'2025年18周'!E63)/'2025年18周'!E63 -> -0.7875 | G63: =E63/C63 -> 228 | H63: =(G63-'2025年18周'!G63)/'2025年18周'!G63 -> -0.483 | I63: =SUMIFS(周检修业务统计数据!L:L,周检修业务统计数据!B:B,B63,周检修业务统计数据!C:C,"干箱",周检修业务统计数据!D:D,"COS")*1.06 -> 2915.1802 | J63: =SUMIFS(周检修业务统计数据!E:E,周检修业务统计数据!B:B,B63,周检修业务统计数据!C:C,"干箱",周检修业务统计数据!D:D,"<>COS") -> 4 | K63: =J63-'2025年18周'!J63 -> -100 | L63: =(SUMIFS(周检修业务统计数据!I:I,周检修业务统计数据!B:B,B63,周检修业务统计数据!C:C,"干箱",周检修业务统计数据!D:D,"<>COS")+SUMIFS(周检修业务统计数据!J:J,周检修业务统计数据!B:B,B63,周检修业务统计数据!C:C,"干箱",周检修业务统计数据!D:D,"<>COS"))*1.13++SUMIFS(周检修业务统计数据!L:L,周检修业务统计数据!B:B,B63,周检修业务统计数据!C:C,"干箱",周检修业务统计数据!D:D,"<>COS")*1.06 -> 1763.72 | M63: =(L63-'2025年18周'!L63)/'2025年18周'!L63 -> -0.9542 | N63: =L63/J63 -> 441 | O63: =(N63-'2025年18周'!N63)/'2025年18周'!N63 -> 0.1919 | P63: =(SUMIFS(周检修业务统计数据!I:I,周检修业务统计数据!B:B,B63,周检修业务统计数据!C:C,"<>干箱")+SUMIFS(周检修业务统计数据!J:J,周检修业务统计数据!B:B,B63,周检修业务统计数据!C:C,"<>干箱"))*1.13++SUMIFS(周检修业务统计数据!L:L,周检修业务统计数据!B:B,B63,周检修业务统计数据!C:C,"<>干箱")*1.06 -> 0 | S63: =S206 -> 0 | T63: =C63+J63 -> 57 | U63: =E63+L63+I63+P63+Q63+R63+S63 -> 16755 | V63: =(E63+L63)/W63 -> 1730 | W63: 8 | X63: 300 | Y63: =T63-X63 -> -243 | Z63: =X63*$Z$2 -> 5700 | AA63: =自营2026周完成情况!BB73 -> 2170 | AB63: =AA63-Z63 -> -3530
A64: 珠三角运营中心 | B64: 佛山南鲲 | C64: =SUMIFS(周检修业务统计数据!E:E,周检修业务统计数据!B:B,B64,周检修业务统计数据!C:C,"干箱",周检修业务统计数据!D:D,"COS") -> 20 | D64: =C64-'2025年18周'!C64 -> -24 | E64: =(SUMIFS(周检修业务统计数据!I:I,周检修业务统计数据!B:B,B64,周检修业务统计数据!C:C,"干箱",周检修业务统计数据!D:D,"COS")+SUMIFS(周检修业务统计数据!J:J,周检修业务统计数据!B:B,B64,周检修业务统计数据!C:C,"干箱",周检修业务统计数据!D:D,"COS"))*1.13 -> 6131.79 | F64: =(E64-'2025年18周'!E64)/'2025年18周'!E64 -> -0.406 | G64: =E64/C64 -> 307 | H64: =(G64-'2025年18周'!G64)/'2025年18周'!G64 -> 0.3064 | I64: =SUMIFS(周检修业务统计数据!L:L,周检修业务统计数据!B:B,B64,周检修业务统计数据!C:C,"干箱",周检修业务统计数据!D:D,"COS")*1.06 -> 1100.068 | J64: =SUMIFS(周检修业务统计数据!E:E,周检修业务统计数据!B:B,B64,周检修业务统计数据!C:C,"干箱",周检修业务统计数据!D:D,"<>COS") -> 18 | K64: =J64-'2025年18周'!J64 -> -45 | L64: =(SUMIFS(周检修业务统计数据!I:I,周检修业务统计数据!B:B,B64,周检修业务统计数据!C:C,"干箱",周检修业务统计数据!D:D,"<>COS")+SUMIFS(周检修业务统计数据!J:J,周检修业务统计数据!B:B,B64,周检修业务统计数据!C:C,"干箱",周检修业务统计数据!D:D,"<>COS"))*1.13++SUMIFS(周检修业务统计数据!L:L,周检修业务统计数据!B:B,B64,周检修业务统计数据!C:C,"干箱",周检修业务统计数据!D:D,"<>COS")*1.06 -> 7008.82 | M64: =(L64-'2025年18周'!L64)/'2025年18周'!L64 -> -0.4865 | N64: =L64/J64 -> 389 | O64: =(N64-'2025年18周'!N64)/'2025年18周'!N64 -> 0.7926 | P64: =(SUMIFS(周检修业务统计数据!I:I,周检修业务统计数据!B:B,B64,周检修业务统计数据!C:C,"<>干箱")+SUMIFS(周检修业务统计数据!J:J,周检修业务统计数据!B:B,B64,周检修业务统计数据!C:C,"<>干箱"))*1.13++SUMIFS(周检修业务统计数据!L:L,周检修业务统计数据!B:B,B64,周检修业务统计数据!C:C,"<>干箱")*1.06 -> 0 | S64: =S207 -> 0 | T64: =C64+J64 -> 38 | U64: =E64+L64+I64+P64+Q64+R64+S64 -> 14241 | V64: =(E64+L64)/W64 -> 1877 | W64: 7 | X64: 150 | Y64: =T64-X64 -> -112 | Z64: =X64*$Z$2 -> 2850 | AA64: =自营2026周完成情况!BB74 -> 1326 | AB64: =AA64-Z64 -> -1524
A65: 珠三角运营中心 | B65: 佛山高明外堆场 | C65: =SUMIFS(周检修业务统计数据!E:E,周检修业务统计数据!B:B,B65,周检修业务统计数据!C:C,"干箱",周检修业务统计数据!D:D,"COS") -> 167 | D65: =C65-'2025年18周'!C65 -> -92 | E65: =(SUMIFS(周检修业务统计数据!I:I,周检修业务统计数据!B:B,B65,周检修业务统计数据!C:C,"干箱",周检修业务统计数据!D:D,"COS")+SUMIFS(周检修业务统计数据!J:J,周检修业务统计数据!B:B,B65,周检修业务统计数据!C:C,"干箱",周检修业务统计数据!D:D,"COS"))*1.13 -> 45307.46 | F65: =(E65-'2025年18周'!E65)/'2025年18周'!E65 -> -0.2037 | G65: =E65/C65 -> 271 | H65: =(G65-'2025年18周'!G65)/'2025年18周'!G65 -> 0.2318 | I65: =SUMIFS(周检修业务统计数据!L:L,周检修业务统计数据!B:B,B65,周检修业务统计数据!C:C,"干箱",周检修业务统计数据!D:D,"COS")*1.06 -> 0 | J65: =SUMIFS(周检修业务统计数据!E:E,周检修业务统计数据!B:B,B65,周检修业务统计数据!C:C,"干箱",周检修业务统计数据!D:D,"<>COS") -> 0 | K65: =J65-'2025年18周'!J65 -> 0 | L65: =(SUMIFS(周检修业务统计数据!I:I,周检修业务统计数据!B:B,B65,周检修业务统计数据!C:C,"干箱",周检修业务统计数据!D:D,"<>COS")+SUMIFS(周检修业务统计数据!J:J,周检修业务统计数据!B:B,B65,周检修业务统计数据!C:C,"干箱",周检修业务统计数据!D:D,"<>COS"))*1.13++SUMIFS(周检修业务统计数据!L:L,周检修业务统计数据!B:B,B65,周检修业务统计数据!C:C,"干箱",周检修业务统计数据!D:D,"<>COS")*1.06 -> 0 | M65: =(L65-'2025年18周'!L65)/'2025年18周'!L65 -> #DIV/0! | N65: =L65/J65 -> #DIV/0! | O65: =(N65-'2025年18周'!N65)/'2025年18周'!N65 -> #DIV/0! | P65: =(SUMIFS(周检修业务统计数据!I:I,周检修业务统计数据!B:B,B65,周检修业务统计数据!C:C,"<>干箱")+SUMIFS(周检修业务统计数据!J:J,周检修业务统计数据!B:B,B65,周检修业务统计数据!C:C,"<>干箱"))*1.13++SUMIFS(周检修业务统计数据!L:L,周检修业务统计数据!B:B,B65,周检修业务统计数据!C:C,"<>干箱")*1.06 -> 0 | Q65: 6882 | S65: =S208 -> 0 | T65: =C65+J65 -> 167 | U65: =E65+L65+I65+P65+Q65+R65+S65 -> 52189 | V65: =(E65+L65)/W65 -> 6472 | W65: 7 | X65: 350 | Y65: =SUM(T65:T67)-X65 -> -182 | Z65: =X65*$Z$2 -> 6650 | AA65: =SUM(自营2026周完成情况!BB75:BB77) -> 3925 | AB65: =AA65-Z65 -> -2725
A66: 珠三角运营中心 | B66: 佛山高明珠江码头 | C66: =SUMIFS(周检修业务统计数据!E:E,周检修业务统计数据!B:B,B66,周检修业务统计数据!C:C,"干箱",周检修业务统计数据!D:D,"COS") -> 0 | D66: =C66-'2025年18周'!C66 -> 0 | E66: =(SUMIFS(周检修业务统计数据!I:I,周检修业务统计数据!B:B,B66,周检修业务统计数据!C:C,"干箱",周检修业务统计数据!D:D,"COS")+SUMIFS(周检修业务统计数据!J:J,周检修业务统计数据!B:B,B66,周检修业务统计数据!C:C,"干箱",周检修业务统计数据!D:D,"COS"))*1.13 -> 0 | F66: =(E66-'2025年18周'!E66)/'2025年18周'!E66 -> #DIV/0! | G66: =E66/C66 -> #DIV/0! | H66: =(G66-'2025年18周'!G66)/'2025年18周'!G66 -> #DIV/0! | I66: =SUMIFS(周检修业务统计数据!L:L,周检修业务统计数据!B:B,B66,周检修业务统计数据!C:C,"干箱",周检修业务统计数据!D:D,"COS")*1.06 -> 0 | J66: =SUMIFS(周检修业务统计数据!E:E,周检修业务统计数据!B:B,B66,周检修业务统计数据!C:C,"干箱",周检修业务统计数据!D:D,"<>COS") -> 0 | K66: =J66-'2025年18周'!J66 -> 0 | L66: =(SUMIFS(周检修业务统计数据!I:I,周检修业务统计数据!B:B,B66,周检修业务统计数据!C:C,"干箱",周检修业务统计数据!D:D,"<>COS")+SUMIFS(周检修业务统计数据!J:J,周检修业务统计数据!B:B,B66,周检修业务统计数据!C:C,"干箱",周检修业务统计数据!D:D,"<>COS"))*1.13++SUMIFS(周检修业务统计数据!L:L,周检修业务统计数据!B:B,B66,周检修业务统计数据!C:C,"干箱",周检修业务统计数据!D:D,"<>COS")*1.06 -> 0 | M66: =(L66-'2025年18周'!L66)/'2025年18周'!L66 -> #DIV/0! | N66: =L66/J66 -> #DIV/0! | O66: =(N66-'2025年18周'!N66)/'2025年18周'!N66 -> #DIV/0! | P66: =(SUMIFS(周检修业务统计数据!I:I,周检修业务统计数据!B:B,B66,周检修业务统计数据!C:C,"<>干箱")+SUMIFS(周检修业务统计数据!J:J,周检修业务统计数据!B:B,B66,周检修业务统计数据!C:C,"<>干箱"))*1.13++SUMIFS(周检修业务统计数据!L:L,周检修业务统计数据!B:B,B66,周检修业务统计数据!C:C,"<>干箱")*1.06 -> 0 | S66: =S209 -> 0 | T66: =C66+J66 -> 0 | U66: =E66+L66+I66+P66+Q66+R66+S66 -> 0 | V66: =(E66+L66)/W66 -> #DIV/0! | W66: 0 | AC66: 优化给弘运高明珠江码头外包
A67: 珠三角运营中心 | B67: 佛山高明战备码头 | C67: =SUMIFS(周检修业务统计数据!E:E,周检修业务统计数据!B:B,B67,周检修业务统计数据!C:C,"干箱",周检修业务统计数据!D:D,"COS") -> 1 | D67: =C67-'2025年18周'!C67 -> -7 | E67: =(SUMIFS(周检修业务统计数据!I:I,周检修业务统计数据!B:B,B67,周检修业务统计数据!C:C,"干箱",周检修业务统计数据!D:D,"COS")+SUMIFS(周检修业务统计数据!J:J,周检修业务统计数据!B:B,B67,周检修业务统计数据!C:C,"干箱",周检修业务统计数据!D:D,"COS"))*1.13 -> 71.21 | F67: =(E67-'2025年18周'!E67)/'2025年18周'!E67 -> -0.8462 | G67: =E67/C67 -> 71 | H67: =(G67-'2025年18周'!G67)/'2025年18周'!G67 -> 0.2241 | I67: =SUMIFS(周检修业务统计数据!L:L,周检修业务统计数据!B:B,B67,周检修业务统计数据!C:C,"干箱",周检修业务统计数据!D:D,"COS")*1.06 -> 74.995 | J67: =SUMIFS(周检修业务统计数据!E:E,周检修业务统计数据!B:B,B67,周检修业务统计数据!C:C,"干箱",周检修业务统计数据!D:D,"<>COS") -> 0 | K67: =J67-'2025年18周'!J67 -> 0 | L67: =(SUMIFS(周检修业务统计数据!I:I,周检修业务统计数据!B:B,B67,周检修业务统计数据!C:C,"干箱",周检修业务统计数据!D:D,"<>COS")+SUMIFS(周检修业务统计数据!J:J,周检修业务统计数据!B:B,B67,周检修业务统计数据!C:C,"干箱",周检修业务统计数据!D:D,"<>COS"))*1.13++SUMIFS(周检修业务统计数据!L:L,周检修业务统计数据!B:B,B67,周检修业务统计数据!C:C,"干箱",周检修业务统计数据!D:D,"<>COS")*1.06 -> 0 | M67: =(L67-'2025年18周'!L67)/'2025年18周'!L67 -> #DIV/0! | N67: =L67/J67 -> #DIV/0! | O67: =(N67-'2025年18周'!N67)/'2025年18周'!N67 -> #DIV/0! | P67: =(SUMIFS(周检修业务统计数据!I:I,周检修业务统计数据!B:B,B67,周检修业务统计数据!C:C,"<>干箱")+SUMIFS(周检修业务统计数据!J:J,周检修业务统计数据!B:B,B67,周检修业务统计数据!C:C,"<>干箱"))*1.13++SUMIFS(周检修业务统计数据!L:L,周检修业务统计数据!B:B,B67,周检修业务统计数据!C:C,"<>干箱")*1.06 -> 0 | S67: =S210 -> 0 | T67: =C67+J67 -> 1 | U67: =E67+L67+I67+P67+Q67+R67+S67 -> 146 | V67: =(E67+L67)/W67 -> 71 | W67: 1
A68: 珠三角运营中心 | B68: 珠海高栏 | C68: =SUMIFS(周检修业务统计数据!E:E,周检修业务统计数据!B:B,B68,周检修业务统计数据!C:C,"干箱",周检修业务统计数据!D:D,"COS") -> 146 | D68: =C68-'2025年18周'!C68 -> -23 | E68: =(SUMIFS(周检修业务统计数据!I:I,周检修业务统计数据!B:B,B68,周检修业务统计数据!C:C,"干箱",周检修业务统计数据!D:D,"COS")+SUMIFS(周检修业务统计数据!J:J,周检修业务统计数据!B:B,B68,周检修业务统计数据!C:C,"干箱",周检修业务统计数据!D:D,"COS"))*1.13 -> 44291.28 | F68: =(E68-'2025年18周'!E68)/'2025年18周'!E68 -> -0.0386 | G68: =E68/C68 -> 303 | H68: =(G68-'2025年18周'!G68)/'2025年18周'!G68 -> 0.1099 | I68: =SUMIFS(周检修业务统计数据!L:L,周检修业务统计数据!B:B,B68,周检修业务统计数据!C:C,"干箱",周检修业务统计数据!D:D,"COS")*1.06 -> 8550.278 | J68: =SUMIFS(周检修业务统计数据!E:E,周检修业务统计数据!B:B,B68,周检修业务统计数据!C:C,"干箱",周检修业务统计数据!D:D,"<>COS") -> 0 | K68: =J68-'2025年18周'!J68 -> -5 | L68: =(SUMIFS(周检修业务统计数据!I:I,周检修业务统计数据!B:B,B68,周检修业务统计数据!C:C,"干箱",周检修业务统计数据!D:D,"<>COS")+SUMIFS(周检修业务统计数据!J:J,周检修业务统计数据!B:B,B68,周检修业务统计数据!C:C,"干箱",周检修业务统计数据!D:D,"<>COS"))*1.13++SUMIFS(周检修业务统计数据!L:L,周检修业务统计数据!B:B,B68,周检修业务统计数据!C:C,"干箱",周检修业务统计数据!D:D,"<>COS")*1.06 -> 0 | M68: =(L68-'2025年18周'!L68)/'2025年18周'!L68 -> -1 | N68: =L68/J68 -> #DIV/0! | O68: =(N68-'2025年18周'!N68)/'2025年18周'!N68 -> #DIV/0! | P68: =(SUMIFS(周检修业务统计数据!I:I,周检修业务统计数据!B:B,B68,周检修业务统计数据!C:C,"<>干箱")+SUMIFS(周检修业务统计数据!J:J,周检修业务统计数据!B:B,B68,周检修业务统计数据!C:C,"<>干箱"))*1.13++SUMIFS(周检修业务统计数据!L:L,周检修业务统计数据!B:B,B68,周检修业务统计数据!C:C,"<>干箱")*1.06 -> 0 | S68: =S211 -> 0 | T68: =C68+J68 -> 146 | U68: =E68+L68+I68+P68+Q68+R68+S68 -> 52842 | V68: =(E68+L68)/W68 -> 5536 | W68: 8 | X68: 350 | Y68: =T68-X68 -> -204 | Z68: =X68*$Z$2 -> 6650 | AA68: =自营2026周完成情况!BB78 -> 5798 | AB68: =AA68-Z68 -> -852
A69: 珠三角运营中心 | B69: 肇庆南江 | C69: =SUMIFS(周检修业务统计数据!E:E,周检修业务统计数据!B:B,B69,周检修业务统计数据!C:C,"干箱",周检修业务统计数据!D:D,"COS") -> 35 | D69: =C69-'2025年18周'!C69 -> -82 | E69: =(SUMIFS(周检修业务统计数据!I:I,周检修业务统计数据!B:B,B69,周检修业务统计数据!C:C,"干箱",周检修业务统计数据!D:D,"COS")+SUMIFS(周检修业务统计数据!J:J,周检修业务统计数据!B:B,B69,周检修业务统计数据!C:C,"干箱",周检修业务统计数据!D:D,"COS"))*1.13 -> 11979.22 | F69: =(E69-'2025年18周'!E69)/'2025年18周'!E69 -> -0.6987 | G69: =E69/C69 -> 342 | H69: =(G69-'2025年18周'!G69)/'2025年18周'!G69 -> 0.0059 | I69: =SUMIFS(周检修业务统计数据!L:L,周检修业务统计数据!B:B,B69,周检修业务统计数据!C:C,"干箱",周检修业务统计数据!D:D,"COS")*1.06 -> 1945.1106 | J69: =SUMIFS(周检修业务统计数据!E:E,周检修业务统计数据!B:B,B69,周检修业务统计数据!C:C,"干箱",周检修业务统计数据!D:D,"<>COS") -> 0 | K69: =J69-'2025年18周'!J69 -> 0 | L69: =(SUMIFS(周检修业务统计数据!I:I,周检修业务统计数据!B:B,B69,周检修业务统计数据!C:C,"干箱",周检修业务统计数据!D:D,"<>COS")+SUMIFS(周检修业务统计数据!J:J,周检修业务统计数据!B:B,B69,周检修业务统计数据!C:C,"干箱",周检修业务统计数据!D:D,"<>COS"))*1.13++SUMIFS(周检修业务统计数据!L:L,周检修业务统计数据!B:B,B69,周检修业务统计数据!C:C,"干箱",周检修业务统计数据!D:D,"<>COS")*1.06 -> 0 | M69: =(L69-'2025年18周'!L69)/'2025年18周'!L69 -> #DIV/0! | N69: =L69/J69 -> #DIV/0! | O69: =(N69-'2025年18周'!N69)/'2025年18周'!N69 -> #DIV/0! | P69: =(SUMIFS(周检修业务统计数据!I:I,周检修业务统计数据!B:B,B69,周检修业务统计数据!C:C,"<>干箱")+SUMIFS(周检修业务统计数据!J:J,周检修业务统计数据!B:B,B69,周检修业务统计数据!C:C,"<>干箱"))*1.13++SUMIFS(周检修业务统计数据!L:L,周检修业务统计数据!B:B,B69,周检修业务统计数据!C:C,"<>干箱")*1.06 -> 0 | S69: =S212 -> 0 | T69: =C69+J69 -> 35 | U69: =E69+L69+I69+P69+Q69+R69+S69 -> 13924 | V69: =(E69+L69)/W69 -> 2995 | W69: 4 | X69: 200 | Y69: =T69-X69 -> -165 | Z69: =X69*$Z$2 -> 3800 | AA69: =自营2026周完成情况!BB79 -> 2438 | AB69: =AA69-Z69 -> -1362
A70: 珠三角运营中心 | B70: 肇庆新港 | C70: =SUMIFS(周检修业务统计数据!E:E,周检修业务统计数据!B:B,B70,周检修业务统计数据!C:C,"干箱",周检修业务统计数据!D:D,"COS") -> 73 | D70: =C70-'2025年18周'!C70 -> -25 | E70: =(SUMIFS(周检修业务统计数据!I:I,周检修业务统计数据!B:B,B70,周检修业务统计数据!C:C,"干箱",周检修业务统计数据!D:D,"COS")+SUMIFS(周检修业务统计数据!J:J,周检修业务统计数据!B:B,B70,周检修业务统计数据!C:C,"干箱",周检修业务统计数据!D:D,"COS"))*1.13 -> 6239.65 | F70: =(E70-'2025年18周'!E70)/'2025年18周'!E70 -> -0.3749 | G70: =E70/C70 -> 85 | H70: =(G70-'2025年18周'!G70)/'2025年18周'!G70 -> -0.1667 | I70: =SUMIFS(周检修业务统计数据!L:L,周检修业务统计数据!B:B,B70,周检修业务统计数据!C:C,"干箱",周检修业务统计数据!D:D,"COS")*1.06 -> 4335.1138 | J70: =SUMIFS(周检修业务统计数据!E:E,周检修业务统计数据!B:B,B70,周检修业务统计数据!C:C,"干箱",周检修业务统计数据!D:D,"<>COS") -> 0 | K70: =J70-'2025年18周'!J70 -> 0 | L70: =(SUMIFS(周检修业务统计数据!I:I,周检修业务统计数据!B:B,B70,周检修业务统计数据!C:C,"干箱",周检修业务统计数据!D:D,"<>COS")+SUMIFS(周检修业务统计数据!J:J,周检修业务统计数据!B:B,B70,周检修业务统计数据!C:C,"干箱",周检修业务统计数据!D:D,"<>COS"))*1.13++SUMIFS(周检修业务统计数据!L:L,周检修业务统计数据!B:B,B70,周检修业务统计数据!C:C,"干箱",周检修业务统计数据!D:D,"<>COS")*1.06 -> 0 | M70: =(L70-'2025年18周'!L70)/'2025年18周'!L70 -> #DIV/0! | N70: =L70/J70 -> #DIV/0! | O70: =(N70-'2025年18周'!N70)/'2025年18周'!N70 -> #DIV/0! | P70: =(SUMIFS(周检修业务统计数据!I:I,周检修业务统计数据!B:B,B70,周检修业务统计数据!C:C,"<>干箱")+SUMIFS(周检修业务统计数据!J:J,周检修业务统计数据!B:B,B70,周检修业务统计数据!C:C,"<>干箱"))*1.13++SUMIFS(周检修业务统计数据!L:L,周检修业务统计数据!B:B,B70,周检修业务统计数据!C:C,"<>干箱")*1.06 -> 0 | S70: =S213 -> 0 | T70: =C70+J70 -> 73 | U70: =E70+L70+I70+P70+Q70+R70+S70 -> 10575 | V70: =(E70+L70)/W70 -> 3120 | W70: 2 | X70: 100 | Y70: =T70-X70 -> -27 | Z70: =X70*$Z$2 -> 1900 | AA70: =自营2026周完成情况!BB80 -> 1451 | AB70: =AA70-Z70 -> -449
A71: 珠三角运营中心 | B71: 江门外海 | C71: =SUMIFS(周检修业务统计数据!E:E,周检修业务统计数据!B:B,B71,周检修业务统计数据!C:C,"干箱",周检修业务统计数据!D:D,"COS") -> 94 | D71: =C71-'2025年18周'!C71 -> -120 | E71: =(SUMIFS(周检修业务统计数据!I:I,周检修业务统计数据!B:B,B71,周检修业务统计数据!C:C,"干箱",周检修业务统计数据!D:D,"COS")+SUMIFS(周检修业务统计数据!J:J,周检修业务统计数据!B:B,B71,周检修业务统计数据!C:C,"干箱",周检修业务统计数据!D:D,"COS"))*1.13 -> 33749.57 | F71: =(E71-'2025年18周'!E71)/'2025年18周'!E71 -> -0.4785 | G71: =E71/C71 -> 359 | H71: =(G71-'2025年18周'!G71)/'2025年18周'!G71 -> 0.1887 | I71: =SUMIFS(周检修业务统计数据!L:L,周检修业务统计数据!B:B,B71,周检修业务统计数据!C:C,"干箱",周检修业务统计数据!D:D,"COS")*1.06 -> 6009.9668 | J71: =SUMIFS(周检修业务统计数据!E:E,周检修业务统计数据!B:B,B71,周检修业务统计数据!C:C,"干箱",周检修业务统计数据!D:D,"<>COS") -> 17 | K71: =J71-'2025年18周'!J71 -> -30 | L71: =(SUMIFS(周检修业务统计数据!I:I,周检修业务统计数据!B:B,B71,周检修业务统计数据!C:C,"干箱",周检修业务统计数据!D:D,"<>COS")+SUMIFS(周检修业务统计数据!J:J,周检修业务统计数据!B:B,B71,周检修业务统计数据!C:C,"干箱",周检修业务统计数据!D:D,"<>COS"))*1.13++SUMIFS(周检修业务统计数据!L:L,周检修业务统计数据!B:B,B71,周检修业务统计数据!C:C,"干箱",周检修业务统计数据!D:D,"<>COS")*1.06 -> 6415.04 | M71: =(L71-'2025年18周'!L71)/'2025年18周'!L71 -> -0.5748 | N71: =L71/J71 -> 377 | O71: =(N71-'2025年18周'!N71)/'2025年18周'!N71 -> 0.1745 | P71: =(SUMIFS(周检修业务统计数据!I:I,周检修业务统计数据!B:B,B71,周检修业务统计数据!C:C,"<>干箱")+SUMIFS(周检修业务统计数据!J:J,周检修业务统计数据!B:B,B71,周检修业务统计数据!C:C,"<>干箱"))*1.13++SUMIFS(周检修业务统计数据!L:L,周检修业务统计数据!B:B,B71,周检修业务统计数据!C:C,"<>干箱")*1.06 -> 0 | S71: =S214 -> 0 | T71: =C71+J71 -> 111 | U71: =E71+L71+I71+P71+Q71+R71+S71 -> 46175 | V71: =(E71+L71)/W71 -> 8033 | W71: 5 | X71: 200 | Y71: =T71-X71 -> -89 | Z71: =X71*$Z$2 -> 3800 | AA71: =自营2026周完成情况!BB81 -> 3364 | AB71: =AA71-Z71 -> -436
A72: 珠三角运营中心 | B72: 贵阳陆港铁路场 | C72: =SUMIFS(周检修业务统计数据!E:E,周检修业务统计数据!B:B,B72,周检修业务统计数据!C:C,"干箱",周检修业务统计数据!D:D,"COS") -> 0 | D72: =C72-'2025年18周'!C72 -> -5 | E72: =(SUMIFS(周检修业务统计数据!I:I,周检修业务统计数据!B:B,B72,周检修业务统计数据!C:C,"干箱",周检修业务统计数据!D:D,"COS")+SUMIFS(周检修业务统计数据!J:J,周检修业务统计数据!B:B,B72,周检修业务统计数据!C:C,"干箱",周检修业务统计数据!D:D,"COS"))*1.13 -> 0 | F72: =(E72-'2025年18周'!E72)/'2025年18周'!E72 -> -1 | G72: =E72/C72 -> #DIV/0! | H72: =(G72-'2025年18周'!G72)/'2025年18周'!G72 -> #DIV/0! | I72: =SUMIFS(周检修业务统计数据!L:L,周检修业务统计数据!B:B,B72,周检修业务统计数据!C:C,"干箱",周检修业务统计数据!D:D,"COS")*1.06 -> 0 | J72: =SUMIFS(周检修业务统计数据!E:E,周检修业务统计数据!B:B,B72,周检修业务统计数据!C:C,"干箱",周检修业务统计数据!D:D,"<>COS") -> 0 | K72: =J72-'2025年18周'!J72 -> 0 | L72: =(SUMIFS(周检修业务统计数据!I:I,周检修业务统计数据!B:B,B72,周检修业务统计数据!C:C,"干箱",周检修业务统计数据!D:D,"<>COS")+SUMIFS(周检修业务统计数据!J:J,周检修业务统计数据!B:B,B72,周检修业务统计数据!C:C,"干箱",周检修业务统计数据!D:D,"<>COS"))*1.13++SUMIFS(周检修业务统计数据!L:L,周检修业务统计数据!B:B,B72,周检修业务统计数据!C:C,"干箱",周检修业务统计数据!D:D,"<>COS")*1.06 -> 0 | M72: =(L72-'2025年18周'!L72)/'2025年18周'!L72 -> #DIV/0! | N72: =L72/J72 -> #DIV/0! | O72: =(N72-'2025年18周'!N72)/'2025年18周'!N72 -> #DIV/0! | P72: =(SUMIFS(周检修业务统计数据!I:I,周检修业务统计数据!B:B,B72,周检修业务统计数据!C:C,"<>干箱")+SUMIFS(周检修业务统计数据!J:J,周检修业务统计数据!B:B,B72,周检修业务统计数据!C:C,"<>干箱"))*1.13++SUMIFS(周检修业务统计数据!L:L,周检修业务统计数据!B:B,B72,周检修业务统计数据!C:C,"<>干箱")*1.06 -> 0 | S72: =S215 -> 0 | T72: =C72+J72 -> 0 | U72: =E72+L72+I72+P72+Q72+R72+S72 -> 0 | V72: =(E72+L72)/W72 -> #DIV/0! | W72: 0 | X72: 0 | Y72: =T72-X72 -> 0 | Z72: =X72*$Z$2 -> 0 | AA72: =自营2026周完成情况!BB82 -> 84 | AB72: =AA72-Z72 -> 84 | AC72: 优化给坚迅江门九江坚迅
A73: 珠三角运营中心 | B73: 顺德乐从 | C73: =SUMIFS(周检修业务统计数据!E:E,周检修业务统计数据!B:B,B73,周检修业务统计数据!C:C,"干箱",周检修业务统计数据!D:D,"COS") -> 286 | D73: =C73-'2025年18周'!C73 -> -49 | E73: =(SUMIFS(周检修业务统计数据!I:I,周检修业务统计数据!B:B,B73,周检修业务统计数据!C:C,"干箱",周检修业务统计数据!D:D,"COS")+SUMIFS(周检修业务统计数据!J:J,周检修业务统计数据!B:B,B73,周检修业务统计数据!C:C,"干箱",周检修业务统计数据!D:D,"COS"))*1.13 -> 45761.59 | F73: =(E73-'2025年18周'!E73)/'2025年18周'!E73 -> -0.1031 | G73: =E73/C73 -> 160 | H73: =(G73-'2025年18周'!G73)/'2025年18周'!G73 -> 0.0526 | I73: =SUMIFS(周检修业务统计数据!L:L,周检修业务统计数据!B:B,B73,周检修业务统计数据!C:C,"干箱",周检修业务统计数据!D:D,"COS")*1.06 -> 18829.67 | J73: =SUMIFS(周检修业务统计数据!E:E,周检修业务统计数据!B:B,B73,周检修业务统计数据!C:C,"干箱",周检修业务统计数据!D:D,"<>COS") -> 0 | K73: =J73-'2025年18周'!J73 -> 0 | L73: =(SUMIFS(周检修业务统计数据!I:I,周检修业务统计数据!B:B,B73,周检修业务统计数据!C:C,"干箱",周检修业务统计数据!D:D,"<>COS")+SUMIFS(周检修业务统计数据!J:J,周检修业务统计数据!B:B,B73,周检修业务统计数据!C:C,"干箱",周检修业务统计数据!D:D,"<>COS"))*1.13++SUMIFS(周检修业务统计数据!L:L,周检修业务统计数据!B:B,B73,周检修业务统计数据!C:C,"干箱",周检修业务统计数据!D:D,"<>COS")*1.06 -> 0 | M73: =(L73-'2025年18周'!L73)/'2025年18周'!L73 -> #DIV/0! | N73: =L73/J73 -> #DIV/0! | O73: =(N73-'2025年18周'!N73)/'2025年18周'!N73 -> #DIV/0! | P73: =(SUMIFS(周检修业务统计数据!I:I,周检修业务统计数据!B:B,B73,周检修业务统计数据!C:C,"<>干箱")+SUMIFS(周检修业务统计数据!J:J,周检修业务统计数据!B:B,B73,周检修业务统计数据!C:C,"<>干箱"))*1.13++SUMIFS(周检修业务统计数据!L:L,周检修业务统计数据!B:B,B73,周检修业务统计数据!C:C,"<>干箱")*1.06 -> 0 | S73: =S216 -> 0 | T73: =C73+J73 -> 286 | U73: =E73+L73+I73+P73+Q73+R73+S73 -> 64591 | V73: =(E73+L73)/W73 -> 11440 | W73: 4 | X73: 380 | Y73: =T73-X73 -> -94 | Z73: =X73*$Z$2 -> 7220 | AA73: =自营2026周完成情况!BB83 -> 3732 | AB73: =AA73-Z73 -> -3488
A74: 珠三角运营中心 | B74: 佛山顺乐自营 | C74: =SUMIFS(周检修业务统计数据!E:E,周检修业务统计数据!B:B,B74,周检修业务统计数据!C:C,"干箱",周检修业务统计数据!D:D,"COS") -> 279 | D74: =C74-'2025年18周'!C74 -> -153 | E74: =(SUMIFS(周检修业务统计数据!I:I,周检修业务统计数据!B:B,B74,周检修业务统计数据!C:C,"干箱",周检修业务统计数据!D:D,"COS")+SUMIFS(周检修业务统计数据!J:J,周检修业务统计数据!B:B,B74,周检修业务统计数据!C:C,"干箱",周检修业务统计数据!D:D,"COS"))*1.13 -> 72786.61 | F74: =(E74-'2025年18周'!E74)/'2025年18周'!E74 -> -0.2144 | G74: =E74/C74 -> 261 | H74: =(G74-'2025年18周'!G74)/'2025年18周'!G74 -> 0.2196 | I74: =SUMIFS(周检修业务统计数据!L:L,周检修业务统计数据!B:B,B74,周检修业务统计数据!C:C,"干箱",周检修业务统计数据!D:D,"COS")*1.06 -> 15345.949 | J74: =SUMIFS(周检修业务统计数据!E:E,周检修业务统计数据!B:B,B74,周检修业务统计数据!C:C,"干箱",周检修业务统计数据!D:D,"<>COS") -> 0 | K74: =J74-'2025年18周'!J74 -> 0 | L74: =(SUMIFS(周检修业务统计数据!I:I,周检修业务统计数据!B:B,B74,周检修业务统计数据!C:C,"干箱",周检修业务统计数据!D:D,"<>COS")+SUMIFS(周检修业务统计数据!J:J,周检修业务统计数据!B:B,B74,周检修业务统计数据!C:C,"干箱",周检修业务统计数据!D:D,"<>COS"))*1.13++SUMIFS(周检修业务统计数据!L:L,周检修业务统计数据!B:B,B74,周检修业务统计数据!C:C,"干箱",周检修业务统计数据!D:D,"<>COS")*1.06 -> 0 | M74: =(L74-'2025年18周'!L74)/'2025年18周'!L74 -> #DIV/0! | N74: =L74/J74 -> #DIV/0! | O74: =(N74-'2025年18周'!N74)/'2025年18周'!N74 -> #DIV/0! | P74: =(SUMIFS(周检修业务统计数据!I:I,周检修业务统计数据!B:B,B74,周检修业务统计数据!C:C,"<>干箱")+SUMIFS(周检修业务统计数据!J:J,周检修业务统计数据!B:B,B74,周检修业务统计数据!C:C,"<>干箱"))*1.13++SUMIFS(周检修业务统计数据!L:L,周检修业务统计数据!B:B,B74,周检修业务统计数据!C:C,"<>干箱")*1.06 -> 0 | S74: =S217 -> 0 | T74: =C74+J74 -> 279 | U74: =E74+L74+I74+P74+Q74+R74+S74 -> 88133 | V74: =(E74+L74)/W74 -> 14557 | W74: 5 | X74: 300 | Y74: =T74-X74 -> -21 | Z74: =X74*$Z$2 -> 5700 | AA74: =自营2026周完成情况!BB84 -> 6327 | AB74: =AA74-Z74 -> 627
A75: 珠三角运营中心 | B75: 顺德中储粮 | C75: =SUMIFS(周检修业务统计数据!E:E,周检修业务统计数据!B:B,B75,周检修业务统计数据!C:C,"干箱",周检修业务统计数据!D:D,"COS") -> 0 | D75: =C75-'2025年18周'!C75 -> 0 | E75: =(SUMIFS(周检修业务统计数据!I:I,周检修业务统计数据!B:B,B75,周检修业务统计数据!C:C,"干箱",周检修业务统计数据!D:D,"COS")+SUMIFS(周检修业务统计数据!J:J,周检修业务统计数据!B:B,B75,周检修业务统计数据!C:C,"干箱",周检修业务统计数据!D:D,"COS"))*1.13 -> 0 | F75: =(E75-'2025年18周'!E75)/'2025年18周'!E75 -> #DIV/0! | G75: =E75/C75 -> #DIV/0! | H75: =(G75-'2025年18周'!G75)/'2025年18周'!G75 -> #DIV/0! | I75: =SUMIFS(周检修业务统计数据!L:L,周检修业务统计数据!B:B,B75,周检修业务统计数据!C:C,"干箱",周检修业务统计数据!D:D,"COS")*1.06 -> 0 | J75: =SUMIFS(周检修业务统计数据!E:E,周检修业务统计数据!B:B,B75,周检修业务统计数据!C:C,"干箱",周检修业务统计数据!D:D,"<>COS") -> 0 | K75: =J75-'2025年18周'!J75 -> 0 | L75: =(SUMIFS(周检修业务统计数据!I:I,周检修业务统计数据!B:B,B75,周检修业务统计数据!C:C,"干箱",周检修业务统计数据!D:D,"<>COS")+SUMIFS(周检修业务统计数据!J:J,周检修业务统计数据!B:B,B75,周检修业务统计数据!C:C,"干箱",周检修业务统计数据!D:D,"<>COS"))*1.13++SUMIFS(周检修业务统计数据!L:L,周检修业务统计数据!B:B,B75,周检修业务统计数据!C:C,"干箱",周检修业务统计数据!D:D,"<>COS")*1.06 -> 0 | M75: =(L75-'2025年18周'!L75)/'2025年18周'!L75 -> #DIV/0! | N75: =L75/J75 -> #DIV/0! | O75: =(N75-'2025年18周'!N75)/'2025年18周'!N75 -> #DIV/0! | P75: =(SUMIFS(周检修业务统计数据!I:I,周检修业务统计数据!B:B,B75,周检修业务统计数据!C:C,"<>干箱")+SUMIFS(周检修业务统计数据!J:J,周检修业务统计数据!B:B,B75,周检修业务统计数据!C:C,"<>干箱"))*1.13++SUMIFS(周检修业务统计数据!L:L,周检修业务统计数据!B:B,B75,周检修业务统计数据!C:C,"<>干箱")*1.06 -> 0 | S75: =S218 -> 0 | T75: =C75+J75 -> 0 | U75: =E75+L75+I75+P75+Q75+R75+S75 -> 0 | V75: =(E75+L75)/W75 -> #DIV/0! | W75: 0 | X75: 20 | Y75: =T75-X75 -> -20 | Z75: =X75*$Z$2 -> 380 | AA75: =自营2026周完成情况!BB85 -> 15 | AB75: =AA75-Z75 -> -365
A76: 珠三角运营中心 | B76: 高明高荷码头 | C76: =SUMIFS(周检修业务统计数据!E:E,周检修业务统计数据!B:B,B76,周检修业务统计数据!C:C,"干箱",周检修业务统计数据!D:D,"COS") -> 45 | D76: =C76-'2025年18周'!C76 -> -37 | E76: =(SUMIFS(周检修业务统计数据!I:I,周检修业务统计数据!B:B,B76,周检修业务统计数据!C:C,"干箱",周检修业务统计数据!D:D,"COS")+SUMIFS(周检修业务统计数据!J:J,周检修业务统计数据!B:B,B76,周检修业务统计数据!C:C,"干箱",周检修业务统计数据!D:D,"COS"))*1.13 -> 1602.28 | F76: =(E76-'2025年18周'!E76)/'2025年18周'!E76 -> -0.4512 | G76: =E76/C76 -> 36 | H76: =(G76-'2025年18周'!G76)/'2025年18周'!G76 -> 0 | I76: =SUMIFS(周检修业务统计数据!L:L,周检修业务统计数据!B:B,B76,周检修业务统计数据!C:C,"干箱",周检修业务统计数据!D:D,"COS")*1.06 -> 2475.153 | J76: =SUMIFS(周检修业务统计数据!E:E,周检修业务统计数据!B:B,B76,周检修业务统计数据!C:C,"干箱",周检修业务统计数据!D:D,"<>COS") -> 1 | K76: =J76-'2025年18周'!J76 -> -11 | L76: =(SUMIFS(周检修业务统计数据!I:I,周检修业务统计数据!B:B,B76,周检修业务统计数据!C:C,"干箱",周检修业务统计数据!D:D,"<>COS")+SUMIFS(周检修业务统计数据!J:J,周检修业务统计数据!B:B,B76,周检修业务统计数据!C:C,"干箱",周检修业务统计数据!D:D,"<>COS"))*1.13++SUMIFS(周检修业务统计数据!L:L,周检修业务统计数据!B:B,B76,周检修业务统计数据!C:C,"干箱",周检修业务统计数据!D:D,"<>COS")*1.06 -> 209.9 | M76: =(L76-'2025年18周'!L76)/'2025年18周'!L76 -> -0.909 | N76: =L76/J76 -> 210 | O76: =(N76-'2025年18周'!N76)/'2025年18周'!N76 -> 0.0938 | P76: =(SUMIFS(周检修业务统计数据!I:I,周检修业务统计数据!B:B,B76,周检修业务统计数据!C:C,"<>干箱")+SUMIFS(周检修业务统计数据!J:J,周检修业务统计数据!B:B,B76,周检修业务统计数据!C:C,"<>干箱"))*1.13++SUMIFS(周检修业务统计数据!L:L,周检修业务统计数据!B:B,B76,周检修业务统计数据!C:C,"<>干箱")*1.06 -> 0 | S76: =S219 -> 0 | T76: =C76+J76 -> 46 | U76: =E76+L76+I76+P76+Q76+R76+S76 -> 4287 | V76: =(E76+L76)/W76 -> 604 | W76: 3 | X76: 200 | Y76: =T76-X76 -> -154 | Z76: =X76*$Z$2 -> 3800 | AA76: =自营2026周完成情况!BB86 -> 1554 | AB76: =AA76-Z76 -> -2246 | AC76: 2023年9月15号新增高荷场站
A77: 粤西运营中心 | B77: 湛江外堆场 | C77: =SUMIFS(周检修业务统计数据!E:E,周检修业务统计数据!B:B,B77,周检修业务统计数据!C:C,"干箱",周检修业务统计数据!D:D,"COS") -> 291 | D77: =C77-'2025年18周'!C77 -> -336 | E77: =(SUMIFS(周检修业务统计数据!I:I,周检修业务统计数据!B:B,B77,周检修业务统计数据!C:C,"干箱",周检修业务统计数据!D:D,"COS")+SUMIFS(周检修业务统计数据!J:J,周检修业务统计数据!B:B,B77,周检修业务统计数据!C:C,"干箱",周检修业务统计数据!D:D,"COS"))*1.13 -> 89546.05 | F77: =(E77-'2025年18周'!E77)/'2025年18周'!E77 -> -0.6275 | G77: =E77/C77 -> 308 | H77: =(G77-'2025年18周'!G77)/'2025年18周'!G77 -> -0.1958 | I77: =SUMIFS(周检修业务统计数据!L:L,周检修业务统计数据!B:B,B77,周检修业务统计数据!C:C,"干箱",周检修业务统计数据!D:D,"COS")*1.06 -> 0 | J77: =SUMIFS(周检修业务统计数据!E:E,周检修业务统计数据!B:B,B77,周检修业务统计数据!C:C,"干箱",周检修业务统计数据!D:D,"<>COS") -> 0 | K77: =J77-'2025年18周'!J77 -> 0 | L77: =(SUMIFS(周检修业务统计数据!I:I,周检修业务统计数据!B:B,B77,周检修业务统计数据!C:C,"干箱",周检修业务统计数据!D:D,"<>COS")+SUMIFS(周检修业务统计数据!J:J,周检修业务统计数据!B:B,B77,周检修业务统计数据!C:C,"干箱",周检修业务统计数据!D:D,"<>COS"))*1.13++SUMIFS(周检修业务统计数据!L:L,周检修业务统计数据!B:B,B77,周检修业务统计数据!C:C,"干箱",周检修业务统计数据!D:D,"<>COS")*1.06 -> 0 | M77: =(L77-'2025年18周'!L77)/'2025年18周'!L77 -> #DIV/0! | N77: =L77/J77 -> #DIV/0! | O77: =(N77-'2025年18周'!N77)/'2025年18周'!N77 -> #DIV/0! | P77: =(SUMIFS(周检修业务统计数据!I:I,周检修业务统计数据!B:B,B77,周检修业务统计数据!C:C,"<>干箱")+SUMIFS(周检修业务统计数据!J:J,周检修业务统计数据!B:B,B77,周检修业务统计数据!C:C,"<>干箱"))*1.13++SUMIFS(周检修业务统计数据!L:L,周检修业务统计数据!B:B,B77,周检修业务统计数据!C:C,"<>干箱")*1.06 -> 0 | Q77: 7155.66 | R77: 10505 | S77: =S220 -> 0 | T77: =C77+J77 -> 291 | U77: =E77+L77+I77+P77+Q77+R77+S77 -> 107207 | V77: =(E77+L77+E78+L78)/W77 -> 10259 | W77: 18 | X77: 1000 | Y77: =SUM(T77:T78)-X77 -> 17 | Z77: =X77*$Z$2 -> 19000 | AA77: =SUM(自营2026周完成情况!BB87:BB88) -> 21512 | AB77: =AA77-Z77 -> 2512 | AC77: 2023年11月新增湛江外堆场
A78: 粤西运营中心 | B78: 湛江港 | C78: =SUMIFS(周检修业务统计数据!E:E,周检修业务统计数据!B:B,B78,周检修业务统计数据!C:C,"干箱",周检修业务统计数据!D:D,"COS") -> 630 | D78: =C78-'2025年18周'!C78 -> 60 | E78: =(SUMIFS(周检修业务统计数据!I:I,周检修业务统计数据!B:B,B78,周检修业务统计数据!C:C,"干箱",周检修业务统计数据!D:D,"COS")+SUMIFS(周检修业务统计数据!J:J,周检修业务统计数据!B:B,B78,周检修业务统计数据!C:C,"干箱",周检修业务统计数据!D:D,"COS"))*1.13 -> 77900.38 | F78: =(E78-'2025年18周'!E78)/'2025年18周'!E78 -> -0.0156 | G78: =E78/C78 -> 124 | H78: =(G78-'2025年18周'!G78)/'2025年18周'!G78 -> -0.1079 | I78: =SUMIFS(周检修业务统计数据!L:L,周检修业务统计数据!B:B,B78,周检修业务统计数据!C:C,"干箱",周检修业务统计数据!D:D,"COS")*1.06 -> 40369.74 | J78: =SUMIFS(周检修业务统计数据!E:E,周检修业务统计数据!B:B,B78,周检修业务统计数据!C:C,"干箱",周检修业务统计数据!D:D,"<>COS") -> 96 | K78: =J78-'2025年18周'!J78 -> 53 | L78: =(SUMIFS(周检修业务统计数据!I:I,周检修业务统计数据!B:B,B78,周检修业务统计数据!C:C,"干箱",周检修业务统计数据!D:D,"<>COS")+SUMIFS(周检修业务统计数据!J:J,周检修业务统计数据!B:B,B78,周检修业务统计数据!C:C,"干箱",周检修业务统计数据!D:D,"<>COS"))*1.13++SUMIFS(周检修业务统计数据!L:L,周检修业务统计数据!B:B,B78,周检修业务统计数据!C:C,"干箱",周检修业务统计数据!D:D,"<>COS")*1.06 -> 17219.58 | M78: =(L78-'2025年18周'!L78)/'2025年18周'!L78 -> 0.406 | N78: =L78/J78 -> 179 | O78: =(N78-'2025年18周'!N78)/'2025年18周'!N78 -> -0.3719 | P78: =(SUMIFS(周检修业务统计数据!I:I,周检修业务统计数据!B:B,B78,周检修业务统计数据!C:C,"<>干箱")+SUMIFS(周检修业务统计数据!J:J,周检修业务统计数据!B:B,B78,周检修业务统计数据!C:C,"<>干箱"))*1.13++SUMIFS(周检修业务统计数据!L:L,周检修业务统计数据!B:B,B78,周检修业务统计数据!C:C,"<>干箱")*1.06 -> 749.89 | S78: =S221 -> 0 | T78: =C78+J78 -> 726 | U78: =E78+L78+I78+P78+Q78+R78+S78 -> 136240
A79: 粤西运营中心 | B79: 水东 | C79: =SUMIFS(周检修业务统计数据!E:E,周检修业务统计数据!B:B,B79,周检修业务统计数据!C:C,"干箱",周检修业务统计数据!D:D,"COS") -> 117 | D79: =C79-'2025年18周'!C79 -> -17 | E79: =(SUMIFS(周检修业务统计数据!I:I,周检修业务统计数据!B:B,B79,周检修业务统计数据!C:C,"干箱",周检修业务统计数据!D:D,"COS")+SUMIFS(周检修业务统计数据!J:J,周检修业务统计数据!B:B,B79,周检修业务统计数据!C:C,"干箱",周检修业务统计数据!D:D,"COS"))*1.13 -> 48196.12 | F79: =(E79-'2025年18周'!E79)/'2025年18周'!E79 -> 0.5621 | G79: =E79/C79 -> 412 | H79: =(G79-'2025年18周'!G79)/'2025年18周'!G79 -> 0.7913 | I79: =SUMIFS(周检修业务统计数据!L:L,周检修业务统计数据!B:B,B79,周检修业务统计数据!C:C,"干箱",周检修业务统计数据!D:D,"COS")*1.06 -> 6635.3138 | J79: =SUMIFS(周检修业务统计数据!E:E,周检修业务统计数据!B:B,B79,周检修业务统计数据!C:C,"干箱",周检修业务统计数据!D:D,"<>COS") -> 0 | K79: =J79-'2025年18周'!J79 -> 0 | L79: =(SUMIFS(周检修业务统计数据!I:I,周检修业务统计数据!B:B,B79,周检修业务统计数据!C:C,"干箱",周检修业务统计数据!D:D,"<>COS")+SUMIFS(周检修业务统计数据!J:J,周检修业务统计数据!B:B,B79,周检修业务统计数据!C:C,"干箱",周检修业务统计数据!D:D,"<>COS"))*1.13++SUMIFS(周检修业务统计数据!L:L,周检修业务统计数据!B:B,B79,周检修业务统计数据!C:C,"干箱",周检修业务统计数据!D:D,"<>COS")*1.06 -> 0 | M79: =(L79-'2025年18周'!L79)/'2025年18周'!L79 -> #DIV/0! | N79: =L79/J79 -> #DIV/0! | O79: =(N79-'2025年18周'!N79)/'2025年18周'!N79 -> #DIV/0! | P79: =(SUMIFS(周检修业务统计数据!I:I,周检修业务统计数据!B:B,B79,周检修业务统计数据!C:C,"<>干箱")+SUMIFS(周检修业务统计数据!J:J,周检修业务统计数据!B:B,B79,周检修业务统计数据!C:C,"<>干箱"))*1.13++SUMIFS(周检修业务统计数据!L:L,周检修业务统计数据!B:B,B79,周检修业务统计数据!C:C,"<>干箱")*1.06 -> 0 | S79: =S222 -> 0 | T79: =C79+J79 -> 117 | U79: =E79+L79+I79+P79+Q79+R79+S79 -> 54831 | V79: =(E79+L79)/W79 -> 16065 | W79: 3 | X79: 100 | Y79: =T79-X79 -> 17 | Z79: =X79*$Z$2 -> 1900 | AA79: =自营2026周完成情况!BB89 -> 2874 | AB79: =AA79-Z79 -> 974
A80: 北部湾运营中心 | B80: 防城港外堆场 | C80: =SUMIFS(周检修业务统计数据!E:E,周检修业务统计数据!B:B,B80,周检修业务统计数据!C:C,"干箱",周检修业务统计数据!D:D,"COS") -> 477 | D80: =C80-'2025年18周'!C80 -> -266 | E80: =(SUMIFS(周检修业务统计数据!I:I,周检修业务统计数据!B:B,B80,周检修业务统计数据!C:C,"干箱",周检修业务统计数据!D:D,"COS")+SUMIFS(周检修业务统计数据!J:J,周检修业务统计数据!B:B,B80,周检修业务统计数据!C:C,"干箱",周检修业务统计数据!D:D,"COS"))*1.13 -> 148364.15 | F80: =(E80-'2025年18周'!E80)/'2025年18周'!E80 -> -0.3663 | G80: =E80/C80 -> 311 | H80: =(G80-'2025年18周'!G80)/'2025年18周'!G80 -> -0.0127 | I80: =SUMIFS(周检修业务统计数据!L:L,周检修业务统计数据!B:B,B80,周检修业务统计数据!C:C,"干箱",周检修业务统计数据!D:D,"COS")*1.06 -> 0 | J80: =SUMIFS(周检修业务统计数据!E:E,周检修业务统计数据!B:B,B80,周检修业务统计数据!C:C,"干箱",周检修业务统计数据!D:D,"<>COS") -> 0 | K80: =J80-'2025年18周'!J80 -> 0 | L80: =(SUMIFS(周检修业务统计数据!I:I,周检修业务统计数据!B:B,B80,周检修业务统计数据!C:C,"干箱",周检修业务统计数据!D:D,"<>COS")+SUMIFS(周检修业务统计数据!J:J,周检修业务统计数据!B:B,B80,周检修业务统计数据!C:C,"干箱",周检修业务统计数据!D:D,"<>COS"))*1.13++SUMIFS(周检修业务统计数据!L:L,周检修业务统计数据!B:B,B80,周检修业务统计数据!C:C,"干箱",周检修业务统计数据!D:D,"<>COS")*1.06 -> 0 | M80: =(L80-'2025年18周'!L80)/'2025年18周'!L80 -> #DIV/0! | N80: =L80/J80 -> #DIV/0! | O80: =(N80-'2025年18周'!N80)/'2025年18周'!N80 -> #DIV/0! | P80: =(SUMIFS(周检修业务统计数据!I:I,周检修业务统计数据!B:B,B80,周检修业务统计数据!C:C,"<>干箱")+SUMIFS(周检修业务统计数据!J:J,周检修业务统计数据!B:B,B80,周检修业务统计数据!C:C,"<>干箱"))*1.13++SUMIFS(周检修业务统计数据!L:L,周检修业务统计数据!B:B,B80,周检修业务统计数据!C:C,"<>干箱")*1.06 -> 0 | Q80: 20091 | S80: =S223 -> 0 | T80: =C80+J80 -> 477 | U80: =E80+L80+I80+P80+Q80+R80+S80 -> 168455 | V80: =(E80+L80)/W80 -> 8242 | W80: 18 | X80: 800 | Y80: =SUM(T80:T81)-X80 -> -183 | Z80: =X80*$Z$2 -> 15200 | AA80: =SUM(自营2026周完成情况!BB90:BB91) -> 21448 | AB80: =AA80-Z80 -> 6248
A81: 北部湾运营中心 | B81: 防城港二堆场 | C81: =SUMIFS(周检修业务统计数据!E:E,周检修业务统计数据!B:B,B81,周检修业务统计数据!C:C,"干箱",周检修业务统计数据!D:D,"COS") -> 140 | D81: =C81-'2025年18周'!C81 -> -70 | E81: =(SUMIFS(周检修业务统计数据!I:I,周检修业务统计数据!B:B,B81,周检修业务统计数据!C:C,"干箱",周检修业务统计数据!D:D,"COS")+SUMIFS(周检修业务统计数据!J:J,周检修业务统计数据!B:B,B81,周检修业务统计数据!C:C,"干箱",周检修业务统计数据!D:D,"COS"))*1.13 -> 45588.62 | F81: =(E81-'2025年18周'!E81)/'2025年18周'!E81 -> -0.3252 | G81: =E81/C81 -> 326 | H81: =(G81-'2025年18周'!G81)/'2025年18周'!G81 -> 0.0124 | I81: =SUMIFS(周检修业务统计数据!L:L,周检修业务统计数据!B:B,B81,周检修业务统计数据!C:C,"干箱",周检修业务统计数据!D:D,"COS")*1.06 -> 0 | J81: =SUMIFS(周检修业务统计数据!E:E,周检修业务统计数据!B:B,B81,周检修业务统计数据!C:C,"干箱",周检修业务统计数据!D:D,"<>COS") -> 0 | K81: =J81-'2025年18周'!J81 -> 0 | L81: =(SUMIFS(周检修业务统计数据!I:I,周检修业务统计数据!B:B,B81,周检修业务统计数据!C:C,"干箱",周检修业务统计数据!D:D,"<>COS")+SUMIFS(周检修业务统计数据!J:J,周检修业务统计数据!B:B,B81,周检修业务统计数据!C:C,"干箱",周检修业务统计数据!D:D,"<>COS"))*1.13++SUMIFS(周检修业务统计数据!L:L,周检修业务统计数据!B:B,B81,周检修业务统计数据!C:C,"干箱",周检修业务统计数据!D:D,"<>COS")*1.06 -> 0 | M81: =(L81-'2025年18周'!L81)/'2025年18周'!L81 -> #DIV/0! | N81: =L81/J81 -> #DIV/0! | O81: =(N81-'2025年18周'!N81)/'2025年18周'!N81 -> #DIV/0! | P81: =(SUMIFS(周检修业务统计数据!I:I,周检修业务统计数据!B:B,B81,周检修业务统计数据!C:C,"<>干箱")+SUMIFS(周检修业务统计数据!J:J,周检修业务统计数据!B:B,B81,周检修业务统计数据!C:C,"<>干箱"))*1.13++SUMIFS(周检修业务统计数据!L:L,周检修业务统计数据!B:B,B81,周检修业务统计数据!C:C,"<>干箱")*1.06 -> 0 | Q81: 13135 | S81: =S224 -> 0 | T81: =C81+J81 -> 140 | U81: =E81+L81+I81+P81+Q81+R81+S81 -> 58724 | V81: =(E81+L81)/W81 -> 9118 | W81: 5
A82: 北部湾运营中心 | B82: 广西钦州外堆场自营 | C82: =SUMIFS(周检修业务统计数据!E:E,周检修业务统计数据!B:B,B82,周检修业务统计数据!C:C,"干箱",周检修业务统计数据!D:D,"COS") -> 881 | D82: =C82-'2025年18周'!C82 -> -114 | E82: =(SUMIFS(周检修业务统计数据!I:I,周检修业务统计数据!B:B,B82,周检修业务统计数据!C:C,"干箱",周检修业务统计数据!D:D,"COS")+SUMIFS(周检修业务统计数据!J:J,周检修业务统计数据!B:B,B82,周检修业务统计数据!C:C,"干箱",周检修业务统计数据!D:D,"COS"))*1.13 -> 243390.59 | F82: =(E82-'2025年18周'!E82)/'2025年18周'!E82 -> -0.2446 | G82: =E82/C82 -> 276 | H82: =(G82-'2025年18周'!G82)/'2025年18周'!G82 -> -0.1481 | I82: =SUMIFS(周检修业务统计数据!L:L,周检修业务统计数据!B:B,B82,周检修业务统计数据!C:C,"干箱",周检修业务统计数据!D:D,"COS")*1.06 -> 0 | J82: =SUMIFS(周检修业务统计数据!E:E,周检修业务统计数据!B:B,B82,周检修业务统计数据!C:C,"干箱",周检修业务统计数据!D:D,"<>COS") -> 15 | K82: =J82-'2025年18周'!J82 -> 1 | L82: =(SUMIFS(周检修业务统计数据!I:I,周检修业务统计数据!B:B,B82,周检修业务统计数据!C:C,"干箱",周检修业务统计数据!D:D,"<>COS")+SUMIFS(周检修业务统计数据!J:J,周检修业务统计数据!B:B,B82,周检修业务统计数据!C:C,"干箱",周检修业务统计数据!D:D,"<>COS"))*1.13++SUMIFS(周检修业务统计数据!L:L,周检修业务统计数据!B:B,B82,周检修业务统计数据!C:C,"干箱",周检修业务统计数据!D:D,"<>COS")*1.06 -> 5543.28 | M82: =(L82-'2025年18周'!L82)/'2025年18周'!L82 -> 1.1711 | N82: =L82/J82 -> 370 | O82: =(N82-'2025年18周'!N82)/'2025年18周'!N82 -> 1.033 | P82: =(SUMIFS(周检修业务统计数据!I:I,周检修业务统计数据!B:B,B82,周检修业务统计数据!C:C,"<>干箱")+SUMIFS(周检修业务统计数据!J:J,周检修业务统计数据!B:B,B82,周检修业务统计数据!C:C,"<>干箱"))*1.13++SUMIFS(周检修业务统计数据!L:L,周检修业务统计数据!B:B,B82,周检修业务统计数据!C:C,"<>干箱")*1.06 -> 0 | Q82: 36112 | R82: 10260 | S82: =S225 -> 0 | T82: =C82+J82 -> 896 | U82: =E82+L82+I82+P82+Q82+R82+S82 -> 295306 | V82: =(E82+L82+E83+L83)/W82 -> 18772 | W82: 14 | X82: 700 | Y82: =SUM(T82:T83)-X82 -> 233 | Z82: =X82*$Z$2 -> 13300 | AA82: =SUM(自营2026周完成情况!BB92:BB94) -> 16035 | AB82: =AA82-Z82 -> 2735
A83: 北部湾运营中心 | B83: 广西钦州港自营 | C83: =SUMIFS(周检修业务统计数据!E:E,周检修业务统计数据!B:B,B83,周检修业务统计数据!C:C,"干箱",周检修业务统计数据!D:D,"COS") -> 37 | D83: =C83-'2025年18周'!C83 -> 28 | E83: =(SUMIFS(周检修业务统计数据!I:I,周检修业务统计数据!B:B,B83,周检修业务统计数据!C:C,"干箱",周检修业务统计数据!D:D,"COS")+SUMIFS(周检修业务统计数据!J:J,周检修业务统计数据!B:B,B83,周检修业务统计数据!C:C,"干箱",周检修业务统计数据!D:D,"COS"))*1.13 -> 13867.6 | F83: =(E83-'2025年18周'!E83)/'2025年18周'!E83 -> 2.1011 | G83: =E83/C83 -> 375 | H83: =(G83-'2025年18周'!G83)/'2025年18周'!G83 -> -0.2455 | I83: =SUMIFS(周检修业务统计数据!L:L,周检修业务统计数据!B:B,B83,周检修业务统计数据!C:C,"干箱",周检修业务统计数据!D:D,"COS")*1.06 -> 2035.1258 | J83: =SUMIFS(周检修业务统计数据!E:E,周检修业务统计数据!B:B,B83,周检修业务统计数据!C:C,"干箱",周检修业务统计数据!D:D,"<>COS") -> 0 | K83: =J83-'2025年18周'!J83 -> 0 | L83: =(SUMIFS(周检修业务统计数据!I:I,周检修业务统计数据!B:B,B83,周检修业务统计数据!C:C,"干箱",周检修业务统计数据!D:D,"<>COS")+SUMIFS(周检修业务统计数据!J:J,周检修业务统计数据!B:B,B83,周检修业务统计数据!C:C,"干箱",周检修业务统计数据!D:D,"<>COS"))*1.13++SUMIFS(周检修业务统计数据!L:L,周检修业务统计数据!B:B,B83,周检修业务统计数据!C:C,"干箱",周检修业务统计数据!D:D,"<>COS")*1.06 -> 0 | M83: =(L83-'2025年18周'!L83)/'2025年18周'!L83 -> #DIV/0! | N83: =L83/J83 -> #DIV/0! | O83: =(N83-'2025年18周'!N83)/'2025年18周'!N83 -> #DIV/0! | P83: =(SUMIFS(周检修业务统计数据!I:I,周检修业务统计数据!B:B,B83,周检修业务统计数据!C:C,"<>干箱")+SUMIFS(周检修业务统计数据!J:J,周检修业务统计数据!B:B,B83,周检修业务统计数据!C:C,"<>干箱"))*1.13++SUMIFS(周检修业务统计数据!L:L,周检修业务统计数据!B:B,B83,周检修业务统计数据!C:C,"<>干箱")*1.06 -> 0 | S83: =S226 -> 0 | T83: =C83+J83 -> 37 | U83: =E83+L83+I83+P83+Q83+R83+S83 -> 15903
A84: 广州弘运 | B84: 东莞石龙 | C84: =SUMIFS(周检修业务统计数据!E:E,周检修业务统计数据!B:B,B84,周检修业务统计数据!C:C,"干箱",周检修业务统计数据!D:D,"COS") -> 154 | D84: =C84-'2025年18周'!C84 -> -159 | E84: =(SUMIFS(周检修业务统计数据!I:I,周检修业务统计数据!B:B,B84,周检修业务统计数据!C:C,"干箱",周检修业务统计数据!D:D,"COS")+SUMIFS(周检修业务统计数据!J:J,周检修业务统计数据!B:B,B84,周检修业务统计数据!C:C,"干箱",周检修业务统计数据!D:D,"COS"))*1.13 -> 39863.17 | F84: =(E84-'2025年18周'!E84)/'2025年18周'!E84 -> -0.4946 | G84: =E84/C84 -> 259 | H84: =(G84-'2025年18周'!G84)/'2025年18周'!G84 -> 0.0278 | I84: =SUMIFS(周检修业务统计数据!L:L,周检修业务统计数据!B:B,B84,周检修业务统计数据!C:C,"干箱",周检修业务统计数据!D:D,"COS")*1.06 -> 9530.0784 | J84: =SUMIFS(周检修业务统计数据!E:E,周检修业务统计数据!B:B,B84,周检修业务统计数据!C:C,"干箱",周检修业务统计数据!D:D,"<>COS") -> 0 | K84: =J84-'2025年18周'!J84 -> 0 | L84: =(SUMIFS(周检修业务统计数据!I:I,周检修业务统计数据!B:B,B84,周检修业务统计数据!C:C,"干箱",周检修业务统计数据!D:D,"<>COS")+SUMIFS(周检修业务统计数据!J:J,周检修业务统计数据!B:B,B84,周检修业务统计数据!C:C,"干箱",周检修业务统计数据!D:D,"<>COS"))*1.13++SUMIFS(周检修业务统计数据!L:L,周检修业务统计数据!B:B,B84,周检修业务统计数据!C:C,"干箱",周检修业务统计数据!D:D,"<>COS")*1.06 -> 0 | M84: =(L84-'2025年18周'!L84)/'2025年18周'!L84 -> #DIV/0! | N84: =L84/J84 -> #DIV/0! | O84: =(N84-'2025年18周'!N84)/'2025年18周'!N84 -> #DIV/0! | P84: =(SUMIFS(周检修业务统计数据!I:I,周检修业务统计数据!B:B,B84,周检修业务统计数据!C:C,"<>干箱")+SUMIFS(周检修业务统计数据!J:J,周检修业务统计数据!B:B,B84,周检修业务统计数据!C:C,"<>干箱"))*1.13++SUMIFS(周检修业务统计数据!L:L,周检修业务统计数据!B:B,B84,周检修业务统计数据!C:C,"<>干箱")*1.06 -> 0 | S84: =S226 -> 0 | T84: =C84+J84 -> 154 | U84: =E84+L84+I84+P84+Q84+R84+S84 -> 49393 | V84: =U84/W84 -> #DIV/0!
A85: 广州弘运 | B85: 南沙弘运外堆场 | C85: =SUMIFS(周检修业务统计数据!E:E,周检修业务统计数据!B:B,B85,周检修业务统计数据!C:C,"干箱",周检修业务统计数据!D:D,"COS") -> 506 | D85: =C85-'2025年18周'!C85 -> 67 | E85: =(SUMIFS(周检修业务统计数据!I:I,周检修业务统计数据!B:B,B85,周检修业务统计数据!C:C,"干箱",周检修业务统计数据!D:D,"COS")+SUMIFS(周检修业务统计数据!J:J,周检修业务统计数据!B:B,B85,周检修业务统计数据!C:C,"干箱",周检修业务统计数据!D:D,"COS"))*1.13 -> 126219.01 | F85: =(E85-'2025年18周'!E85)/'2025年18周'!E85 -> 0.1944 | G85: =E85/C85 -> 249 | H85: =(G85-'2025年18周'!G85)/'2025年18周'!G85 -> 0.0332 | I85: =SUMIFS(周检修业务统计数据!L:L,周检修业务统计数据!B:B,B85,周检修业务统计数据!C:C,"干箱",周检修业务统计数据!D:D,"COS")*1.06 -> 0 | J85: =SUMIFS(周检修业务统计数据!E:E,周检修业务统计数据!B:B,B85,周检修业务统计数据!C:C,"干箱",周检修业务统计数据!D:D,"<>COS") -> 0 | K85: =J85-'2025年18周'!J85 -> 0 | L85: =(SUMIFS(周检修业务统计数据!I:I,周检修业务统计数据!B:B,B85,周检修业务统计数据!C:C,"干箱",周检修业务统计数据!D:D,"<>COS")+SUMIFS(周检修业务统计数据!J:J,周检修业务统计数据!B:B,B85,周检修业务统计数据!C:C,"干箱",周检修业务统计数据!D:D,"<>COS"))*1.13++SUMIFS(周检修业务统计数据!L:L,周检修业务统计数据!B:B,B85,周检修业务统计数据!C:C,"干箱",周检修业务统计数据!D:D,"<>COS")*1.06 -> 0 | M85: =(L85-'2025年18周'!L85)/'2025年18周'!L85 -> #DIV/0! | N85: =L85/J85 -> #DIV/0! | O85: =(N85-'2025年18周'!N85)/'2025年18周'!N85 -> #DIV/0! | P85: =(SUMIFS(周检修业务统计数据!I:I,周检修业务统计数据!B:B,B85,周检修业务统计数据!C:C,"<>干箱")+SUMIFS(周检修业务统计数据!J:J,周检修业务统计数据!B:B,B85,周检修业务统计数据!C:C,"<>干箱"))*1.13++SUMIFS(周检修业务统计数据!L:L,周检修业务统计数据!B:B,B85,周检修业务统计数据!C:C,"<>干箱")*1.06 -> 6828.73 | S85: =S227 -> 0 | T85: =C85+J85 -> 506 | U85: =E85+L85+I85+P85+Q85+R85+S85 -> 133048 | V85: =U85/W85 -> #DIV/0! | AC85: 优化为自营佛山顺乐自营
A86: 广州弘运 | B86: 三水新港 | C86: =SUMIFS(周检修业务统计数据!E:E,周检修业务统计数据!B:B,B86,周检修业务统计数据!C:C,"干箱",周检修业务统计数据!D:D,"COS") -> 22 | D86: =C86-'2025年18周'!C86 -> -7 | E86: =(SUMIFS(周检修业务统计数据!I:I,周检修业务统计数据!B:B,B86,周检修业务统计数据!C:C,"干箱",周检修业务统计数据!D:D,"COS")+SUMIFS(周检修业务统计数据!J:J,周检修业务统计数据!B:B,B86,周检修业务统计数据!C:C,"干箱",周检修业务统计数据!D:D,"COS"))*1.13 -> 842.87 | F86: =(E86-'2025年18周'!E86)/'2025年18周'!E86 -> -0.7477 | G86: =E86/C86 -> 38 | H86: =(G86-'2025年18周'!G86)/'2025年18周'!G86 -> -0.6696 | I86: =SUMIFS(周检修业务统计数据!L:L,周检修业务统计数据!B:B,B86,周检修业务统计数据!C:C,"干箱",周检修业务统计数据!D:D,"COS")*1.06 -> 1649.89 | J86: =SUMIFS(周检修业务统计数据!E:E,周检修业务统计数据!B:B,B86,周检修业务统计数据!C:C,"干箱",周检修业务统计数据!D:D,"<>COS") -> 0 | K86: =J86-'2025年18周'!J86 -> 0 | L86: =(SUMIFS(周检修业务统计数据!I:I,周检修业务统计数据!B:B,B86,周检修业务统计数据!C:C,"干箱",周检修业务统计数据!D:D,"<>COS")+SUMIFS(周检修业务统计数据!J:J,周检修业务统计数据!B:B,B86,周检修业务统计数据!C:C,"干箱",周检修业务统计数据!D:D,"<>COS"))*1.13++SUMIFS(周检修业务统计数据!L:L,周检修业务统计数据!B:B,B86,周检修业务统计数据!C:C,"干箱",周检修业务统计数据!D:D,"<>COS")*1.06 -> 0 | M86: =(L86-'2025年18周'!L86)/'2025年18周'!L86 -> #DIV/0! | N86: =L86/J86 -> #DIV/0! | O86: =(N86-'2025年18周'!N86)/'2025年18周'!N86 -> #DIV/0! | P86: =(SUMIFS(周检修业务统计数据!I:I,周检修业务统计数据!B:B,B86,周检修业务统计数据!C:C,"<>干箱")+SUMIFS(周检修业务统计数据!J:J,周检修业务统计数据!B:B,B86,周检修业务统计数据!C:C,"<>干箱"))*1.13++SUMIFS(周检修业务统计数据!L:L,周检修业务统计数据!B:B,B86,周检修业务统计数据!C:C,"<>干箱")*1.06 -> 0 | S86: =S228 -> 0 | T86: =C86+J86 -> 22 | U86: =E86+L86+I86+P86+Q86+R86+S86 -> 2493 | V86: =U86/W86 -> #DIV/0!
A87: 广州弘运 | B87: 江门李锦记 | C87: =SUMIFS(周检修业务统计数据!E:E,周检修业务统计数据!B:B,B87,周检修业务统计数据!C:C,"干箱",周检修业务统计数据!D:D,"COS") -> 15 | D87: =C87-'2025年18周'!C87 -> 2 | E87: =(SUMIFS(周检修业务统计数据!I:I,周检修业务统计数据!B:B,B87,周检修业务统计数据!C:C,"干箱",周检修业务统计数据!D:D,"COS")+SUMIFS(周检修业务统计数据!J:J,周检修业务统计数据!B:B,B87,周检修业务统计数据!C:C,"干箱",周检修业务统计数据!D:D,"COS"))*1.13 -> 1542.03 | F87: =(E87-'2025年18周'!E87)/'2025年18周'!E87 -> 0.5381 | G87: =E87/C87 -> 103 | H87: =(G87-'2025年18周'!G87)/'2025年18周'!G87 -> 0.3377 | I87: =SUMIFS(周检修业务统计数据!L:L,周检修业务统计数据!B:B,B87,周检修业务统计数据!C:C,"干箱",周检修业务统计数据!D:D,"COS")*1.06 -> 825.051 | J87: =SUMIFS(周检修业务统计数据!E:E,周检修业务统计数据!B:B,B87,周检修业务统计数据!C:C,"干箱",周检修业务统计数据!D:D,"<>COS") -> 0 | K87: =J87-'2025年18周'!J87 -> 0 | L87: =(SUMIFS(周检修业务统计数据!I:I,周检修业务统计数据!B:B,B87,周检修业务统计数据!C:C,"干箱",周检修业务统计数据!D:D,"<>COS")+SUMIFS(周检修业务统计数据!J:J,周检修业务统计数据!B:B,B87,周检修业务统计数据!C:C,"干箱",周检修业务统计数据!D:D,"<>COS"))*1.13++SUMIFS(周检修业务统计数据!L:L,周检修业务统计数据!B:B,B87,周检修业务统计数据!C:C,"干箱",周检修业务统计数据!D:D,"<>COS")*1.06 -> 0 | M87: =(L87-'2025年18周'!L87)/'2025年18周'!L87 -> #DIV/0! | N87: =L87/J87 -> #DIV/0! | O87: =(N87-'2025年18周'!N87)/'2025年18周'!N87 -> #DIV/0! | P87: =(SUMIFS(周检修业务统计数据!I:I,周检修业务统计数据!B:B,B87,周检修业务统计数据!C:C,"<>干箱")+SUMIFS(周检修业务统计数据!J:J,周检修业务统计数据!B:B,B87,周检修业务统计数据!C:C,"<>干箱"))*1.13++SUMIFS(周检修业务统计数据!L:L,周检修业务统计数据!B:B,B87,周检修业务统计数据!C:C,"<>干箱")*1.06 -> 0 | S87: =S229 -> 0 | T87: =C87+J87 -> 15 | U87: =E87+L87+I87+P87+Q87+R87+S87 -> 2367 | V87: =U87/W87 -> #DIV/0!
A88: 广州弘运 | B88: 江门双水 | C88: =SUMIFS(周检修业务统计数据!E:E,周检修业务统计数据!B:B,B88,周检修业务统计数据!C:C,"干箱",周检修业务统计数据!D:D,"COS") -> 52 | D88: =C88-'2025年18周'!C88 -> 15 | E88: =(SUMIFS(周检修业务统计数据!I:I,周检修业务统计数据!B:B,B88,周检修业务统计数据!C:C,"干箱",周检修业务统计数据!D:D,"COS")+SUMIFS(周检修业务统计数据!J:J,周检修业务统计数据!B:B,B88,周检修业务统计数据!C:C,"干箱",周检修业务统计数据!D:D,"COS"))*1.13 -> 18127.77 | F88: =(E88-'2025年18周'!E88)/'2025年18周'!E88 -> 0.5537 | G88: =E88/C88 -> 349 | H88: =(G88-'2025年18周'!G88)/'2025年18周'!G88 -> 0.1079 | I88: =SUMIFS(周检修业务统计数据!L:L,周检修业务统计数据!B:B,B88,周检修业务统计数据!C:C,"干箱",周检修业务统计数据!D:D,"COS")*1.06 -> 2980.1264 | J88: =SUMIFS(周检修业务统计数据!E:E,周检修业务统计数据!B:B,B88,周检修业务统计数据!C:C,"干箱",周检修业务统计数据!D:D,"<>COS") -> 0 | K88: =J88-'2025年18周'!J88 -> 0 | L88: =(SUMIFS(周检修业务统计数据!I:I,周检修业务统计数据!B:B,B88,周检修业务统计数据!C:C,"干箱",周检修业务统计数据!D:D,"<>COS")+SUMIFS(周检修业务统计数据!J:J,周检修业务统计数据!B:B,B88,周检修业务统计数据!C:C,"干箱",周检修业务统计数据!D:D,"<>COS"))*1.13++SUMIFS(周检修业务统计数据!L:L,周检修业务统计数据!B:B,B88,周检修业务统计数据!C:C,"干箱",周检修业务统计数据!D:D,"<>COS")*1.06 -> 0 | M88: =(L88-'2025年18周'!L88)/'2025年18周'!L88 -> #DIV/0! | N88: =L88/J88 -> #DIV/0! | O88: =(N88-'2025年18周'!N88)/'2025年18周'!N88 -> #DIV/0! | P88: =(SUMIFS(周检修业务统计数据!I:I,周检修业务统计数据!B:B,B88,周检修业务统计数据!C:C,"<>干箱")+SUMIFS(周检修业务统计数据!J:J,周检修业务统计数据!B:B,B88,周检修业务统计数据!C:C,"<>干箱"))*1.13++SUMIFS(周检修业务统计数据!L:L,周检修业务统计数据!B:B,B88,周检修业务统计数据!C:C,"<>干箱")*1.06 -> 0 | S88: =S230 -> 0 | T88: =C88+J88 -> 52 | U88: =E88+L88+I88+P88+Q88+R88+S88 -> 21108 | V88: =U88/W88 -> #DIV/0!
A89: 广州弘运 | B89: 江门天马港 | C89: =SUMIFS(周检修业务统计数据!E:E,周检修业务统计数据!B:B,B89,周检修业务统计数据!C:C,"干箱",周检修业务统计数据!D:D,"COS") -> 0 | D89: =C89-'2025年18周'!C89 -> -1 | E89: =(SUMIFS(周检修业务统计数据!I:I,周检修业务统计数据!B:B,B89,周检修业务统计数据!C:C,"干箱",周检修业务统计数据!D:D,"COS")+SUMIFS(周检修业务统计数据!J:J,周检修业务统计数据!B:B,B89,周检修业务统计数据!C:C,"干箱",周检修业务统计数据!D:D,"COS"))*1.13 -> 0 | F89: =(E89-'2025年18周'!E89)/'2025年18周'!E89 -> -1 | G89: =E89/C89 -> #DIV/0! | H89: =(G89-'2025年18周'!G89)/'2025年18周'!G89 -> #DIV/0! | I89: =SUMIFS(周检修业务统计数据!L:L,周检修业务统计数据!B:B,B89,周检修业务统计数据!C:C,"干箱",周检修业务统计数据!D:D,"COS")*1.06 -> 0 | J89: =SUMIFS(周检修业务统计数据!E:E,周检修业务统计数据!B:B,B89,周检修业务统计数据!C:C,"干箱",周检修业务统计数据!D:D,"<>COS") -> 0 | K89: =J89-'2025年18周'!J89 -> 0 | L89: =(SUMIFS(周检修业务统计数据!I:I,周检修业务统计数据!B:B,B89,周检修业务统计数据!C:C,"干箱",周检修业务统计数据!D:D,"<>COS")+SUMIFS(周检修业务统计数据!J:J,周检修业务统计数据!B:B,B89,周检修业务统计数据!C:C,"干箱",周检修业务统计数据!D:D,"<>COS"))*1.13++SUMIFS(周检修业务统计数据!L:L,周检修业务统计数据!B:B,B89,周检修业务统计数据!C:C,"干箱",周检修业务统计数据!D:D,"<>COS")*1.06 -> 0 | M89: =(L89-'2025年18周'!L89)/'2025年18周'!L89 -> #DIV/0! | N89: =L89/J89 -> #DIV/0! | O89: =(N89-'2025年18周'!N89)/'2025年18周'!N89 -> #DIV/0! | P89: =(SUMIFS(周检修业务统计数据!I:I,周检修业务统计数据!B:B,B89,周检修业务统计数据!C:C,"<>干箱")+SUMIFS(周检修业务统计数据!J:J,周检修业务统计数据!B:B,B89,周检修业务统计数据!C:C,"<>干箱"))*1.13++SUMIFS(周检修业务统计数据!L:L,周检修业务统计数据!B:B,B89,周检修业务统计数据!C:C,"<>干箱")*1.06 -> 0 | S89: =S231 -> 0 | T89: =C89+J89 -> 0 | U89: =E89+L89+I89+P89+Q89+R89+S89 -> 0 | V89: =U89/W89 -> #DIV/0!
A90: 广州弘运 | B90: 江门鹤山 | C90: =SUMIFS(周检修业务统计数据!E:E,周检修业务统计数据!B:B,B90,周检修业务统计数据!C:C,"干箱",周检修业务统计数据!D:D,"COS") -> 39 | D90: =C90-'2025年18周'!C90 -> 34 | E90: =(SUMIFS(周检修业务统计数据!I:I,周检修业务统计数据!B:B,B90,周检修业务统计数据!C:C,"干箱",周检修业务统计数据!D:D,"COS")+SUMIFS(周检修业务统计数据!J:J,周检修业务统计数据!B:B,B90,周检修业务统计数据!C:C,"干箱",周检修业务统计数据!D:D,"COS"))*1.13 -> 10627.93 | F90: =(E90-'2025年18周'!E90)/'2025年18周'!E90 -> 16.8921 | G90: =E90/C90 -> 273 | H90: =(G90-'2025年18周'!G90)/'2025年18周'!G90 -> 1.2941 | I90: =SUMIFS(周检修业务统计数据!L:L,周检修业务统计数据!B:B,B90,周检修业务统计数据!C:C,"干箱",周检修业务统计数据!D:D,"COS")*1.06 -> 2524.973 | J90: =SUMIFS(周检修业务统计数据!E:E,周检修业务统计数据!B:B,B90,周检修业务统计数据!C:C,"干箱",周检修业务统计数据!D:D,"<>COS") -> 0 | K90: =J90-'2025年18周'!J90 -> 0 | L90: =(SUMIFS(周检修业务统计数据!I:I,周检修业务统计数据!B:B,B90,周检修业务统计数据!C:C,"干箱",周检修业务统计数据!D:D,"<>COS")+SUMIFS(周检修业务统计数据!J:J,周检修业务统计数据!B:B,B90,周检修业务统计数据!C:C,"干箱",周检修业务统计数据!D:D,"<>COS"))*1.13++SUMIFS(周检修业务统计数据!L:L,周检修业务统计数据!B:B,B90,周检修业务统计数据!C:C,"干箱",周检修业务统计数据!D:D,"<>COS")*1.06 -> 0 | M90: =(L90-'2025年18周'!L90)/'2025年18周'!L90 -> #DIV/0! | N90: =L90/J90 -> #DIV/0! | O90: =(N90-'2025年18周'!N90)/'2025年18周'!N90 -> #DIV/0! | P90: =(SUMIFS(周检修业务统计数据!I:I,周检修业务统计数据!B:B,B90,周检修业务统计数据!C:C,"<>干箱")+SUMIFS(周检修业务统计数据!J:J,周检修业务统计数据!B:B,B90,周检修业务统计数据!C:C,"<>干箱"))*1.13++SUMIFS(周检修业务统计数据!L:L,周检修业务统计数据!B:B,B90,周检修业务统计数据!C:C,"<>干箱")*1.06 -> 0 | S90: =S232 -> 0 | T90: =C90+J90 -> 39 | U90: =E90+L90+I90+P90+Q90+R90+S90 -> 13153 | V90: =U90/W90 -> #DIV/0!
A91: 广州弘运 | B91: 南沙一期弘运 | C91: =SUMIFS(周检修业务统计数据!E:E,周检修业务统计数据!B:B,B91,周检修业务统计数据!C:C,"干箱",周检修业务统计数据!D:D,"COS") -> 75 | D91: =C91-'2025年18周'!C91 -> -95 | E91: =(SUMIFS(周检修业务统计数据!I:I,周检修业务统计数据!B:B,B91,周检修业务统计数据!C:C,"干箱",周检修业务统计数据!D:D,"COS")+SUMIFS(周检修业务统计数据!J:J,周检修业务统计数据!B:B,B91,周检修业务统计数据!C:C,"干箱",周检修业务统计数据!D:D,"COS"))*1.13 -> 7272.04 | F91: =(E91-'2025年18周'!E91)/'2025年18周'!E91 -> -0.5372 | G91: =E91/C91 -> 97 | H91: =(G91-'2025年18周'!G91)/'2025年18周'!G91 -> 0.0543 | I91: =SUMIFS(周检修业务统计数据!L:L,周检修业务统计数据!B:B,B91,周检修业务统计数据!C:C,"干箱",周检修业务统计数据!D:D,"COS")*1.06 -> 5624.625 | J91: =SUMIFS(周检修业务统计数据!E:E,周检修业务统计数据!B:B,B91,周检修业务统计数据!C:C,"干箱",周检修业务统计数据!D:D,"<>COS") -> 0 | K91: =J91-'2025年18周'!J91 -> 0 | L91: =(SUMIFS(周检修业务统计数据!I:I,周检修业务统计数据!B:B,B91,周检修业务统计数据!C:C,"干箱",周检修业务统计数据!D:D,"<>COS")+SUMIFS(周检修业务统计数据!J:J,周检修业务统计数据!B:B,B91,周检修业务统计数据!C:C,"干箱",周检修业务统计数据!D:D,"<>COS"))*1.13++SUMIFS(周检修业务统计数据!L:L,周检修业务统计数据!B:B,B91,周检修业务统计数据!C:C,"干箱",周检修业务统计数据!D:D,"<>COS")*1.06 -> 0 | M91: =(L91-'2025年18周'!L91)/'2025年18周'!L91 -> #DIV/0! | N91: =L91/J91 -> #DIV/0! | O91: =(N91-'2025年18周'!N91)/'2025年18周'!N91 -> #DIV/0! | P91: =(SUMIFS(周检修业务统计数据!I:I,周检修业务统计数据!B:B,B91,周检修业务统计数据!C:C,"<>干箱")+SUMIFS(周检修业务统计数据!J:J,周检修业务统计数据!B:B,B91,周检修业务统计数据!C:C,"<>干箱"))*1.13++SUMIFS(周检修业务统计数据!L:L,周检修业务统计数据!B:B,B91,周检修业务统计数据!C:C,"<>干箱")*1.06 -> 1061.63 | S91: =S233 -> 0 | T91: =C91+J91 -> 75 | U91: =E91+L91+I91+P91+Q91+R91+S91 -> 13958 | V91: =U91/W91 -> #DIV/0!
A92: 广州弘运 | B92: 云浮新港 | C92: =SUMIFS(周检修业务统计数据!E:E,周检修业务统计数据!B:B,B92,周检修业务统计数据!C:C,"干箱",周检修业务统计数据!D:D,"COS") -> 45 | D92: =C92-'2025年18周'!C92 -> -107 | E92: =(SUMIFS(周检修业务统计数据!I:I,周检修业务统计数据!B:B,B92,周检修业务统计数据!C:C,"干箱",周检修业务统计数据!D:D,"COS")+SUMIFS(周检修业务统计数据!J:J,周检修业务统计数据!B:B,B92,周检修业务统计数据!C:C,"干箱",周检修业务统计数据!D:D,"COS"))*1.13 -> 21754.66 | F92: =(E92-'2025年18周'!E92)/'2025年18周'!E92 -> -0.674 | G92: =E92/C92 -> 483 | H92: =(G92-'2025年18周'!G92)/'2025年18周'!G92 -> 0.1002 | I92: =SUMIFS(周检修业务统计数据!L:L,周检修业务统计数据!B:B,B92,周检修业务统计数据!C:C,"干箱",周检修业务统计数据!D:D,"COS")*1.06 -> 2475.153 | J92: =SUMIFS(周检修业务统计数据!E:E,周检修业务统计数据!B:B,B92,周检修业务统计数据!C:C,"干箱",周检修业务统计数据!D:D,"<>COS") -> 0 | K92: =J92-'2025年18周'!J92 -> 0 | L92: =(SUMIFS(周检修业务统计数据!I:I,周检修业务统计数据!B:B,B92,周检修业务统计数据!C:C,"干箱",周检修业务统计数据!D:D,"<>COS")+SUMIFS(周检修业务统计数据!J:J,周检修业务统计数据!B:B,B92,周检修业务统计数据!C:C,"干箱",周检修业务统计数据!D:D,"<>COS"))*1.13++SUMIFS(周检修业务统计数据!L:L,周检修业务统计数据!B:B,B92,周检修业务统计数据!C:C,"干箱",周检修业务统计数据!D:D,"<>COS")*1.06 -> 0 | M92: =(L92-'2025年18周'!L92)/'2025年18周'!L92 -> #DIV/0! | N92: =L92/J92 -> #DIV/0! | O92: =(N92-'2025年18周'!N92)/'2025年18周'!N92 -> #DIV/0! | P92: =(SUMIFS(周检修业务统计数据!I:I,周检修业务统计数据!B:B,B92,周检修业务统计数据!C:C,"<>干箱")+SUMIFS(周检修业务统计数据!J:J,周检修业务统计数据!B:B,B92,周检修业务统计数据!C:C,"<>干箱"))*1.13++SUMIFS(周检修业务统计数据!L:L,周检修业务统计数据!B:B,B92,周检修业务统计数据!C:C,"<>干箱")*1.06 -> 0 | S92: =S234 -> 0 | T92: =C92+J92 -> 45 | U92: =E92+L92+I92+P92+Q92+R92+S92 -> 24230 | V92: =U92/W92 -> #DIV/0!
A93: 广州弘运 | B93: 新会新港 | C93: =SUMIFS(周检修业务统计数据!E:E,周检修业务统计数据!B:B,B93,周检修业务统计数据!C:C,"干箱",周检修业务统计数据!D:D,"COS") -> 106 | D93: =C93-'2025年18周'!C93 -> -439 | E93: =(SUMIFS(周检修业务统计数据!I:I,周检修业务统计数据!B:B,B93,周检修业务统计数据!C:C,"干箱",周检修业务统计数据!D:D,"COS")+SUMIFS(周检修业务统计数据!J:J,周检修业务统计数据!B:B,B93,周检修业务统计数据!C:C,"干箱",周检修业务统计数据!D:D,"COS"))*1.13 -> 29452.46 | F93: =(E93-'2025年18周'!E93)/'2025年18周'!E93 -> -0.7835 | G93: =E93/C93 -> 278 | H93: =(G93-'2025年18周'!G93)/'2025年18周'!G93 -> 0.112 | I93: =SUMIFS(周检修业务统计数据!L:L,周检修业务统计数据!B:B,B93,周检修业务统计数据!C:C,"干箱",周检修业务统计数据!D:D,"COS")*1.06 -> 6010.2848 | J93: =SUMIFS(周检修业务统计数据!E:E,周检修业务统计数据!B:B,B93,周检修业务统计数据!C:C,"干箱",周检修业务统计数据!D:D,"<>COS") -> 0 | K93: =J93-'2025年18周'!J93 -> 0 | L93: =(SUMIFS(周检修业务统计数据!I:I,周检修业务统计数据!B:B,B93,周检修业务统计数据!C:C,"干箱",周检修业务统计数据!D:D,"<>COS")+SUMIFS(周检修业务统计数据!J:J,周检修业务统计数据!B:B,B93,周检修业务统计数据!C:C,"干箱",周检修业务统计数据!D:D,"<>COS"))*1.13++SUMIFS(周检修业务统计数据!L:L,周检修业务统计数据!B:B,B93,周检修业务统计数据!C:C,"干箱",周检修业务统计数据!D:D,"<>COS")*1.06 -> 0 | M93: =(L93-'2025年18周'!L93)/'2025年18周'!L93 -> #DIV/0! | N93: =L93/J93 -> #DIV/0! | O93: =(N93-'2025年18周'!N93)/'2025年18周'!N93 -> #DIV/0! | P93: =(SUMIFS(周检修业务统计数据!I:I,周检修业务统计数据!B:B,B93,周检修业务统计数据!C:C,"<>干箱")+SUMIFS(周检修业务统计数据!J:J,周检修业务统计数据!B:B,B93,周检修业务统计数据!C:C,"<>干箱"))*1.13++SUMIFS(周检修业务统计数据!L:L,周检修业务统计数据!B:B,B93,周检修业务统计数据!C:C,"<>干箱")*1.06 -> 0 | S93: =S235 -> 0 | T93: =C93+J93 -> 106 | U93: =E93+L93+I93+P93+Q93+R93+S93 -> 35463 | V93: =U93/W93 -> #DIV/0!
A94: 广州弘运 | B94: 广西钦州外堆场弘运 | C94: =SUMIFS(周检修业务统计数据!E:E,周检修业务统计数据!B:B,B94,周检修业务统计数据!C:C,"干箱",周检修业务统计数据!D:D,"COS") -> 12 | D94: =C94-'2025年18周'!C94 -> -69 | E94: =(SUMIFS(周检修业务统计数据!I:I,周检修业务统计数据!B:B,B94,周检修业务统计数据!C:C,"干箱",周检修业务统计数据!D:D,"COS")+SUMIFS(周检修业务统计数据!J:J,周检修业务统计数据!B:B,B94,周检修业务统计数据!C:C,"干箱",周检修业务统计数据!D:D,"COS"))*1.13 -> 5446.57 | F94: =(E94-'2025年18周'!E94)/'2025年18周'!E94 -> -0.7391 | G94: =E94/C94 -> 454 | H94: =(G94-'2025年18周'!G94)/'2025年18周'!G94 -> 0.7597 | I94: =SUMIFS(周检修业务统计数据!L:L,周检修业务统计数据!B:B,B94,周检修业务统计数据!C:C,"干箱",周检修业务统计数据!D:D,"COS")*1.06 -> 0 | J94: =SUMIFS(周检修业务统计数据!E:E,周检修业务统计数据!B:B,B94,周检修业务统计数据!C:C,"干箱",周检修业务统计数据!D:D,"<>COS") -> 0 | K94: =J94-'2025年18周'!J94 -> 0 | L94: =(SUMIFS(周检修业务统计数据!I:I,周检修业务统计数据!B:B,B94,周检修业务统计数据!C:C,"干箱",周检修业务统计数据!D:D,"<>COS")+SUMIFS(周检修业务统计数据!J:J,周检修业务统计数据!B:B,B94,周检修业务统计数据!C:C,"干箱",周检修业务统计数据!D:D,"<>COS"))*1.13++SUMIFS(周检修业务统计数据!L:L,周检修业务统计数据!B:B,B94,周检修业务统计数据!C:C,"干箱",周检修业务统计数据!D:D,"<>COS")*1.06 -> 0 | M94: =(L94-'2025年18周'!L94)/'2025年18周'!L94 -> #DIV/0! | N94: =L94/J94 -> #DIV/0! | O94: =(N94-'2025年18周'!N94)/'2025年18周'!N94 -> #DIV/0! | P94: =(SUMIFS(周检修业务统计数据!I:I,周检修业务统计数据!B:B,B94,周检修业务统计数据!C:C,"<>干箱")+SUMIFS(周检修业务统计数据!J:J,周检修业务统计数据!B:B,B94,周检修业务统计数据!C:C,"<>干箱"))*1.13++SUMIFS(周检修业务统计数据!L:L,周检修业务统计数据!B:B,B94,周检修业务统计数据!C:C,"<>干箱")*1.06 -> 0 | S94: =S236 -> 0 | T94: =C94+J94 -> 12 | U94: =E94+L94+I94+P94+Q94+R94+S94 -> 5447 | V94: =U94/W94 -> #DIV/0! | AC94: 流动修箱场
A95: 广州弘运 | B95: 高明珠江码头外包 | C95: =SUMIFS(周检修业务统计数据!E:E,周检修业务统计数据!B:B,B95,周检修业务统计数据!C:C,"干箱",周检修业务统计数据!D:D,"COS") -> 3 | D95: =C95-'2025年18周'!C95 -> -2 | E95: =(SUMIFS(周检修业务统计数据!I:I,周检修业务统计数据!B:B,B95,周检修业务统计数据!C:C,"干箱",周检修业务统计数据!D:D,"COS")+SUMIFS(周检修业务统计数据!J:J,周检修业务统计数据!B:B,B95,周检修业务统计数据!C:C,"干箱",周检修业务统计数据!D:D,"COS"))*1.13 -> 337.2 | F95: =(E95-'2025年18周'!E95)/'2025年18周'!E95 -> -0.0277 | G95: =E95/C95 -> 112 | H95: =(G95-'2025年18周'!G95)/'2025年18周'!G95 -> 0.6232 | I95: =SUMIFS(周检修业务统计数据!L:L,周检修业务统计数据!B:B,B95,周检修业务统计数据!C:C,"干箱",周检修业务统计数据!D:D,"COS")*1.06 -> 165.0102 | J95: =SUMIFS(周检修业务统计数据!E:E,周检修业务统计数据!B:B,B95,周检修业务统计数据!C:C,"干箱",周检修业务统计数据!D:D,"<>COS") -> 0 | K95: =J95-'2025年18周'!J95 -> -20 | L95: =(SUMIFS(周检修业务统计数据!I:I,周检修业务统计数据!B:B,B95,周检修业务统计数据!C:C,"干箱",周检修业务统计数据!D:D,"<>COS")+SUMIFS(周检修业务统计数据!J:J,周检修业务统计数据!B:B,B95,周检修业务统计数据!C:C,"干箱",周检修业务统计数据!D:D,"<>COS"))*1.13++SUMIFS(周检修业务统计数据!L:L,周检修业务统计数据!B:B,B95,周检修业务统计数据!C:C,"干箱",周检修业务统计数据!D:D,"<>COS")*1.06 -> 0 | M95: =(L95-'2025年18周'!L95)/'2025年18周'!L95 -> -1 | N95: =L95/J95 -> #DIV/0! | O95: =(N95-'2025年18周'!N95)/'2025年18周'!N95 -> #DIV/0! | P95: =(SUMIFS(周检修业务统计数据!I:I,周检修业务统计数据!B:B,B95,周检修业务统计数据!C:C,"<>干箱")+SUMIFS(周检修业务统计数据!J:J,周检修业务统计数据!B:B,B95,周检修业务统计数据!C:C,"<>干箱"))*1.13++SUMIFS(周检修业务统计数据!L:L,周检修业务统计数据!B:B,B95,周检修业务统计数据!C:C,"<>干箱")*1.06 -> 0 | S95: =S237 -> 0 | T95: =C95+J95 -> 3 | U95: =E95+L95+I95+P95+Q95+R95+S95 -> 502 | V95: =U95/W95 -> #DIV/0!
A96: 浚得兴 | B96: 江门奔达码头 | C96: =SUMIFS(周检修业务统计数据!E:E,周检修业务统计数据!B:B,B96,周检修业务统计数据!C:C,"干箱",周检修业务统计数据!D:D,"COS") -> 51 | D96: =C96-'2025年18周'!C96 -> 31 | E96: =(SUMIFS(周检修业务统计数据!I:I,周检修业务统计数据!B:B,B96,周检修业务统计数据!C:C,"干箱",周检修业务统计数据!D:D,"COS")+SUMIFS(周检修业务统计数据!J:J,周检修业务统计数据!B:B,B96,周检修业务统计数据!C:C,"干箱",周检修业务统计数据!D:D,"COS"))*1.13 -> 18134.25 | F96: =(E96-'2025年18周'!E96)/'2025年18周'!E96 -> 1.0583 | G96: =E96/C96 -> 356 | H96: =(G96-'2025年18周'!G96)/'2025年18周'!G96 -> -0.1927 | I96: =SUMIFS(周检修业务统计数据!L:L,周检修业务统计数据!B:B,B96,周检修业务统计数据!C:C,"干箱",周检修业务统计数据!D:D,"COS")*1.06 -> 2825.165 | J96: =SUMIFS(周检修业务统计数据!E:E,周检修业务统计数据!B:B,B96,周检修业务统计数据!C:C,"干箱",周检修业务统计数据!D:D,"<>COS") -> 0 | K96: =J96-'2025年18周'!J96 -> 0 | L96: =(SUMIFS(周检修业务统计数据!I:I,周检修业务统计数据!B:B,B96,周检修业务统计数据!C:C,"干箱",周检修业务统计数据!D:D,"<>COS")+SUMIFS(周检修业务统计数据!J:J,周检修业务统计数据!B:B,B96,周检修业务统计数据!C:C,"干箱",周检修业务统计数据!D:D,"<>COS"))*1.13++SUMIFS(周检修业务统计数据!L:L,周检修业务统计数据!B:B,B96,周检修业务统计数据!C:C,"干箱",周检修业务统计数据!D:D,"<>COS")*1.06 -> 0 | M96: =(L96-'2025年18周'!L96)/'2025年18周'!L96 -> #DIV/0! | N96: =L96/J96 -> #DIV/0! | O96: =(N96-'2025年18周'!N96)/'2025年18周'!N96 -> #DIV/0! | P96: =(SUMIFS(周检修业务统计数据!I:I,周检修业务统计数据!B:B,B96,周检修业务统计数据!C:C,"<>干箱")+SUMIFS(周检修业务统计数据!J:J,周检修业务统计数据!B:B,B96,周检修业务统计数据!C:C,"<>干箱"))*1.13++SUMIFS(周检修业务统计数据!L:L,周检修业务统计数据!B:B,B96,周检修业务统计数据!C:C,"<>干箱")*1.06 -> 0 | S96: =S238 -> 0 | T96: =C96+J96 -> 51 | U96: =E96+L96+I96+P96+Q96+R96+S96 -> 20959 | V96: =U96/W96 -> #DIV/0!
A97: 广州弘运 | B97: 黄埔集司 | C97: =SUMIFS(周检修业务统计数据!E:E,周检修业务统计数据!B:B,B97,周检修业务统计数据!C:C,"干箱",周检修业务统计数据!D:D,"COS") -> 0 | D97: =C97-'2025年18周'!C97 -> 0 | E97: =(SUMIFS(周检修业务统计数据!I:I,周检修业务统计数据!B:B,B97,周检修业务统计数据!C:C,"干箱",周检修业务统计数据!D:D,"COS")+SUMIFS(周检修业务统计数据!J:J,周检修业务统计数据!B:B,B97,周检修业务统计数据!C:C,"干箱",周检修业务统计数据!D:D,"COS"))*1.13 -> 0 | F97: =(E97-'2025年18周'!E97)/'2025年18周'!E97 -> #DIV/0! | G97: =E97/C97 -> #DIV/0! | H97: =(G97-'2025年18周'!G97)/'2025年18周'!G97 -> #DIV/0! | I97: =SUMIFS(周检修业务统计数据!L:L,周检修业务统计数据!B:B,B97,周检修业务统计数据!C:C,"干箱",周检修业务统计数据!D:D,"COS")*1.06 -> 0 | J97: =SUMIFS(周检修业务统计数据!E:E,周检修业务统计数据!B:B,B97,周检修业务统计数据!C:C,"干箱",周检修业务统计数据!D:D,"<>COS") -> 0 | K97: =J97-'2025年18周'!J97 -> 0 | L97: =(SUMIFS(周检修业务统计数据!I:I,周检修业务统计数据!B:B,B97,周检修业务统计数据!C:C,"干箱",周检修业务统计数据!D:D,"<>COS")+SUMIFS(周检修业务统计数据!J:J,周检修业务统计数据!B:B,B97,周检修业务统计数据!C:C,"干箱",周检修业务统计数据!D:D,"<>COS"))*1.13++SUMIFS(周检修业务统计数据!L:L,周检修业务统计数据!B:B,B97,周检修业务统计数据!C:C,"干箱",周检修业务统计数据!D:D,"<>COS")*1.06 -> 0 | M97: =(L97-'2025年18周'!L97)/'2025年18周'!L97 -> #DIV/0! | N97: =L97/J97 -> #DIV/0! | O97: =(N97-'2025年18周'!N97)/'2025年18周'!N97 -> #DIV/0! | P97: =(SUMIFS(周检修业务统计数据!I:I,周检修业务统计数据!B:B,B97,周检修业务统计数据!C:C,"<>干箱")+SUMIFS(周检修业务统计数据!J:J,周检修业务统计数据!B:B,B97,周检修业务统计数据!C:C,"<>干箱"))*1.13++SUMIFS(周检修业务统计数据!L:L,周检修业务统计数据!B:B,B97,周检修业务统计数据!C:C,"<>干箱")*1.06 -> 0 | S97: =S239 -> 0 | T97: =C97+J97 -> 0 | U97: =E97+L97+I97+P97+Q97+R97+S97 -> 0 | V97: =U97/W97 -> #DIV/0! | AC97: OOCL外包业务
A98: 广州弘运 | B98: 肇庆三榕 | C98: =SUMIFS(周检修业务统计数据!E:E,周检修业务统计数据!B:B,B98,周检修业务统计数据!C:C,"干箱",周检修业务统计数据!D:D,"COS") -> 29 | D98: =C98-'2025年18周'!C98 -> 7 | E98: =(SUMIFS(周检修业务统计数据!I:I,周检修业务统计数据!B:B,B98,周检修业务统计数据!C:C,"干箱",周检修业务统计数据!D:D,"COS")+SUMIFS(周检修业务统计数据!J:J,周检修业务统计数据!B:B,B98,周检修业务统计数据!C:C,"干箱",周检修业务统计数据!D:D,"COS"))*1.13 -> 6997.23 | F98: =(E98-'2025年18周'!E98)/'2025年18周'!E98 -> 0.1612 | G98: =E98/C98 -> 241 | H98: =(G98-'2025年18周'!G98)/'2025年18周'!G98 -> -0.1204 | I98: =SUMIFS(周检修业务统计数据!L:L,周检修业务统计数据!B:B,B98,周检修业务统计数据!C:C,"干箱",周检修业务统计数据!D:D,"COS")*1.06 -> 1655.0734 | J98: =SUMIFS(周检修业务统计数据!E:E,周检修业务统计数据!B:B,B98,周检修业务统计数据!C:C,"干箱",周检修业务统计数据!D:D,"<>COS") -> 0 | K98: =J98-'2025年18周'!J98 -> 0 | L98: =(SUMIFS(周检修业务统计数据!I:I,周检修业务统计数据!B:B,B98,周检修业务统计数据!C:C,"干箱",周检修业务统计数据!D:D,"<>COS")+SUMIFS(周检修业务统计数据!J:J,周检修业务统计数据!B:B,B98,周检修业务统计数据!C:C,"干箱",周检修业务统计数据!D:D,"<>COS"))*1.13++SUMIFS(周检修业务统计数据!L:L,周检修业务统计数据!B:B,B98,周检修业务统计数据!C:C,"干箱",周检修业务统计数据!D:D,"<>COS")*1.06 -> 0 | M98: =(L98-'2025年18周'!L98)/'2025年18周'!L98 -> #DIV/0! | N98: =L98/J98 -> #DIV/0! | O98: =(N98-'2025年18周'!N98)/'2025年18周'!N98 -> #DIV/0! | P98: =(SUMIFS(周检修业务统计数据!I:I,周检修业务统计数据!B:B,B98,周检修业务统计数据!C:C,"<>干箱")+SUMIFS(周检修业务统计数据!J:J,周检修业务统计数据!B:B,B98,周检修业务统计数据!C:C,"<>干箱"))*1.13++SUMIFS(周检修业务统计数据!L:L,周检修业务统计数据!B:B,B98,周检修业务统计数据!C:C,"<>干箱")*1.06 -> 0 | S98: =S240 -> 0 | T98: =C98+J98 -> 29 | U98: =E98+L98+I98+P98+Q98+R98+S98 -> 8652 | V98: =U98/W98 -> #DIV/0!
A99: 广州弘运 | B99: 新会亚太 | C99: =SUMIFS(周检修业务统计数据!E:E,周检修业务统计数据!B:B,B99,周检修业务统计数据!C:C,"干箱",周检修业务统计数据!D:D,"COS") -> 5 | D99: =C99-'2025年18周'!C99 -> 4 | E99: =(SUMIFS(周检修业务统计数据!I:I,周检修业务统计数据!B:B,B99,周检修业务统计数据!C:C,"干箱",周检修业务统计数据!D:D,"COS")+SUMIFS(周检修业务统计数据!J:J,周检修业务统计数据!B:B,B99,周检修业务统计数据!C:C,"干箱",周检修业务统计数据!D:D,"COS"))*1.13 -> 1205.74 | F99: =(E99-'2025年18周'!E99)/'2025年18周'!E99 -> 4.7422 | G99: =E99/C99 -> 241 | H99: =(G99-'2025年18周'!G99)/'2025年18周'!G99 -> 0.1476 | I99: =SUMIFS(周检修业务统计数据!L:L,周检修业务统计数据!B:B,B99,周检修业务统计数据!C:C,"干箱",周检修业务统计数据!D:D,"COS")*1.06 -> 374.975 | J99: =SUMIFS(周检修业务统计数据!E:E,周检修业务统计数据!B:B,B99,周检修业务统计数据!C:C,"干箱",周检修业务统计数据!D:D,"<>COS") -> 0 | K99: =J99-'2025年18周'!J99 -> 0 | L99: =(SUMIFS(周检修业务统计数据!I:I,周检修业务统计数据!B:B,B99,周检修业务统计数据!C:C,"干箱",周检修业务统计数据!D:D,"<>COS")+SUMIFS(周检修业务统计数据!J:J,周检修业务统计数据!B:B,B99,周检修业务统计数据!C:C,"干箱",周检修业务统计数据!D:D,"<>COS"))*1.13++SUMIFS(周检修业务统计数据!L:L,周检修业务统计数据!B:B,B99,周检修业务统计数据!C:C,"干箱",周检修业务统计数据!D:D,"<>COS")*1.06 -> 0 | M99: =(L99-'2025年18周'!L99)/'2025年18周'!L99 -> #DIV/0! | N99: =L99/J99 -> #DIV/0! | O99: =(N99-'2025年18周'!N99)/'2025年18周'!N99 -> #DIV/0! | P99: =(SUMIFS(周检修业务统计数据!I:I,周检修业务统计数据!B:B,B99,周检修业务统计数据!C:C,"<>干箱")+SUMIFS(周检修业务统计数据!J:J,周检修业务统计数据!B:B,B99,周检修业务统计数据!C:C,"<>干箱"))*1.13++SUMIFS(周检修业务统计数据!L:L,周检修业务统计数据!B:B,B99,周检修业务统计数据!C:C,"<>干箱")*1.06 -> 0 | S99: =S241 -> 0 | T99: =C99+J99 -> 5 | U99: =E99+L99+I99+P99+Q99+R99+S99 -> 1581 | V99: =U99/W99 -> #DIV/0!
A100: 广州弘运 | B100: 防城港 | C100: =SUMIFS(周检修业务统计数据!E:E,周检修业务统计数据!B:B,B100,周检修业务统计数据!C:C,"干箱",周检修业务统计数据!D:D,"COS") -> 0 | D100: =C100-'2025年18周'!C100 -> 0 | E100: =(SUMIFS(周检修业务统计数据!I:I,周检修业务统计数据!B:B,B100,周检修业务统计数据!C:C,"干箱",周检修业务统计数据!D:D,"COS")+SUMIFS(周检修业务统计数据!J:J,周检修业务统计数据!B:B,B100,周检修业务统计数据!C:C,"干箱",周检修业务统计数据!D:D,"COS"))*1.13 -> 0 | F100: =(E100-'2025年18周'!E100)/'2025年18周'!E100 -> #DIV/0! | G100: =E100/C100 -> #DIV/0! | H100: =(G100-'2025年18周'!G100)/'2025年18周'!G100 -> #DIV/0! | I100: =SUMIFS(周检修业务统计数据!L:L,周检修业务统计数据!B:B,B100,周检修业务统计数据!C:C,"干箱",周检修业务统计数据!D:D,"COS")*1.06 -> 0 | J100: =SUMIFS(周检修业务统计数据!E:E,周检修业务统计数据!B:B,B100,周检修业务统计数据!C:C,"干箱",周检修业务统计数据!D:D,"<>COS") -> 0 | K100: =J100-'2025年18周'!J100 -> 0 | L100: =(SUMIFS(周检修业务统计数据!I:I,周检修业务统计数据!B:B,B100,周检修业务统计数据!C:C,"干箱",周检修业务统计数据!D:D,"<>COS")+SUMIFS(周检修业务统计数据!J:J,周检修业务统计数据!B:B,B100,周检修业务统计数据!C:C,"干箱",周检修业务统计数据!D:D,"<>COS"))*1.13++SUMIFS(周检修业务统计数据!L:L,周检修业务统计数据!B:B,B100,周检修业务统计数据!C:C,"干箱",周检修业务统计数据!D:D,"<>COS")*1.06 -> 0 | M100: =(L100-'2025年18周'!L100)/'2025年18周'!L100 -> #DIV/0! | N100: =L100/J100 -> #DIV/0! | O100: =(N100-'2025年18周'!N100)/'2025年18周'!N100 -> #DIV/0! | P100: =(SUMIFS(周检修业务统计数据!I:I,周检修业务统计数据!B:B,B100,周检修业务统计数据!C:C,"<>干箱")+SUMIFS(周检修业务统计数据!J:J,周检修业务统计数据!B:B,B100,周检修业务统计数据!C:C,"<>干箱"))*1.13++SUMIFS(周检修业务统计数据!L:L,周检修业务统计数据!B:B,B100,周检修业务统计数据!C:C,"<>干箱")*1.06 -> 0 | S100: =S242 -> 0 | T100: =C100+J100 -> 0 | U100: =E100+L100+I100+P100+Q100+R100+S100 -> 0 | V100: =U100/W100 -> #DIV/0! | AC100: 关停，并给钦州弘运
A101: 广州弘运 | B101: 乐平码头弘运 | C101: =SUMIFS(周检修业务统计数据!E:E,周检修业务统计数据!B:B,B101,周检修业务统计数据!C:C,"干箱",周检修业务统计数据!D:D,"COS") -> 29 | D101: =C101-'2025年18周'!C101 -> -40 | E101: =(SUMIFS(周检修业务统计数据!I:I,周检修业务统计数据!B:B,B101,周检修业务统计数据!C:C,"干箱",周检修业务统计数据!D:D,"COS")+SUMIFS(周检修业务统计数据!J:J,周检修业务统计数据!B:B,B101,周检修业务统计数据!C:C,"干箱",周检修业务统计数据!D:D,"COS"))*1.13 -> 10338.99 | F101: =(E101-'2025年18周'!E101)/'2025年18周'!E101 -> -0.6141 | G101: =E101/C101 -> 357 | H101: =(G101-'2025年18周'!G101)/'2025年18周'!G101 -> -0.0799 | I101: =SUMIFS(周检修业务统计数据!L:L,周检修业务统计数据!B:B,B101,周检修业务统计数据!C:C,"干箱",周检修业务统计数据!D:D,"COS")*1.06 -> 1595.0986 | J101: =SUMIFS(周检修业务统计数据!E:E,周检修业务统计数据!B:B,B101,周检修业务统计数据!C:C,"干箱",周检修业务统计数据!D:D,"<>COS") -> 0 | K101: =J101-'2025年18周'!J101 -> 0 | L101: =(SUMIFS(周检修业务统计数据!I:I,周检修业务统计数据!B:B,B101,周检修业务统计数据!C:C,"干箱",周检修业务统计数据!D:D,"<>COS")+SUMIFS(周检修业务统计数据!J:J,周检修业务统计数据!B:B,B101,周检修业务统计数据!C:C,"干箱",周检修业务统计数据!D:D,"<>COS"))*1.13++SUMIFS(周检修业务统计数据!L:L,周检修业务统计数据!B:B,B101,周检修业务统计数据!C:C,"干箱",周检修业务统计数据!D:D,"<>COS")*1.06 -> 0 | M101: =(L101-'2025年18周'!L101)/'2025年18周'!L101 -> #DIV/0! | N101: =L101/J101 -> #DIV/0! | O101: =(N101-'2025年18周'!N101)/'2025年18周'!N101 -> #DIV/0! | P101: =(SUMIFS(周检修业务统计数据!I:I,周检修业务统计数据!B:B,B101,周检修业务统计数据!C:C,"<>干箱")+SUMIFS(周检修业务统计数据!J:J,周检修业务统计数据!B:B,B101,周检修业务统计数据!C:C,"<>干箱"))*1.13++SUMIFS(周检修业务统计数据!L:L,周检修业务统计数据!B:B,B101,周检修业务统计数据!C:C,"<>干箱")*1.06 -> 0 | S101: =S243 -> 0 | T101: =C101+J101 -> 29 | U101: =E101+L101+I101+P101+Q101+R101+S101 -> 11934 | V101: =U101/W101 -> #DIV/0! | AC101: 2022年10月新增
A102: 广州弘运 | B102: 南沙二期弘运 | C102: =SUMIFS(周检修业务统计数据!E:E,周检修业务统计数据!B:B,B102,周检修业务统计数据!C:C,"干箱",周检修业务统计数据!D:D,"COS") -> 24 | D102: =C102-'2025年18周'!C102 -> -99 | E102: =(SUMIFS(周检修业务统计数据!I:I,周检修业务统计数据!B:B,B102,周检修业务统计数据!C:C,"干箱",周检修业务统计数据!D:D,"COS")+SUMIFS(周检修业务统计数据!J:J,周检修业务统计数据!B:B,B102,周检修业务统计数据!C:C,"干箱",周检修业务统计数据!D:D,"COS"))*1.13 -> 3239.6 | F102: =(E102-'2025年18周'!E102)/'2025年18周'!E102 -> -0.8151 | G102: =E102/C102 -> 135 | H102: =(G102-'2025年18周'!G102)/'2025年18周'!G102 -> -0.0493 | I102: =SUMIFS(周检修业务统计数据!L:L,周检修业务统计数据!B:B,B102,周检修业务统计数据!C:C,"干箱",周检修业务统计数据!D:D,"COS")*1.06 -> 1799.88 | J102: =SUMIFS(周检修业务统计数据!E:E,周检修业务统计数据!B:B,B102,周检修业务统计数据!C:C,"干箱",周检修业务统计数据!D:D,"<>COS") -> 0 | K102: =J102-'2025年18周'!J102 -> 0 | L102: =(SUMIFS(周检修业务统计数据!I:I,周检修业务统计数据!B:B,B102,周检修业务统计数据!C:C,"干箱",周检修业务统计数据!D:D,"<>COS")+SUMIFS(周检修业务统计数据!J:J,周检修业务统计数据!B:B,B102,周检修业务统计数据!C:C,"干箱",周检修业务统计数据!D:D,"<>COS"))*1.13++SUMIFS(周检修业务统计数据!L:L,周检修业务统计数据!B:B,B102,周检修业务统计数据!C:C,"干箱",周检修业务统计数据!D:D,"<>COS")*1.06 -> 0 | M102: =(L102-'2025年18周'!L102)/'2025年18周'!L102 -> #DIV/0! | N102: =L102/J102 -> #DIV/0! | O102: =(N102-'2025年18周'!N102)/'2025年18周'!N102 -> #DIV/0! | P102: =(SUMIFS(周检修业务统计数据!I:I,周检修业务统计数据!B:B,B102,周检修业务统计数据!C:C,"<>干箱")+SUMIFS(周检修业务统计数据!J:J,周检修业务统计数据!B:B,B102,周检修业务统计数据!C:C,"<>干箱"))*1.13++SUMIFS(周检修业务统计数据!L:L,周检修业务统计数据!B:B,B102,周检修业务统计数据!C:C,"<>干箱")*1.06 -> 794.5 | S102: =S244 -> 0 | T102: =C102+J102 -> 24 | U102: =E102+L102+I102+P102+Q102+R102+S102 -> 5834 | V102: =U102/W102 -> #DIV/0!
A103: 钦州弘运 | B103: 北海港 | C103: =SUMIFS(周检修业务统计数据!E:E,周检修业务统计数据!B:B,B103,周检修业务统计数据!C:C,"干箱",周检修业务统计数据!D:D,"COS") -> 0 | D103: =C103-'2025年18周'!C103 -> 0 | E103: =(SUMIFS(周检修业务统计数据!I:I,周检修业务统计数据!B:B,B103,周检修业务统计数据!C:C,"干箱",周检修业务统计数据!D:D,"COS")+SUMIFS(周检修业务统计数据!J:J,周检修业务统计数据!B:B,B103,周检修业务统计数据!C:C,"干箱",周检修业务统计数据!D:D,"COS"))*1.13 -> 0 | F103: =(E103-'2025年18周'!E103)/'2025年18周'!E103 -> #DIV/0! | G103: =E103/C103 -> #DIV/0! | H103: =(G103-'2025年18周'!G103)/'2025年18周'!G103 -> #DIV/0! | I103: =SUMIFS(周检修业务统计数据!L:L,周检修业务统计数据!B:B,B103,周检修业务统计数据!C:C,"干箱",周检修业务统计数据!D:D,"COS")*1.06 -> 0 | J103: =SUMIFS(周检修业务统计数据!E:E,周检修业务统计数据!B:B,B103,周检修业务统计数据!C:C,"干箱",周检修业务统计数据!D:D,"<>COS") -> 0 | K103: =J103-'2025年18周'!J103 -> 0 | L103: =(SUMIFS(周检修业务统计数据!I:I,周检修业务统计数据!B:B,B103,周检修业务统计数据!C:C,"干箱",周检修业务统计数据!D:D,"<>COS")+SUMIFS(周检修业务统计数据!J:J,周检修业务统计数据!B:B,B103,周检修业务统计数据!C:C,"干箱",周检修业务统计数据!D:D,"<>COS"))*1.13++SUMIFS(周检修业务统计数据!L:L,周检修业务统计数据!B:B,B103,周检修业务统计数据!C:C,"干箱",周检修业务统计数据!D:D,"<>COS")*1.06 -> 0 | M103: =(L103-'2025年18周'!L103)/'2025年18周'!L103 -> #DIV/0! | N103: =L103/J103 -> #DIV/0! | O103: =(N103-'2025年18周'!N103)/'2025年18周'!N103 -> #DIV/0! | P103: =(SUMIFS(周检修业务统计数据!I:I,周检修业务统计数据!B:B,B103,周检修业务统计数据!C:C,"<>干箱")+SUMIFS(周检修业务统计数据!J:J,周检修业务统计数据!B:B,B103,周检修业务统计数据!C:C,"<>干箱"))*1.13++SUMIFS(周检修业务统计数据!L:L,周检修业务统计数据!B:B,B103,周检修业务统计数据!C:C,"<>干箱")*1.06 -> 0 | S103: =S245 -> 0 | T103: =C103+J103 -> 0 | U103: =E103+L103+I103+P103+Q103+R103+S103 -> 0 | V103: =U103/W103 -> #DIV/0!
A104: 钦州弘运 | B104: 铁山东岸港 | C104: =SUMIFS(周检修业务统计数据!E:E,周检修业务统计数据!B:B,B104,周检修业务统计数据!C:C,"干箱",周检修业务统计数据!D:D,"COS") -> 0 | D104: =C104-'2025年18周'!C104 -> 0 | E104: =(SUMIFS(周检修业务统计数据!I:I,周检修业务统计数据!B:B,B104,周检修业务统计数据!C:C,"干箱",周检修业务统计数据!D:D,"COS")+SUMIFS(周检修业务统计数据!J:J,周检修业务统计数据!B:B,B104,周检修业务统计数据!C:C,"干箱",周检修业务统计数据!D:D,"COS"))*1.13 -> 0 | F104: =(E104-'2025年18周'!E104)/'2025年18周'!E104 -> #DIV/0! | G104: =E104/C104 -> #DIV/0! | H104: =(G104-'2025年18周'!G104)/'2025年18周'!G104 -> #DIV/0! | I104: =SUMIFS(周检修业务统计数据!L:L,周检修业务统计数据!B:B,B104,周检修业务统计数据!C:C,"干箱",周检修业务统计数据!D:D,"COS")*1.06 -> 0 | J104: =SUMIFS(周检修业务统计数据!E:E,周检修业务统计数据!B:B,B104,周检修业务统计数据!C:C,"干箱",周检修业务统计数据!D:D,"<>COS") -> 0 | K104: =J104-'2025年18周'!J104 -> 0 | L104: =(SUMIFS(周检修业务统计数据!I:I,周检修业务统计数据!B:B,B104,周检修业务统计数据!C:C,"干箱",周检修业务统计数据!D:D,"<>COS")+SUMIFS(周检修业务统计数据!J:J,周检修业务统计数据!B:B,B104,周检修业务统计数据!C:C,"干箱",周检修业务统计数据!D:D,"<>COS"))*1.13++SUMIFS(周检修业务统计数据!L:L,周检修业务统计数据!B:B,B104,周检修业务统计数据!C:C,"干箱",周检修业务统计数据!D:D,"<>COS")*1.06 -> 0 | M104: =(L104-'2025年18周'!L104)/'2025年18周'!L104 -> #DIV/0! | N104: =L104/J104 -> #DIV/0! | O104: =(N104-'2025年18周'!N104)/'2025年18周'!N104 -> #DIV/0! | P104: =(SUMIFS(周检修业务统计数据!I:I,周检修业务统计数据!B:B,B104,周检修业务统计数据!C:C,"<>干箱")+SUMIFS(周检修业务统计数据!J:J,周检修业务统计数据!B:B,B104,周检修业务统计数据!C:C,"<>干箱"))*1.13++SUMIFS(周检修业务统计数据!L:L,周检修业务统计数据!B:B,B104,周检修业务统计数据!C:C,"<>干箱")*1.06 -> 0 | S104: =S246 -> 0 | T104: =C104+J104 -> 0 | U104: =E104+L104+I104+P104+Q104+R104+S104 -> 0 | V104: =U104/W104 -> #DIV/0!
A105: 钦州弘运 | B105: 广西钦州港外包 | C105: =SUMIFS(周检修业务统计数据!E:E,周检修业务统计数据!B:B,B105,周检修业务统计数据!C:C,"干箱",周检修业务统计数据!D:D,"COS") -> 108 | D105: =C105-'2025年18周'!C105 -> 108 | E105: =(SUMIFS(周检修业务统计数据!I:I,周检修业务统计数据!B:B,B105,周检修业务统计数据!C:C,"干箱",周检修业务统计数据!D:D,"COS")+SUMIFS(周检修业务统计数据!J:J,周检修业务统计数据!B:B,B105,周检修业务统计数据!C:C,"干箱",周检修业务统计数据!D:D,"COS"))*1.13 -> 40053.16 | F105: =(E105-'2025年18周'!E105)/'2025年18周'!E105 -> #DIV/0! | G105: =E105/C105 -> 371 | H105: =(G105-'2025年18周'!G105)/'2025年18周'!G105 -> #DIV/0! | I105: =SUMIFS(周检修业务统计数据!L:L,周检修业务统计数据!B:B,B105,周检修业务统计数据!C:C,"干箱",周检修业务统计数据!D:D,"COS")*1.06 -> 5940.3672 | J105: =SUMIFS(周检修业务统计数据!E:E,周检修业务统计数据!B:B,B105,周检修业务统计数据!C:C,"干箱",周检修业务统计数据!D:D,"<>COS") -> 0 | K105: =J105-'2025年18周'!J105 -> 0 | L105: =(SUMIFS(周检修业务统计数据!I:I,周检修业务统计数据!B:B,B105,周检修业务统计数据!C:C,"干箱",周检修业务统计数据!D:D,"<>COS")+SUMIFS(周检修业务统计数据!J:J,周检修业务统计数据!B:B,B105,周检修业务统计数据!C:C,"干箱",周检修业务统计数据!D:D,"<>COS"))*1.13++SUMIFS(周检修业务统计数据!L:L,周检修业务统计数据!B:B,B105,周检修业务统计数据!C:C,"干箱",周检修业务统计数据!D:D,"<>COS")*1.06 -> 0 | M105: =(L105-'2025年18周'!L105)/'2025年18周'!L105 -> #DIV/0! | N105: =L105/J105 -> #DIV/0! | O105: =(N105-'2025年18周'!N105)/'2025年18周'!N105 -> #DIV/0! | P105: =(SUMIFS(周检修业务统计数据!I:I,周检修业务统计数据!B:B,B105,周检修业务统计数据!C:C,"<>干箱")+SUMIFS(周检修业务统计数据!J:J,周检修业务统计数据!B:B,B105,周检修业务统计数据!C:C,"<>干箱"))*1.13++SUMIFS(周检修业务统计数据!L:L,周检修业务统计数据!B:B,B105,周检修业务统计数据!C:C,"<>干箱")*1.06 -> 158.6 | S105: =S247 -> 0 | T105: =C105+J105 -> 108 | U105: =E105+L105+I105+P105+Q105+R105+S105 -> 46152 | V105: =U105/W105 -> #DIV/0! | AC105: 业务外移到外堆场
A106: 钦州弘运 | B106: 防城港钦州弘运 | C106: =SUMIFS(周检修业务统计数据!E:E,周检修业务统计数据!B:B,B106,周检修业务统计数据!C:C,"干箱",周检修业务统计数据!D:D,"COS") -> 151 | D106: =C106-'2025年18周'!C106 -> -66 | E106: =(SUMIFS(周检修业务统计数据!I:I,周检修业务统计数据!B:B,B106,周检修业务统计数据!C:C,"干箱",周检修业务统计数据!D:D,"COS")+SUMIFS(周检修业务统计数据!J:J,周检修业务统计数据!B:B,B106,周检修业务统计数据!C:C,"干箱",周检修业务统计数据!D:D,"COS"))*1.13 -> 43425.7 | F106: =(E106-'2025年18周'!E106)/'2025年18周'!E106 -> -0.1953 | G106: =E106/C106 -> 288 | H106: =(G106-'2025年18周'!G106)/'2025年18周'!G106 -> 0.1566 | I106: =SUMIFS(周检修业务统计数据!L:L,周检修业务统计数据!B:B,B106,周检修业务统计数据!C:C,"干箱",周检修业务统计数据!D:D,"COS")*1.06 -> 8305.5134 | J106: =SUMIFS(周检修业务统计数据!E:E,周检修业务统计数据!B:B,B106,周检修业务统计数据!C:C,"干箱",周检修业务统计数据!D:D,"<>COS") -> 0 | K106: =J106-'2025年18周'!J106 -> -4 | L106: =(SUMIFS(周检修业务统计数据!I:I,周检修业务统计数据!B:B,B106,周检修业务统计数据!C:C,"干箱",周检修业务统计数据!D:D,"<>COS")+SUMIFS(周检修业务统计数据!J:J,周检修业务统计数据!B:B,B106,周检修业务统计数据!C:C,"干箱",周检修业务统计数据!D:D,"<>COS"))*1.13++SUMIFS(周检修业务统计数据!L:L,周检修业务统计数据!B:B,B106,周检修业务统计数据!C:C,"干箱",周检修业务统计数据!D:D,"<>COS")*1.06 -> 0 | M106: =(L106-'2025年18周'!L106)/'2025年18周'!L106 -> -1 | N106: =L106/J106 -> #DIV/0! | O106: =(N106-'2025年18周'!N106)/'2025年18周'!N106 -> #DIV/0! | P106: =(SUMIFS(周检修业务统计数据!I:I,周检修业务统计数据!B:B,B106,周检修业务统计数据!C:C,"<>干箱")+SUMIFS(周检修业务统计数据!J:J,周检修业务统计数据!B:B,B106,周检修业务统计数据!C:C,"<>干箱"))*1.13++SUMIFS(周检修业务统计数据!L:L,周检修业务统计数据!B:B,B106,周检修业务统计数据!C:C,"<>干箱")*1.06 -> 0 | S106: =S248 -> 0 | T106: =C106+J106 -> 151 | U106: =E106+L106+I106+P106+Q106+R106+S106 -> 51731 | V106: =U106/W106 -> #DIV/0!
A107: 钦州弘运 | B107: 广西铁山港 | C107: =SUMIFS(周检修业务统计数据!E:E,周检修业务统计数据!B:B,B107,周检修业务统计数据!C:C,"干箱",周检修业务统计数据!D:D,"COS") -> 238 | D107: =C107-'2025年18周'!C107 -> -26 | E107: =(SUMIFS(周检修业务统计数据!I:I,周检修业务统计数据!B:B,B107,周检修业务统计数据!C:C,"干箱",周检修业务统计数据!D:D,"COS")+SUMIFS(周检修业务统计数据!J:J,周检修业务统计数据!B:B,B107,周检修业务统计数据!C:C,"干箱",周检修业务统计数据!D:D,"COS"))*1.13 -> 36900.72 | F107: =(E107-'2025年18周'!E107)/'2025年18周'!E107 -> -0.1279 | G107: =E107/C107 -> 155 | H107: =(G107-'2025年18周'!G107)/'2025年18周'!G107 -> -0.0313 | I107: =SUMIFS(周检修业务统计数据!L:L,周检修业务统计数据!B:B,B107,周检修业务统计数据!C:C,"干箱",周检修业务统计数据!D:D,"COS")*1.06 -> 13170.776 | J107: =SUMIFS(周检修业务统计数据!E:E,周检修业务统计数据!B:B,B107,周检修业务统计数据!C:C,"干箱",周检修业务统计数据!D:D,"<>COS") -> 0 | K107: =J107-'2025年18周'!J107 -> 0 | L107: =(SUMIFS(周检修业务统计数据!I:I,周检修业务统计数据!B:B,B107,周检修业务统计数据!C:C,"干箱",周检修业务统计数据!D:D,"<>COS")+SUMIFS(周检修业务统计数据!J:J,周检修业务统计数据!B:B,B107,周检修业务统计数据!C:C,"干箱",周检修业务统计数据!D:D,"<>COS"))*1.13++SUMIFS(周检修业务统计数据!L:L,周检修业务统计数据!B:B,B107,周检修业务统计数据!C:C,"干箱",周检修业务统计数据!D:D,"<>COS")*1.06 -> 0 | M107: =(L107-'2025年18周'!L107)/'2025年18周'!L107 -> #DIV/0! | N107: =L107/J107 -> #DIV/0! | O107: =(N107-'2025年18周'!N107)/'2025年18周'!N107 -> #DIV/0! | P107: =(SUMIFS(周检修业务统计数据!I:I,周检修业务统计数据!B:B,B107,周检修业务统计数据!C:C,"<>干箱")+SUMIFS(周检修业务统计数据!J:J,周检修业务统计数据!B:B,B107,周检修业务统计数据!C:C,"<>干箱"))*1.13++SUMIFS(周检修业务统计数据!L:L,周检修业务统计数据!B:B,B107,周检修业务统计数据!C:C,"<>干箱")*1.06 -> 0 | S107: =S249 -> 0 | T107: =C107+J107 -> 238 | U107: =E107+L107+I107+P107+Q107+R107+S107 -> 50071 | V107: =U107/W107 -> #DIV/0!
A108: 钦州弘运 | B108: 广西铁山港外堆场 | C108: =SUMIFS(周检修业务统计数据!E:E,周检修业务统计数据!B:B,B108,周检修业务统计数据!C:C,"干箱",周检修业务统计数据!D:D,"COS") -> 209 | D108: =C108-'2025年18周'!C108 -> -8 | E108: =(SUMIFS(周检修业务统计数据!I:I,周检修业务统计数据!B:B,B108,周检修业务统计数据!C:C,"干箱",周检修业务统计数据!D:D,"COS")+SUMIFS(周检修业务统计数据!J:J,周检修业务统计数据!B:B,B108,周检修业务统计数据!C:C,"干箱",周检修业务统计数据!D:D,"COS"))*1.13 -> 59774.8 | F108: =(E108-'2025年18周'!E108)/'2025年18周'!E108 -> -0.0837 | G108: =E108/C108 -> 286 | H108: =(G108-'2025年18周'!G108)/'2025年18周'!G108 -> -0.0498 | I108: =SUMIFS(周检修业务统计数据!L:L,周检修业务统计数据!B:B,B108,周检修业务统计数据!C:C,"干箱",周检修业务统计数据!D:D,"COS")*1.06 -> 0 | J108: =SUMIFS(周检修业务统计数据!E:E,周检修业务统计数据!B:B,B108,周检修业务统计数据!C:C,"干箱",周检修业务统计数据!D:D,"<>COS") -> 9 | K108: =J108-'2025年18周'!J108 -> 9 | L108: =(SUMIFS(周检修业务统计数据!I:I,周检修业务统计数据!B:B,B108,周检修业务统计数据!C:C,"干箱",周检修业务统计数据!D:D,"<>COS")+SUMIFS(周检修业务统计数据!J:J,周检修业务统计数据!B:B,B108,周检修业务统计数据!C:C,"干箱",周检修业务统计数据!D:D,"<>COS"))*1.13++SUMIFS(周检修业务统计数据!L:L,周检修业务统计数据!B:B,B108,周检修业务统计数据!C:C,"干箱",周检修业务统计数据!D:D,"<>COS")*1.06 -> 3733.98 | M108: =(L108-'2025年18周'!L108)/'2025年18周'!L108 -> #DIV/0! | N108: =L108/J108 -> 415 | O108: =(N108-'2025年18周'!N108)/'2025年18周'!N108 -> #DIV/0! | P108: =(SUMIFS(周检修业务统计数据!I:I,周检修业务统计数据!B:B,B108,周检修业务统计数据!C:C,"<>干箱")+SUMIFS(周检修业务统计数据!J:J,周检修业务统计数据!B:B,B108,周检修业务统计数据!C:C,"<>干箱"))*1.13++SUMIFS(周检修业务统计数据!L:L,周检修业务统计数据!B:B,B108,周检修业务统计数据!C:C,"<>干箱")*1.06 -> 0 | S108: =S250 -> 0 | T108: =C108+J108 -> 218 | U108: =E108+L108+I108+P108+Q108+R108+S108 -> 63509 | V108: =U108/W108 -> #DIV/0!
A109: 弘运天浩 | B109: 江门三埠港 | C109: =SUMIFS(周检修业务统计数据!E:E,周检修业务统计数据!B:B,B109,周检修业务统计数据!C:C,"干箱",周检修业务统计数据!D:D,"COS") -> 58 | D109: =C109-'2025年18周'!C109 -> -4 | E109: =(SUMIFS(周检修业务统计数据!I:I,周检修业务统计数据!B:B,B109,周检修业务统计数据!C:C,"干箱",周检修业务统计数据!D:D,"COS")+SUMIFS(周检修业务统计数据!J:J,周检修业务统计数据!B:B,B109,周检修业务统计数据!C:C,"干箱",周检修业务统计数据!D:D,"COS"))*1.13 -> 18117.97 | F109: =(E109-'2025年18周'!E109)/'2025年18周'!E109 -> -0.2232 | G109: =E109/C109 -> 312 | H109: =(G109-'2025年18周'!G109)/'2025年18周'!G109 -> -0.1702 | I109: =SUMIFS(周检修业务统计数据!L:L,周检修业务统计数据!B:B,B109,周检修业务统计数据!C:C,"干箱",周检修业务统计数据!D:D,"COS")*1.06 -> 3290.1552 | J109: =SUMIFS(周检修业务统计数据!E:E,周检修业务统计数据!B:B,B109,周检修业务统计数据!C:C,"干箱",周检修业务统计数据!D:D,"<>COS") -> 0 | K109: =J109-'2025年18周'!J109 -> 0 | L109: =(SUMIFS(周检修业务统计数据!I:I,周检修业务统计数据!B:B,B109,周检修业务统计数据!C:C,"干箱",周检修业务统计数据!D:D,"<>COS")+SUMIFS(周检修业务统计数据!J:J,周检修业务统计数据!B:B,B109,周检修业务统计数据!C:C,"干箱",周检修业务统计数据!D:D,"<>COS"))*1.13++SUMIFS(周检修业务统计数据!L:L,周检修业务统计数据!B:B,B109,周检修业务统计数据!C:C,"干箱",周检修业务统计数据!D:D,"<>COS")*1.06 -> 0 | M109: =(L109-'2025年18周'!L109)/'2025年18周'!L109 -> #DIV/0! | N109: =L109/J109 -> #DIV/0! | O109: =(N109-'2025年18周'!N109)/'2025年18周'!N109 -> #DIV/0! | P109: =(SUMIFS(周检修业务统计数据!I:I,周检修业务统计数据!B:B,B109,周检修业务统计数据!C:C,"<>干箱")+SUMIFS(周检修业务统计数据!J:J,周检修业务统计数据!B:B,B109,周检修业务统计数据!C:C,"<>干箱"))*1.13++SUMIFS(周检修业务统计数据!L:L,周检修业务统计数据!B:B,B109,周检修业务统计数据!C:C,"<>干箱")*1.06 -> 0 | S109: =S251 -> 0 | T109: =C109+J109 -> 58 | U109: =E109+L109+I109+P109+Q109+R109+S109 -> 21408 | V109: =U109/W109 -> #DIV/0!
A110: 万建达 | B110: 防城港万建达堆场 | C110: =SUMIFS(周检修业务统计数据!E:E,周检修业务统计数据!B:B,B110,周检修业务统计数据!C:C,"干箱",周检修业务统计数据!D:D,"COS") -> 329 | D110: =C110-'2025年18周'!C110 -> -412 | E110: =(SUMIFS(周检修业务统计数据!I:I,周检修业务统计数据!B:B,B110,周检修业务统计数据!C:C,"干箱",周检修业务统计数据!D:D,"COS")+SUMIFS(周检修业务统计数据!J:J,周检修业务统计数据!B:B,B110,周检修业务统计数据!C:C,"干箱",周检修业务统计数据!D:D,"COS"))*1.13 -> 117602.03 | F110: =(E110-'2025年18周'!E110)/'2025年18周'!E110 -> -0.5767 | G110: =E110/C110 -> 357 | H110: =(G110-'2025年18周'!G110)/'2025年18周'!G110 -> -0.048 | I110: =SUMIFS(周检修业务统计数据!L:L,周检修业务统计数据!B:B,B110,周检修业务统计数据!C:C,"干箱",周检修业务统计数据!D:D,"COS")*1.06 -> 0 | J110: =SUMIFS(周检修业务统计数据!E:E,周检修业务统计数据!B:B,B110,周检修业务统计数据!C:C,"干箱",周检修业务统计数据!D:D,"<>COS") -> 0 | K110: =J110-'2025年18周'!J110 -> 0 | L110: =(SUMIFS(周检修业务统计数据!I:I,周检修业务统计数据!B:B,B110,周检修业务统计数据!C:C,"干箱",周检修业务统计数据!D:D,"<>COS")+SUMIFS(周检修业务统计数据!J:J,周检修业务统计数据!B:B,B110,周检修业务统计数据!C:C,"干箱",周检修业务统计数据!D:D,"<>COS"))*1.13++SUMIFS(周检修业务统计数据!L:L,周检修业务统计数据!B:B,B110,周检修业务统计数据!C:C,"干箱",周检修业务统计数据!D:D,"<>COS")*1.06 -> 0 | M110: =(L110-'2025年18周'!L110)/'2025年18周'!L110 -> #DIV/0! | N110: =L110/J110 -> #DIV/0! | O110: =(N110-'2025年18周'!N110)/'2025年18周'!N110 -> #DIV/0! | P110: =(SUMIFS(周检修业务统计数据!I:I,周检修业务统计数据!B:B,B110,周检修业务统计数据!C:C,"<>干箱")+SUMIFS(周检修业务统计数据!J:J,周检修业务统计数据!B:B,B110,周检修业务统计数据!C:C,"<>干箱"))*1.13++SUMIFS(周检修业务统计数据!L:L,周检修业务统计数据!B:B,B110,周检修业务统计数据!C:C,"<>干箱")*1.06 -> 0 | S110: =S252 -> 0 | T110: =C110+J110 -> 329 | U110: =E110+L110+I110+P110+Q110+R110+S110 -> 117602 | V110: =U110/W110 -> #DIV/0!
...

Sheet 自营2026周完成情况
A1: 财务月（2025年） | B1: 1月 | C1: 2月 | D1: 3月 | E1: 4月 | F1: 5月 | G1: 6月 | H1: 7月 | I1: 8月 | J1: 9月 | K1: 10月 | L1: 11月 | M1: 12月
A2: 财务月天数 | B2: 31 | C2: 31 | D2: 28 | E2: 31 | F2: 30 | G2: 31 | H2: 30 | I2: 31 | J2: 31 | K2: 30 | L2: 31 | M2: 30
A3: 财务月产值指标比100% | B3: =B4/29000 -> 0.078 | C3: =C4/29000 -> 0.061 | D3: =D4/29000 -> 0.078 | E3: =E4/29000 -> 0.082 | F3: =F4/29000 -> 0.082 | G3: =G4/29000 -> 0.089 | H3: =H4/29000 -> 0.089 | I3: =I4/29000 -> 0.089 | ... M3: =M4/29000 -> 0.083
A4: 财务月指标（年25900万） | B4: 2268 | C4: 1780 | D4: 2268 | E4: 2368 | F4: 2368 | G4: 2590 | H4: 2590 | I4: 2590 | J4: 2590 | K4: 2505 | L4: 2668 | M4: 2415
A5: 每天产值指标 | B5: =B4/B2 -> 73.16 | C5: =C4/C2 -> 57.42 | D5: =D4/D2 -> 81 | E5: =E4/E2 -> 76.39 | F5: =F4/F2 -> 78.93 | G5: =G4/G2 -> 83.55 | H5: =H4/H2 -> 86.33 | I5: =I4/I2 -> 83.55 | ... M5: =M4/M2 -> 80.5
A6: 生产月完成指标
A7: 财务月完成指标
A8: 财务月度指标完成比例 | B8: =B7/B4 -> 0 | C8: =C7/C4 -> 0 | D8: =D7/D4 -> 0 | E8: =E7/E4 -> 0 | F8: =F7/F4 -> 0 | G8: =G7/G4 -> 0 | H8: =H7/H4 -> 0 | I8: =I7/I4 -> 0 | ... L8: =L7/L4 -> 0
A11: 自营每周产值（2025年） | B11: 第1周 | C11: 第2周 | D11: 第3周 | E11: 第4周 | F11: 第5周 | G11: 第6周 | H11: 第7周 | I11: 第8周 | J11: 第9周 | K11: 第10周 | L11: 第11周 | M11: 第12周 | N11: 第13周 | O11: 第14周 | P11: 第15周 | Q11: 第16周 | R11: 第17周 | S11: 第18周 | T11: 第19周 | U11: 第20周 | V11: 第21周 | W11: 第22周 | X11: 第23周 | Y11: 第24周 | Z11: 第25周 | AA11: 第26周 | AB11: 第27周 | AC11: 第28周 | AD11: 第29周 | AE11: 第30周 | AF11: 第31周 | AG11: 第32周 | AH11: 第33周 | AI11: 第34周 | AJ11: 第35周 | AK11: 第36周 | AL11: 第37周 | AM11: 第38周 | AN11: 第39周 | AO11: 第40周 | AP11: 第41周 | AQ11: 第42周 | AR11: 第43周 | AS11: 第44周 | AT11: 第45周 | AU11: 第46周 | AV11: 第47周 | AW11: 第48周 | AX11: 第49周 | AY11: 第50周 | AZ11: 第51周 | BA11: 第52周 | BB11: 合计
A12: 生产周起始时间 | B12: 1225-1231 | C12: 0101-0107 | D12: 0108-0114 | E12: 0115-0121 | F12: 0122-0128 | G12: 0229-0204 | H12: 0205-0211 | I12: 0212-0218 | J12: 0219-0225 | K12: 0226-0304 | L12: 0305-0311 | M12: 0312-0328 | N12: 0319-0325 | O12: 0326-0401 | P12: 0402-0408 | Q12: 0409-0415 | R12: 0416-0422 | S12: 0423-0429 | T12: 0430-0506
A13: 生产周产值指标（万元） | B13: =7*$B$5 -> 512.12 | C13: =7*$B$5 -> 512.12 | D13: =7*$B$5 -> 512.12 | E13: =7*$B$5 -> 512.12 | F13: =B5*3+4*C5 -> 449.16 | G13: =$C$5*7 -> 401.94 | H13: =$C$5*7 -> 401.94 | I13: =$C$5*7 -> 401.94 | J13: =C5*5+D5*2 -> 449.1 | K13: =$D$5*7 -> 567 | L13: =$D$5*7 -> 567 | M13: =$D$5*7 -> 567 | N13: =$D$5*5+$E$5*2 -> 557.78 | O13: =$E$5*7 -> 534.73 | P13: =$E$5*7 -> 534.73 | Q13: =$E$5*7 -> 534.73 | R13: =$E$5*7 -> 534.73 | S13: =$E$5*6+$F$5*1 -> 537.27 | T13: =$F$5*7 -> 552.51 | U13: =$F$5*7 -> 552.51 | V13: =$F$5*7 -> 552.51 | W13: =$F$5*7 -> 552.51 | X13: =$F$5*3+$G$5*4 -> 570.99 | Y13: =$G$5*7 -> 584.85 | Z13: =$G$5*7 -> 584.85 | AA13: =$G$5*7 -> 584.85 | AB13: =$G$5*4+$H$5*3 -> 593.19 | AC13: =$H$5*7 -> 604.31 | AD13: =$H$5*7 -> 604.31 | AE13: =$H$5*7 -> 604.31 | AF13: =$H$5*7 -> 604.31 | AG13: =$I$5*7 -> 584.85 | AH13: =$I$5*7 -> 584.85 | AI13: =$I$5*7 -> 584.85 | AJ13: =$I$5*7 -> 584.85 | AK13: =$I$5*4+$J$5*3 -> 584.85 | AL13: =$J$5*7 -> 584.85 | AM13: =$J$5*7 -> 584.85 | AN13: =$J$5*7 -> 584.85 | AO13: =$J$5*7 -> 584.85 | AP13: =$J$5*7 -> 584.85 | AQ13: =$K$5*7 -> 584.5 | AR13: =$K$5*7 -> 584.5 | AS13: =$K$5*7 -> 584.5 | AT13: =$L$5*7 -> 602.42 | AU13: =$L$5*7 -> 602.42 | AV13: =$L$5*7 -> 602.42 | AW13: =$L$5*7 -> 602.42 | AX13: =$L$5*3+$M$5*4 -> 580.18 | AY13: =$M$5*7 -> 563.5 | AZ13: =$M$5*7 -> 563.5 | BA13: =$M$5*7 -> 563.5 | BB13: =SUM(B13:BA13) -> 28915.9
A14: 生产周实际完成产值（元） | B14: =B52 -> 5530553.3 | C14: =C52 -> 4852687.7 | D14: =D52 -> 6290487.2 | E14: =E52 -> 6214755.6 | F14: =F52 -> 6629699.8 | G14: =G52 -> 5427768.5 | H14: =H52 -> 5318554.3 | I14: =I52 -> 1824749.4 | ... BA14: =BA52 -> 0 | BB14: =SUM(B14:BA14) -> 99153639
A15: 生产周指标完成情况 | B15: =B14/(B13*10000) -> 1.0799 | C15: =C14/(C13*10000) -> 0.9476 | D15: =D14/(D13*10000) -> 1.2283 | E15: =E14/(E13*10000) -> 1.2135 | F15: =F14/(F13*10000) -> 1.476 | G15: =G14/(G13*10000) -> 1.3504 | H15: =H14/(H13*10000) -> 1.3232 | I15: =I14/(I13*10000) -> 0.454 | ... BA15: =BA14/(BA13*10000) -> 0
A17: 生产周累积产值完成指标 | B17: =BB14/(SUMIF(B14:BA14,"<>0 ",B13:BA13)*10000) -> 1.0286
A18: 完成全年总产值指标比 | B18: =BE52 -> 0.3419
A19: 生产时间与全年时间占比 | B19: =BF52 -> 0.3654
A21: 自营每周（2025年） | B21: 周累计箱量 | C21: 周累计量同比 | D21: 周累计产值(万) | E21: 周累计产值同比（万） | F21: 当周完成箱量 | G21: 当周指标差额
A22: 深圳运营中心 | B22: =BB35 -> 10160 | C22: =BC35 -> -6505 | D22: =BB45/10000 -> 1235 | E22: =BC45/10000 -> 484 | F22: ='2026年第19周'!T4 -> 344 | G22: ='2026年第19周'!Y4 -> -556
A23: 广州运营中心 | B23: =BB36 -> 51345 | C23: =BC36 -> -276 | D23: =BB46/10000 -> 1194 | E23: =BC46/10000 -> -92 | F23: ='2026年第19周'!T5 -> 2139 | G23: ='2026年第19周'!Y5 -> -361
A24: 珠三角运营中心 | B24: =BB37 -> 38596 | C24: =BC37 -> -8326 | D24: =BB47/10000 -> 1156 | E24: =BC47/10000 -> -191 | F24: ='2026年第19周'!T6 -> 1471 | G24: ='2026年第19周'!Y6 -> -1529
A25: 粤西 | B25: =BB38 -> 24386 | C25: =BC38 -> 3060 | D25: =BB48/10000 -> 826 | E25: =BC48/10000 -> 70 | F25: ='2026年第19周'!T7 -> 1134 | G25: ='2026年第19周'!Y7 -> 34
A26: 北部湾 | B26: =BB39 -> 39046 | C26: =BC39 -> 10062 | D26: =BB49/10000 -> 1279 | E26: =BC49/10000 -> 132 | F26: ='2026年第19周'!T8 -> 1550 | G26: ='2026年第19周'!Y8 -> 50
A27: 南岗分公司 | B27: =BB40 -> 11367 | C27: =BC40 -> 4307 | D27: =BB50/10000 -> 593 | E27: =BC50/10000 -> 95 | F27: ='2026年第19周'!T9 -> 190 | G27: ='2026年第19周'!Y9 -> -410
A28: 自营总计 | B28: =BB41 -> 174900 | C28: =BC41 -> 2322 | D28: =BB51/10000 -> 6283 | E28: =BC51/10000 -> 498 | F28: ='2026年第19周'!T10 -> 6828 | G28: ='2026年第19周'!Y10 -> -2772
A29: 总计完成 | B29: =BB42 -> 333785 | C29: =BC42 -> 48141 | D29: =BB52/10000 -> 9915 | E29: =BC52/10000 -> 1506 | F29: ='2026年第19周'!T36 -> 13577
A34: 自营每周箱量（2026年） | B34: 第1周 | C34: 第2周 | D34: 第3周 | E34: 第4周 | F34: 第5周 | G34: 第6周 | H34: 第7周 | I34: 第8周 | J34: 第9周 | K34: 第10周 | L34: 第11周 | M34: 第12周 | N34: 第13周 | O34: 第14周 | P34: 第15周 | Q34: 第16周 | R34: 第17周 | S34: 第18周 | T34: 第19周 | U34: 第20周 | V34: 第21周 | W34: 第22周 | X34: 第23周 | Y34: 第24周 | Z34: 第25周 | AA34: 第26周 | AB34: 第27周 | AC34: 第28周 | AD34: 第29周 | AE34: 第30周 | AF34: 第31周 | AG34: 第32周 | AH34: 第33周 | AI34: 第34周 | AJ34: 第35周 | AK34: 第36周 | AL34: 第37周 | AM34: 第38周 | AN34: 第39周 | AO34: 第40周 | AP34: 第41周 | AQ34: 第42周 | AR34: 第43周 | AS34: 第44周 | AT34: 第45周 | AU34: 第46周 | AV34: 第47周 | AW34: 第48周 | AX34: 第49周 | AY34: 第50周 | AZ34: 第51周 | BA34: 第52周 | BB34: 合计 | BC34: 同比2025年
A35: 深圳运营中心 | B35: 781 | C35: 710 | D35: 634 | E35: 686 | F35: 618 | G35: 569 | H35: 589 | I35: 50 | J35: 182 | K35: 446 | L35: 435 | M35: 576 | N35: 613 | O35: 694 | P35: 356 | Q35: 691 | R35: 559 | S35: 627 | T35: 344 | AY35: 0 | AZ35: 0 | BA35: 0 | BB35: =SUM(B35:BA35) -> 10160 | BC35: =BB35-(SUMIF(B35:BA35,"<>0",B100:BA100)) -> -6505
A36: 广州运营中心 | B36: 3534 | C36: 2523 | D36: 3511 | E36: 2946 | F36: 2919 | G36: 2620 | H36: 2562 | I36: 555 | J36: 336 | K36: 2462 | L36: 3368 | M36: 3252 | N36: 2947 | O36: 3285 | P36: 3088 | Q36: 3153 | R36: 3148 | S36: 2997 | T36: 2139 | BB36: =SUM(B36:BA36) -> 51345 | BC36: =BB36-(SUMIF(B36:BA36,"<>0",B101:BA101)) -> -276
A37: 珠三角运营中心 | B37: 2618 | C37: 2250 | D37: 2408 | E37: 2412 | F37: 2609 | G37: 1913 | H37: 1391 | I37: 225 | J37: 204 | K37: 1396 | L37: 2577 | M37: 2345 | N37: 2907 | O37: 2347 | P37: 2257 | Q37: 2447 | R37: 2286 | S37: 2533 | T37: 1471 | BB37: =SUM(B37:BA37) -> 38596 | BC37: =BB37-(SUMIF(B37:BA37,"<>0",B102:BA102)) -> -8326
A38: 粤西 | B38: 1141 | C38: 1225 | D38: 1596 | E38: 1220 | F38: 1478 | G38: 1750 | H38: 1847 | I38: 732 | J38: 403 | K38: 811 | L38: 1294 | M38: 1251 | N38: 1523 | O38: 1443 | P38: 1479 | Q38: 1690 | R38: 995 | S38: 1374 | T38: 1134 | BB38: =SUM(B38:BA38) -> 24386 | BC38: =BB38-(SUMIF(B38:BA38,"<>0",B103:BA103)) -> 3060
A39: 北部湾 | B39: 2211 | C39: 1969 | D39: 2109 | E39: 2356 | F39: 1934 | G39: 2020 | H39: 1953 | I39: 1402 | J39: 1071 | K39: 2409 | L39: 2299 | M39: 2356 | N39: 2241 | O39: 2519 | P39: 1942 | Q39: 2566 | R39: 2168 | S39: 1971 | T39: 1550 | BB39: =SUM(B39:BA39) -> 39046 | BC39: =BB39-(SUMIF(B39:BA39,"<>0",B104:BA104)) -> 10062
A40: 南岗分公司 | B40: 801 | C40: 392 | D40: 607 | E40: 687 | F40: 809 | G40: 756 | H40: 869 | I40: 122 | J40: 74 | K40: 666 | L40: 511 | M40: 623 | N40: 609 | O40: 1161 | P40: 273 | Q40: 353 | R40: 1196 | S40: 668 | T40: 190 | BB40: =SUM(B40:BA40) -> 11367 | BC40: =BB40-(SUMIF(B40:BA40,"<>0",B105:BA105)) -> 4307
A41: 自营总计 | B41: 11086 | C41: 9069 | D41: 10865 | E41: 10307 | F41: 10367 | G41: 9628 | H41: 9211 | I41: 3086 | J41: 2270 | K41: 8190 | L41: 10484 | M41: 10403 | N41: 10840 | O41: 11449 | P41: 9395 | Q41: 10900 | R41: 10352 | S41: 10170 | T41: 6828 | BB41: =SUM(B41:BA41) -> 174900 | BC41: =BB41-(SUMIF(B41:BA41,"<>0",B106:BA106)) -> 2322
A42: 总计完成 | B42: 20047 | C42: 16564 | D42: 20018 | E42: 19403 | F42: 19359 | G42: 18426 | H42: 18477 | I42: 6811 | J42: 4314 | K42: 15456 | L42: 20707 | M42: 20498 | N42: 20432 | O42: 21478 | P42: 17627 | Q42: 20939 | R42: 20105 | S42: 19547 | T42: 13577 | BB42: =SUM(B42:BA42) -> 333785 | BC42: =BB42-(SUMIF(B42:BA42,"<>0",B107:BA107)) -> 48141 | BD42: 箱量增长
BD43: 产值增长
A44: 自营每周产值（2026年） | B44: 第1周 | C44: 第2周 | D44: 第3周 | E44: 第4周 | F44: 第5周 | G44: 第6周 | H44: 第7周 | I44: 第8周 | J44: 第9周 | K44: 第10周 | L44: 第11周 | M44: 第12周 | N44: 第13周 | O44: 第14周 | P44: 第15周 | Q44: 第16周 | R44: 第17周 | S44: 第18周 | T44: 第19周 | U44: 第20周 | V44: 第21周 | W44: 第22周 | X44: 第23周 | Y44: 第24周 | Z44: 第25周 | AA44: 第26周 | AB44: 第27周 | AC44: 第28周 | AD44: 第29周 | AE44: 第30周 | AF44: 第31周 | AG44: 第32周 | AH44: 第33周 | AI44: 第34周 | AJ44: 第35周 | AK44: 第36周 | AL44: 第37周 | AM44: 第38周 | AN44: 第39周 | AO44: 第40周 | AP44: 第41周 | AQ44: 第42周 | AR44: 第43周 | AS44: 第44周 | AT44: 第45周 | AU44: 第46周 | AV44: 第47周 | AW44: 第48周 | AX44: 第49周 | AY44: 第50周 | AZ44: 第51周 | BA44: 第52周 | BB44: 合计 | BC44: 同比2025年
A45: 深圳运营中心 | B45: 257454.83 | C45: 494272.15 | D45: 1054131.3 | E45: 1107480.2 | F45: 1327075.5 | G45: 421899.87 | H45: 331043.96 | I45: 16986.34 | J45: 131134.75 | K45: 243342.46 | L45: 242144.27 | M45: 345035.92 | N45: 323318.89 | O45: 662295.68 | P45: 751614.5 | Q45: 1142097.7 | R45: 1892854.1 | S45: 1388119.4 | T45: 216721.8 | BB45: =SUM(B45:BA45) -> 12349024 | BC45: =BB45-(SUMIF(B45:BA45,"<>0",B110:BA110)) -> 4839676
A46: 广州运营中心 | B46: 850408.98 | C46: 569018.76 | D46: 833531.29 | E46: 677114.84 | F46: 761824.89 | G46: 670480.99 | H46: 600611.47 | I46: 177803.02 | J46: 94957.43 | K46: 509760.05 | L46: 717742.63 | M46: 780496.58 | N46: 638699.17 | O46: 722678.24 | P46: 713124.51 | Q46: 687279.49 | R46: 783153.69 | S46: 677523.56 | T46: 469814.53 | BB46: =SUM(B46:BA46) -> 11936024 | BC46: =BB46-(SUMIF(B46:BA46,"<>0",B111:BA111)) -> -922861
A47: 珠三角运营中心 | B47: 802134.31 | C47: 677238.06 | D47: 708527.66 | E47: 804663.46 | F47: 838731.8 | G47: 547421.74 | H47: 379280.74 | I47: 54622.37 | J47: 54879.78 | K47: 419966.7 | L47: 781639.67 | M47: 684079.31 | N47: 855426.31 | O47: 702961.8 | P47: 644924.7 | Q47: 746902.28 | R47: 700971.64 | S47: 731190.69 | T47: 425756.65 | BB47: =SUM(B47:BA47) -> 11561320 | BC47: =BB47-(SUMIF(B47:BA47,"<>0",B112:BA112)) -> -1907796
A48: 粤西 | B48: 349155.92 | C48: 397531.64 | D48: 550886.2 | E48: 322709 | F48: 419604.51 | G48: 695747.79 | H48: 534109.08 | I48: 206126.79 | J48: 197344.78 | K48: 298983.3 | L48: 473152.42 | M48: 425558.55 | N48: 518021.47 | O48: 588060.79 | P48: 480475.85 | Q48: 615430.8 | R48: 389366.2 | S48: 499247.67 | T48: 298278.15 | BB48: =SUM(B48:BA48) -> 8259790.9 | BC48: =BB48-(SUMIF(B48:BA48,"<>0",B113:BA113)) -> 700864
A49: 北部湾 | B49: 725530.9 | C49: 648295.18 | D49: 668730.74 | E49: 795731.25 | F49: 665223.58 | G49: 656068.18 | H49: 652699.8 | I49: 411463.44 | J49: 339557.96 | K49: 754091.86 | L49: 714780.53 | M49: 731823.45 | N49: 682177.51 | O49: 803765.98 | P49: 643314.47 | Q49: 857206.35 | R49: 794830.12 | S49: 709951.61 | T49: 538522.09 | BB49: =SUM(B49:BA49) -> 12793765 | BC49: =BB49-(SUMIF(B49:BA49,"<>0",B114:BA114)) -> 1318074
A50: 南岗分公司 | B50: 375652.46 | C50: 318610.23 | D50: 290398.26 | E50: 440971.01 | F50: 508129.47 | G50: 442698.19 | H50: 315392.46 | I50: 31738.77 | J50: 97967.44 | K50: 320288.34 | L50: 290712.53 | M50: 390388.24 | N50: 279276.86 | O50: 429770.32 | P50: 384393.86 | Q50: 245028.11 | R50: 314993.94 | S50: 234846.85 | T50: 222249.69 | BB50: =SUM(B50:BA50) -> 5933507 | BC50: =BB50-(SUMIF(B50:BA50,"<>0",B115:BA115)) -> 949584
A51: 自营总计 | B51: 3360337.4 | C51: 3104966 | D51: 4106205.5 | E51: 4148669.7 | F51: 4520589.7 | G51: 3434316.8 | H51: 2813137.5 | I51: 898740.73 | J51: 915842.14 | K51: 2546432.7 | L51: 3220172 | M51: 3357382 | N51: 3296920.2 | O51: 3909532.8 | P51: 3617847.9 | Q51: 4293944.7 | R51: 4876169.7 | S51: 4240879.8 | T51: 2171342.9 | BB51: =SUM(B51:BA51) -> 62833430 | BC51: =BB51-(SUMIF(B51:BA51,"<>0",B116:BA116)) -> 4977541 | BD51: 含税 | BE51: 完成全年总额比 | BF51: 完成时间
A52: 总计完成（不含税） | B52: 5530553.3 | C52: 4852687.7 | D52: 6290487.2 | E52: 6214755.6 | F52: 6629699.8 | G52: 5427768.5 | H52: 5318554.3 | I52: 1824749.4 | J52: 1310246.2 | K52: 4157012.6 | L52: 5510974 | M52: 5632148.8 | N52: 5469073.2 | O52: 6106479.4 | P52: 5275420.7 | Q52: 6574471.8 | R52: 6968013.6 | S52: 6378639.3 | T52: 3681903.8 | BB52: =SUM(B52:BA52) -> 99153639 | BC52: =BB52-(SUMIF(B52:BA52,"<>0",B117:BA117)) -> 15061426 | BD52: 不含税 | BE52: =BB52/290000000 -> 0.3419 | BF52: ='2026年第19周'!Z2/52 -> 0.3654
A54: 自营每周箱量（2026年） | B54: 第1周 | C54: 第2周 | D54: 第3周 | E54: 第4周 | F54: 第5周 | G54: 第6周 | H54: 第7周 | I54: 第8周 | J54: 第9周 | K54: 第10周 | L54: 第11周 | M54: 第12周 | N54: 第13周 | O54: 第14周 | P54: 第15周 | Q54: 第16周 | R54: 第17周 | S54: 第18周 | T54: 第19周 | U54: 第20周 | V54: 第21周 | W54: 第22周 | X54: 第23周 | Y54: 第24周 | Z54: 第25周 | AA54: 第26周 | AB54: 第27周 | AC54: 第28周 | AD54: 第29周 | AE54: 第30周 | AF54: 第31周 | AG54: 第32周 | AH54: 第33周 | AI54: 第34周 | AJ54: 第35周 | AK54: 第36周 | AL54: 第37周 | AM54: 第38周 | AN54: 第39周 | AO54: 第40周 | AP54: 第41周 | AQ54: 第42周 | AR54: 第43周 | AS54: 第44周 | AT54: 第45周 | AU54: 第46周 | AV54: 第47周 | AW54: 第48周 | AX54: 第49周 | AY54: 第50周 | AZ54: 第51周 | BA54: 第52周 | BB54: 合计
A55: 南岗堆场 | B55: 617 | C55: 293 | D55: 437 | E55: 502 | F55: 561 | G55: 571 | H55: 611 | I55: 41 | J55: 22 | K55: 487 | L55: 288 | M55: 443 | N55: 356 | O55: 875 | P55: 126 | Q55: 134 | R55: 968 | S55: 466 | T55: 100 | BB55: =SUM(B55:BA55) -> 7898
A56: 东江仓码头 | B56: 184 | C56: 99 | D56: 170 | E56: 185 | F56: 248 | G56: 185 | H56: 258 | I56: 81 | J56: 52 | K56: 179 | L56: 223 | M56: 180 | N56: 253 | O56: 286 | P56: 147 | Q56: 219 | R56: 228 | S56: 202 | T56: 90 | BB56: =SUM(B56:BA56) -> 3469
A57: 深圳大铲湾 | B57: 187 | C57: 132 | D57: 146 | E57: 202 | F57: 159 | G57: 131 | H57: 203 | I57: 0 | J57: 10 | K57: 63 | L57: 21 | M57: 153 | N57: 175 | O57: 210 | P57: 134 | Q57: 166 | R57: 209 | S57: 175 | T57: 102 | BB57: =SUM(B57:BA57) -> 2578
A58: 深圳蛇口堆场 | B58: 242 | C58: 393 | D58: 553 | E58: 393 | F58: 579 | G58: 319 | H58: 328 | I58: 119 | J58: 83 | K58: 359 | L58: 251 | M58: 361 | N58: 419 | O58: 288 | P58: 406 | Q58: 663 | R58: 460 | S58: 496 | T58: 321 | BB58: =SUM(B58:BA58) -> 7033
A59: 汕头广澳 | B59: 0 | C59: 0 | D59: 0 | E59: 0 | F59: 0 | G59: 0 | H59: 0 | I59: 0 | J59: 0 | K59: 0 | L59: 0 | M59: 0 | N59: 0 | O59: 0 | P59: 0 | Q59: 0 | R59: 0 | S59: 0 | T59: 0 | BB59: =SUM(B59:BA59) -> 0
A60: 汕头堆场 | B60: 352 | C60: 578 | D60: 488 | E60: 484 | F60: 459 | G60: 438 | H60: 386 | I60: 50 | J60: 172 | K60: 383 | L60: 414 | M60: 423 | N60: 438 | O60: 484 | P60: 222 | Q60: 525 | R60: 350 | S60: 452 | T60: 242 | BB60: =SUM(B60:BA60) -> 7340
A61: 汕头国集 | B61: 0 | C61: 0 | D61: 0 | E61: 0 | F61: 0 | G61: 0 | H61: 0 | I61: 0 | J61: 0 | K61: 0 | L61: 0 | M61: 0 | N61: 0 | O61: 0 | P61: 0 | Q61: 0 | R61: 0 | S61: 0 | T61: 0 | BB61: =SUM(B61:BA61) -> 0
A62: 黄埔旧港 | B62: 1583 | C62: 924 | D62: 1422 | E62: 1450 | F62: 1174 | G62: 1272 | H62: 1186 | I62: 297 | J62: 133 | K62: 994 | L62: 1390 | M62: 1390 | N62: 1172 | O62: 1515 | P62: 1172 | Q62: 1289 | R62: 1334 | S62: 1258 | T62: 1128 | BB62: =SUM(B62:BA62) -> 22083
A63: 淡水河码头 | B63: 0 | C63: 0 | D63: 0 | E63: 0 | F63: 0 | G63: 0 | H63: 0 | I63: 0 | J63: 0 | K63: 0 | L63: 0 | M63: 0 | N63: 0 | O63: 0 | P63: 0 | Q63: 0 | R63: 0 | S63: 0 | T63: 0 | BB63: =SUM(B63:BA63) -> 0
A64: 新沙港 | B64: 21 | C64: 11 | D64: 22 | E64: 12 | F64: 67 | G64: 20 | H64: 20 | I64: 10 | J64: 42 | K64: 33 | L64: 22 | M64: 24 | N64: 16 | O64: 30 | P64: 36 | Q64: 9 | R64: 58 | S64: 12 | T64: 9 | BB64: =SUM(B64:BA64) -> 474
A65: 南沙三期自营 | B65: 0 | C65: 0 | D65: 0 | E65: 0 | F65: 0 | G65: 0 | H65: 0 | I65: 0 | J65: 0 | K65: 0 | L65: 0 | M65: 0 | N65: 0 | O65: 0 | P65: 0 | Q65: 0 | R65: 0 | S65: 0 | T65: 0 | BB65: =SUM(B65:BA65) -> 0
A66: 南沙一期码头 | B66: 554 | C66: 272 | D66: 296 | E66: 316 | F66: 348 | G66: 230 | H66: 284 | I66: 74 | J66: 66 | K66: 284 | L66: 397 | M66: 213 | N66: 124 | O66: 186 | P66: 282 | Q66: 353 | R66: 303 | S66: 294 | T66: 135 | BB66: =SUM(B66:BA66) -> 5011
... A92: 广西钦州外堆场自营 | B92: 994 | C92: 753 | D92: 820 | E92: 870 | F92: 805 | G92: 964 | H92: 924 | I92: 675 | J92: 224 | K92: 913 | L92: 828 | M92: 906 | N92: 693 | O92: 918 | P92: 843 | Q92: 1031 | R92: 969 | S92: 1009 | T92: 896 | BB92: =SUM(B92:BA92) -> 16035
A93: 广西钦州港自营 | B93: 112 | C93: 47 | D93: 108 | E93: 108 | F93: 133 | G93: 71 | H93: 116 | I93: 105 | J93: 19 | K93: 72 | L93: 88 | M93: 117 | N93: 71 | O93: 85 | P93: 70 | Q93: 146 | R93: 49 | S93: 9 | T93: 37
A99: 自营每周箱量（2025年） | B99: 第1周 | C99: 第2周 | D99: 第3周 | E99: 第4周 | F99: 第5周 | G99: 第6周 | H99: 第7周 | I99: 第8周 | J99: 第9周 | K99: 第10周 | L99: 第11周 | M99: 第12周 | N99: 第13周 | O99: 第14周 | P99: 第15周 | Q99: 第16周 | R99: 第17周 | S99: 第18周 | T99: 第19周 | U99: 第20周 | V99: 第21周 | W99: 第22周 | X99: 第23周 | Y99: 第24周 | Z99: 第25周 | AA99: 第26周 | AB99: 第27周 | AC99: 第28周 | AD99: 第29周 | AE99: 第30周 | AF99: 第31周 | AG99: 第32周 | AH99: 第33周 | AI99: 第34周 | AJ99: 第35周 | AK99: 第36周 | AL99: 第37周 | AM99: 第38周 | AN99: 第39周 | AO99: 第40周 | AP99: 第41周 | AQ99: 第42周 | AR99: 第43周 | AS99: 第44周 | AT99: 第45周 | AU99: 第46周 | AV99: 第47周 | AW99: 第48周 | AX99: 第49周 | AY99: 第50周 | AZ99: 第51周 | BA99: 第52周 | BB99: 合计
A100: 深圳运营中心 | B100: 753 | C100: 1038 | D100: 980 | E100: 980 | F100: 356 | G100: 175 | H100: 548 | I100: 878 | J100: 888 | K100: 985 | L100: 955 | M100: 1018 | N100: 999 | O100: 1228 | P100: 895 | Q100: 1186 | R100: 817 | S100: 1246 | T100: 740 | BB100: =SUM(B100:BA100) -> 16665
A101: 广州运营中心 | B101: 2744 | C101: 3284 | D101: 3308 | E101: 3117 | F101: 689 | G101: 50 | H101: 2542 | I101: 3287 | J101: 3031 | K101: 2715 | L101: 3256 | M101: 3070 | N101: 3475 | O101: 3452 | P101: 2396 | Q101: 2966 | R101: 2931 | S101: 3454 | T101: 1854 | BB101: =SUM(B101:BA101) -> 51621
A102: 珠三角运营中心 | B102: 2789 | C102: 2835 | D102: 2734 | E102: 1950 | F102: 552 | G102: 357 | H102: 2138 | I102: 3146 | J102: 3031 | K102: 3087 | L102: 2892 | M102: 2641 | N102: 2572 | O102: 2965 | P102: 2508 | Q102: 2568 | R102: 3022 | S102: 2976 | T102: 2159 | BB102: =SUM(B102:BA102) -> 46922
A103: 粤西 | B103: 922 | C103: 1012 | D103: 897 | E103: 1319 | F103: 534 | G103: 153 | H103: 653 | I103: 906 | J103: 733 | K103: 1259 | L103: 1393 | M103: 1396 | N103: 1679 | O103: 1426 | P103: 1138 | Q103: 1897 | R103: 1485 | S103: 1319 | T103: 1205 | BB103: =SUM(B103:BA103) -> 21326
A104: 北部湾 | B104: 1371 | C104: 1894 | D104: 1785 | E104: 1465 | F104: 942 | G104: 368 | H104: 858 | I104: 1186 | J104: 1527 | K104: 1889 | L104: 1608 | M104: 1509 | N104: 1527 | O104: 1779 | P104: 1656 | Q104: 2247 | R104: 1638 | S104: 1812 | T104: 1923 | BB104: =SUM(B104:BA104) -> 28984
A105: 南岗分公司 | B105: 347 | C105: 396 | D105: 442 | E105: 365 | F105: 80 | G105: 80 | H105: 295 | I105: 386 | J105: 421 | K105: 420 | L105: 506 | M105: 340 | N105: 549 | O105: 464 | P105: 386 | Q105: 345 | R105: 469 | S105: 544 | T105: 225 | BB105: =SUM(B105:BA105) -> 7060
A106: 自营总计 | B106: 8926 | C106: 10459 | D106: 10146 | E106: 9196 | F106: 3153 | G106: 1183 | H106: 7034 | I106: 9789 | J106: 9631 | K106: 10355 | L106: 10610 | M106: 9974 | N106: 10801 | O106: 11314 | P106: 8979 | Q106: 11209 | R106: 10362 | S106: 11351 | T106: 8106 | BB106: =SUM(B106:BA106) -> 172578
A107: 总计完成 | B107: 14499 | C107: 18379 | D107: 17006 | E107: 15323 | F107: 5766 | G107: 2111 | H107: 12096 | I107: 16034 | J107: 16294 | K107: 15962 | L107: 17310 | M107: 18023 | N107: 17387 | O107: 17438 | P107: 15147 | Q107: 18408 | R107: 17759 | S107: 18153 | T107: 12549 | BB107: =SUM(B107:BA107) -> 285644
A109: 自营每周产值（2025年） | B109: 第1周 | C109: 第2周 | D109: 第3周 | E109: 第4周 | F109: 第5周 | G109: 第6周 | H109: 第7周 | I109: 第8周 | J109: 第9周 | K109: 第10周 | L109: 第11周 | M109: 第12周 | N109: 第13周 | O109: 第14周 | P109: 第15周 | Q109: 第16周 | R109: 第17周 | S109: 第18周 | T109: 第19周 | U109: 第20周 | V109: 第21周 | W109: 第22周 | X109: 第23周 | Y109: 第24周 | Z109: 第25周 | AA109: 第26周 | AB109: 第27周 | AC109: 第28周 | AD109: 第29周 | AE109: 第30周 | AF109: 第31周 | AG109: 第32周 | AH109: 第33周 | AI109: 第34周 | AJ109: 第35周 | AK109: 第36周 | AL109: 第37周 | AM109: 第38周 | AN109: 第39周 | AO109: 第40周 | AP109: 第41周 | AQ109: 第42周 | AR109: 第43周 | AS109: 第44周 | AT109: 第45周 | AU109: 第46周 | AV109: 第47周 | AW109: 第48周 | AX109: 第49周 | AY109: 第50周 | AZ109: 第51周 | BA109: 第52周 | BB109: 合计
A110: 深圳运营中心 | B110: 340709.9 | C110: 481723.07 | D110: 483504.59 | E110: 401035.25 | F110: 134349.35 | G110: 70140.25 | H110: 265862.43 | I110: 426240.77 | J110: 393049.37 | K110: 426669.99 | L110: 431979.51 | M110: 452885.36 | N110: 456493.04 | O110: 547763.95 | P110: 413556.06 | Q110: 503517.44 | R110: 369791.2 | S110: 581346.53 | T110: 328729.75 | BB110: =SUM(B110:BA110) -> 7509347.8
A111: 广州运营中心 | B111: 694973.19 | C111: 784258.41 | D111: 890215.45 | E111: 773069.56 | F111: 208981.88 | G111: 54032.88 | H111: 637571.57 | I111: 834191.43 | J111: 755669.44 | K111: 686129.96 | L111: 844746.44 | M111: 724880.82 | N111: 855447.93 | O111: 820613.56 | P111: 577546.21 | Q111: 743867.28 | R111: 713948.69 | S111: 861809.26 | T111: 396931.06 | BB111: =SUM(B111:BA111) -> 12858885
A112: 珠三角运营中心 | B112: 884795.68 | C112: 831520.29 | D112: 845352.38 | E112: 546465.09 | F112: 150020.3 | G112: 134361.81 | H112: 619001.48 | I112: 807358.44 | J112: 824783.57 | K112: 942955.78 | L112: 866187.12 | M112: 740795.99 | N112: 734880.52 | O112: 906898.23 | P112: 678226.65 | Q112: 710083.02 | R112: 781007.18 | S112: 898458.44 | T112: 565963.47 | BB112: =SUM(B112:BA112) -> 13469115
A113: 粤西 | B113: 286447.52 | C113: 384217.53 | D113: 328679.58 | E113: 455393.76 | F113: 227545.4 | G113: 66384.92 | H113: 220069.94 | I113: 334566.4 | J113: 308048.19 | K113: 422208.58 | L113: 545621.64 | M113: 504958.76 | N113: 584452.93 | O113: 547365.2 | P113: 341197.38 | Q113: 699916.44 | R113: 498948.75 | S113: 454935.61 | T113: 347968.51 | BB113: =SUM(B113:BA113) -> 7558927
A114: 北部湾 | B114: 608961.87 | C114: 745723.46 | D114: 736237.22 | E114: 583930.06 | F114: 345895.49 | G114: 158808.32 | H114: 404128.77 | I114: 543089.22 | J114: 599498.78 | K114: 734124.84 | L114: 675821.68 | M114: 641728.73 | N114: 641849.11 | O114: 695112.41 | P114: 617557.32 | Q114: 733865.1 | R114: 637108.74 | S114: 695837.73 | T114: 676411.95 | BB114: =SUM(B114:BA114) -> 11475691
A115: 南岗分公司 | B115: 255223.54 | C115: 234750.62 | D115: 302763.62 | E115: 393227.58 | F115: 37585.71 | G115: 32910.14 | H115: 369641.55 | I115: 261815.89 | J115: 252634.66 | K115: 265985.6 | L115: 284579.83 | M115: 223525.93 | N115: 424697.14 | O115: 289016.01 | P115: 330575.79 | Q115: 282212.73 | R115: 256963.72 | S115: 272298.35 | T115: 213514.45 | BB115: =SUM(B115:BA115) -> 4983922.9
A116: 自营总计 | B116: 3071111.7 | C116: 3462193.4 | D116: 3586752.8 | E116: 3153121.3 | F116: 1104378.1 | G116: 516638.32 | H116: 2516275.7 | I116: 3207262.1 | J116: 3133684 | K116: 3478074.8 | L116: 3648936.2 | M116: 3288775.6 | N116: 3697820.7 | O116: 3806769.4 | P116: 2958659.4 | Q116: 3673462 | R116: 3257768.3 | S116: 3764685.9 | T116: 2529519.2 | BB116: =SUM(B116:BA116) -> 57855889
A117: 总计完成（不含税） | B117: 4359686 | C117: 5258380 | D117: 5188532.2 | E117: 4561611.1 | F117: 1576205.1 | G117: 712740.6 | H117: 3596237.2 | I117: 4503300.9 | J117: 4658310.2 | K117: 4711383.9 | L117: 5215736.1 | M117: 5165058.9 | N117: 5304339.5 | O117: 5211016.7 | P117: 4587786.5 | Q117: 5451546.7 | R117: 5097353 | S117: 5355688.5 | T117: 3577299.5 | BB117: =SUM(B117:BA117) -> 84092213
A121: 自营每周箱量（2025年） | B121: 第1周 | C121: 第2周 | D121: 第3周 | E121: 第4周 | F121: 第5周 | G121: 第6周 | H121: 第7周 | I121: 第8周 | J121: 第9周 | K121: 第10周 | L121: 第11周 | M121: 第12周 | N121: 第13周 | O121: 第14周 | P121: 第15周 | Q121: 第16周 | R121: 第17周 | S121: 第18周 | T121: 第19周 | U121: 第20周 | V121: 第21周 | W121: 第22周 | X121: 第23周 | Y121: 第24周 | Z121: 第25周 | AA121: 第26周 | AB121: 第27周 | AC121: 第28周 | AD121: 第29周 | AE121: 第30周 | AF121: 第31周 | AG121: 第32周 | AH121: 第33周 | AI121: 第34周 | AJ121: 第35周 | AK121: 第36周 | AL121: 第37周 | AM121: 第38周 | AN121: 第39周 | AO121: 第40周 | AP121: 第41周 | AQ121: 第42周 | AR121: 第43周 | AS121: 第44周 | AT121: 第45周 | AU121: 第46周 | AV121: 第47周 | AW121: 第48周 | AX121: 第49周 | AY121: 第50周 | AZ121: 第51周 | BA121: 第52周 | BB121: 合计
A122: 深圳运营中心 | B122: 753 | C122: 1038 | D122: 980 | E122: 980 | F122: 356 | G122: 175 | H122: 548 | I122: 878 | J122: 888 | K122: 985 | L122: 955 | M122: 1018 | N122: 999 | O122: 1228 | P122: 895 | Q122: 1186 | R122: 817 | S122: 1246 | T122: 740 | U122: 1202 | V122: 1156 | W122: 1141 | X122: 803 | Y122: 1078 | Z122: 780 | AA122: 1062 | AB122: 943 | AC122: 1094 | AD122: 901 | AE122: 910 | AF122: 956 | AG122: 752 | AH122: 933 | AI122: 848 | AJ122: 1283 | AK122: 895 | AL122: 660 | AM122: 944 | AN122: 513 | AO122: 732 | AP122: 732 | AQ122: 1043 | AR122: 1096 | AS122: 1077 | AT122: 1028 | AU122: 1119 | AV122: 791 | AW122: 1151 | AX122: 1109 | AY122: 912 | AZ122: 875 | BA122: 873 | BB122: 48057
A123: 广州运营中心 | B123: 2744 | C123: 3284 | D123: 3308 | E123: 3117 | F123: 689 | G123: 50 | H123: 2542 | I123: 3287 | J123: 3031 | K123: 2715 | L123: 3256 | M123: 3070 | N123: 3475 | O123: 3452 | P123: 2396 | Q123: 2966 | R123: 2931 | S123: 3454 | T123: 1854 | U123: 3270 | V123: 2838 | W123: 2799 | X123: 2661 | Y123: 2874 | Z123: 2693 | AA123: 2853 | AB123: 3141 | AC123: 2777 | AD123: 2820 | AE123: 2718 | AF123: 2590 | AG123: 2092 | AH123: 3084 | AI123: 2448 | AJ123: 2670 | AK123: 2648 | AL123: 2547 | AM123: 2879 | AN123: 1767 | AO123: 1886 | AP123: 1886 | AQ123: 3656 | AR123: 3036 | AS123: 3349 | AT123: 3167 | AU123: 3075 | AV123: 2711 | AW123: 2916 | AX123: 3272 | AY123: 3069 | AZ123: 3024 | BA123: 2223 | BB123: 143060
A124: 珠三角运营中心 | B124: 2789 | C124: 2835 | D124: 2734 | E124: 1950 | F124: 552 | G124: 357 | H124: 2138 | I124: 3146 | J124: 3031 | K124: 3087 | L124: 2892 | M124: 2641 | N124: 2572 | O124: 2965 | P124: 2508 | Q124: 2568 | R124: 3022 | S124: 2976 | T124: 2159 | U124: 2831 | V124: 3337 | W124: 3034 | X124: 3055 | Y124: 2968 | Z124: 2795 | AA124: 2987 | AB124: 3778 | AC124: 2791 | AD124: 2728 | AE124: 2379 | AF124: 2471 | AG124: 2859 | AH124: 3130 | AI124: 2638 | AJ124: 3203 | AK124: 3031 | AL124: 2535 | AM124: 2498 | AN124: 2411 | AO124: 1921 | AP124: 1921 | AQ124: 3778 | AR124: 2713 | AS124: 4277 | AT124: 2582 | AU124: 2573 | AV124: 3093 | AW124: 2824 | AX124: 3488 | AY124: 2778 | AZ124: 2394 | BA124: 2691 | BB124: 141414
A125: 粤西 | B125: 922 | C125: 1012 | D125: 897 | E125: 1319 | F125: 534 | G125: 153 | H125: 653 | I125: 906 | J125: 733 | K125: 1259 | L125: 1393 | M125: 1396 | N125: 1679 | O125: 1426 | P125: 1138 | Q125: 1897 | R125: 1485 | S125: 1319 | T125: 1205 | U125: 1235 | V125: 1263 | W125: 1247 | X125: 1198 | Y125: 1529 | Z125: 841 | AA125: 1475 | AB125: 1394 | AC125: 1461 | AD125: 1653 | AE125: 1363 | AF125: 1368 | AG125: 1180 | AH125: 1750 | AI125: 1522 | AJ125: 2036 | AK125: 2067 | AL125: 1996 | AM125: 1389 | AN125: 1644 | AO125: 1112 | AP125: 1112 | AQ125: 1998 | AR125: 1652 | AS125: 1682 | AT125: 1394 | AU125: 1808 | AV125: 1835 | AW125: 1570 | AX125: 1195 | AY125: 1629 | AZ125: 1894 | BA125: 1582 | BB125: 71400
A126: 北部湾 | B126: 1371 | C126: 1894 | D126: 1785 | E126: 1465 | F126: 942 | G126: 368 | H126: 858 | I126: 1186 | J126: 1527 | K126: 1889 | L126: 1608 | M126: 1509 | N126: 1527 | O126: 1779 | P126: 1656 | Q126: 2247 | R126: 1638 | S126: 1812 | T126: 1923 | U126: 1896 | V126: 1795 | W126: 1922 | X126: 1412 | Y126: 2150 | Z126: 1940 | AA126: 2057 | AB126: 2068 | AC126: 2055 | AD126: 2043 | AE126: 1765 | AF126: 1750 | AG126: 1642 | AH126: 2051 | AI126: 2066 | AJ126: 2044 | AK126: 1596 | AL126: 1970 | AM126: 1946 | AN126: 1628 | AO126: 1843 | AP126: 1843 | AQ126: 2107 | AR126: 1917 | AS126: 1874 | AT126: 2054 | AU126: 1968 | AV126: 1991 | AW126: 1435 | AX126: 2026 | AY126: 1911 | AZ126: 2081 | BA126: 2381 | BB126: 92211
A127: 南岗分公司 | B127: 347 | C127: 396 | D127: 442 | E127: 365 | F127: 80 | G127: 80 | H127: 295 | I127: 386 | J127: 421 | K127: 420 | L127: 506 | M127: 340 | N127: 549 | O127: 464 | P127: 386 | Q127: 345 | R127: 469 | S127: 544 | T127: 225 | U127: 387 | V127: 901 | W127: 244 | X127: 546 | Y127: 459 | Z127: 659 | AA127: 931 | AB127: 567 | AC127: 783 | AD127: 590 | AE127: 705 | AF127: 526 | AG127: 443 | AH127: 412 | AI127: 429 | AJ127: 722 | AK127: 793 | AL127: 347 | AM127: 513 | AN127: 360 | AO127: 377 | AP127: 377 | AQ127: 394 | AR127: 820 | AS127: 507 | AT127: 775 | AU127: 416 | AV127: 657 | AW127: 671 | AX127: 660 | AY127: 669 | AZ127: 585 | BA127: 569 | BB127: 25854
A128: 自营总计 | B128: 8926 | C128: 10459 | D128: 10146 | E128: 9196 | F128: 3153 | G128: 1183 | H128: 7034 | I128: 9789 | J128: 9631 | K128: 10355 | L128: 10610 | M128: 9974 | N128: 10801 | O128: 11314 | P128: 8979 | Q128: 11209 | R128: 10362 | S128: 11351 | T128: 8106 | U128: 10821 | V128: 11290 | W128: 10387 | X128: 9675 | Y128: 11058 | Z128: 9708 | AA128: 11365 | AB128: 11891 | AC128: 10961 | AD128: 10735 | AE128: 9840 | AF128: 9661 | AG128: 8968 | AH128: 11360 | AI128: 9951 | AJ128: 11958 | AK128: 11030 | AL128: 10055 | AM128: 10169 | AN128: 8323 | AO128: 7871 | AP128: 7871 | AQ128: 12976 | AR128: 11234 | AS128: 12766 | AT128: 11000 | AU128: 10959 | AV128: 11078 | AW128: 10567 | AX128: 11750 | AY128: 10968 | AZ128: 10853 | BA128: 10319 | BB128: 521996
A129: 总计完成 | B129: 14499 | C129: 18379 | D129: 17006 | E129: 15323 | F129: 5766 | G129: 2111 | H129: 12096 | I129: 16034 | J129: 16294 | K129: 15962 | L129: 17310 | M129: 18023 | N129: 17387 | O129: 17438 | P129: 15147 | Q129: 18408 | R129: 17759 | S129: 18153 | T129: 12549 | U129: 17665 | V129: 17522 | W129: 17225 | X129: 15285 | Y129: 18292 | Z129: 16050 | AA129: 18658 | AB129: 20333 | AC129: 18487 | AD129: 18564 | AE129: 17392 | AF129: 17253 | AG129: 15421 | AH129: 19324 | AI129: 19075 | AJ129: 20284 | AK129: 19209 | AL129: 18044 | AM129: 18071 | AN129: 15266 | AO129: 16599 | AP129: 5997 | AQ129: 24165 | AR129: 18685 | AS129: 23246 | AT129: 20080 | AU129: 20650 | AV129: 20803 | AW129: 20261 | AX129: 21291 | AY129: 20817 | AZ129: 19312 | BA129: 18102 | BB129: 893072
A131: 自营每周产值（2025年） | B131: 第1周 | C131: 第2周 | D131: 第3周 | E131: 第4周 | F131: 第5周 | G131: 第6周 | H131: 第7周 | I131: 第8周 | J131: 第9周 | K131: 第10周 | L131: 第11周 | M131: 第12周 | N131: 第13周 | O131: 第14周 | P131: 第15周 | Q131: 第16周 | R131: 第17周 | S131: 第18周 | T131: 第19周 | U131: 第20周 | V131: 第21周 | W131: 第22周 | X131: 第23周 | Y131: 第24周 | Z131: 第25周 | AA131: 第26周 | AB131: 第27周 | AC131: 第28周 | AD131: 第29周 | AE131: 第30周 | AF131: 第31周 | AG131: 第32周 | AH131: 第33周 | AI131: 第34周 | AJ131: 第35周 | AK131: 第36周 | AL131: 第37周 | AM131: 第38周 | AN131: 第39周 | AO131: 第40周 | AP131: 第41周 | AQ131: 第42周 | AR131: 第43周 | AS131: 第44周 | AT131: 第45周 | AU131: 第46周 | AV131: 第47周 | AW131: 第48周 | AX131: 第49周 | AY131: 第50周 | AZ131: 第51周 | BA131: 第52周 | BB131: 合计
A132: 深圳运营中心 | B132: 340709.9 | C132: 481723.07 | D132: 483504.59 | E132: 401035.25 | F132: 134349.35 | G132: 70140.25 | H132: 265862.43 | I132: 426240.77 | J132: 393049.37 | K132: 426669.99 | L132: 431979.51 | M132: 452885.36 | N132: 456493.04 | O132: 547763.95 | P132: 413556.06 | Q132: 503517.44 | R132: 369791.2 | S132: 581346.53 | T132: 328729.75 | U132: 552310.29 | V132: 565277.14 | W132: 564276.23 | X132: 378417.37 | Y132: 519844.76 | Z132: 434563.04 | AA132: 522672 | AB132: 437331.9 | AC132: 477794.86 | AD132: 435944.1 | AE132: 419129.32 | AF132: 488603.58 | AG132: 384651.04 | AH132: 424505.2 | AI132: 426326.29 | AJ132: 576395.53 | AK132: 955025.76 | AL132: 486198.88 | AM132: 491580.5 | AN132: 479421.25 | AO132: 418371.72 | AP132: 144047.83 | AQ132: 579198.86 | AR132: 768392.53 | AS132: 1079046.2 | AT132: 1383786.1 | AU132: 662646.49 | AV132: 458841.89 | AW132: 1072840.5 | AX132: 1003591.3 | AY132: 807662.86 | AZ132: 677587.43 | BA132: 1085379.6 | BB132: 27671010
A133: 广州运营中心 | B133: 694973.19 | C133: 784258.41 | D133: 890215.45 | E133: 773069.56 | F133: 208981.88 | G133: 54032.88 | H133: 637571.57 | I133: 834191.43 | J133: 755669.44 | K133: 686129.96 | L133: 844746.44 | M133: 724880.82 | N133: 855447.93 | O133: 820613.56 | P133: 577546.21 | Q133: 743867.28 | R133: 713948.69 | S133: 861809.26 | T133: 396931.06 | U133: 759786.61 | V133: 678313.09 | W133: 682911.51 | X133: 641515.13 | Y133: 629314.31 | Z133: 619124.7 | AA133: 687743 | AB133: 763859.19 | AC133: 692995.49 | AD133: 667316.64 | AE133: 663642.76 | AF133: 597784.46 | AG133: 450663.31 | AH133: 703762.25 | AI133: 578889.21 | AJ133: 611631.85 | AK133: 660812.08 | AL133: 599134.09 | AM133: 691016.25 | AN133: 392359.08 | AO133: 496195.97 | AP133: 159265.5 | AQ133: 822000.16 | AR133: 748332.48 | AS133: 793193.03 | AT133: 814081.16 | AU133: 746457.4 | AV133: 674899.67 | AW133: 690864.95 | AX133: 735538.15 | AY133: 724254.41 | AZ133: 739919.27 | BA133: 584582.48 | BB133: 34361045
A134: 珠三角运营中心 | B134: 884795.68 | C134: 831520.29 | D134: 845352.38 | E134: 546465.09 | F134: 150020.3 | G134: 134361.81 | H134: 619001.48 | I134: 807358.44 | J134: 824783.57 | K134: 942955.78 | L134: 866187.12 | M134: 740795.99 | N134: 734880.52 | O134: 906898.23 | P134: 678226.65 | Q134: 710083.02 | R134: 781007.18 | S134: 898458.44 | T134: 565963.47 | U134: 789043.01 | V134: 872582.58 | W134: 831370.81 | X134: 853081.46 | Y134: 859817.82 | Z134: 756314.63 | AA134: 821467 | AB134: 1023217.1 | AC134: 738350.86 | AD134: 774133.45 | AE134: 634019.2 | AF134: 673128.02 | AG134: 757809.41 | AH134: 816958.95 | AI134: 728658.65 | AJ134: 853782.13 | AK134: 894588.41 | AL134: 751049.07 | AM134: 733574.03 | AN134: 712572.78 | AO134: 581905.82 | AP134: 420684.37 | AQ134: 1168629.4 | AR134: 791068.02 | AS134: 1285981.4 | AT134: 845554.36 | AU134: 819021.03 | AV134: 1016913.4 | AW134: 869964.2 | AX134: 1041593.1 | AY134: 882378.84 | AZ134: 753913.85 | BA134: 846691.05 | BB134: 40668934
A135: 粤西 | B135: 286447.52 | C135: 384217.53 | D135: 328679.58 | E135: 455393.76 | F135: 227545.4 | G135: 66384.92 | H135: 220069.94 | I135: 334566.4 | J135: 308048.19 | K135: 422208.58 | L135: 545621.64 | M135: 504958.76 | N135: 584452.93 | O135: 547365.2 | P135: 341197.38 | Q135: 699916.44 | R135: 498948.75 | S135: 454935.61 | T135: 347968.51 | U135: 476925.34 | V135: 426114.14 | W135: 432207.93 | X135: 393455.88 | Y135: 505777.25 | Z135: 312159 | AA135: 510837 | AB135: 503946.94 | AC135: 476626.66 | AD135: 536283.83 | AE135: 403195.38 | AF135: 442184.28 | AG135: 365166.2 | AH135: 536138.14 | AI135: 548490.81 | AJ135: 721934.93 | AK135: 645624.18 | AL135: 630862.47 | AM135: 445891 | AN135: 470812.7 | AO135: 348541.23 | AP135: 124124.09 | AQ135: 669213.4 | AR135: 468744.09 | AS135: 562393.28 | AT135: 426572.15 | AU135: 468759.13 | AV135: 583821.19 | AW135: 575263.17 | AX135: 393337.93 | AY135: 390039.8 | AZ135: 509433.55 | BA135: 517865.93 | BB135: 23381670
A136: 北部湾 | B136: 608961.87 | C136: 745723.46 | D136: 736237.22 | E136: 583930.06 | F136: 345895.49 | G136: 158808.32 | H136: 404128.77 | I136: 543089.22 | J136: 599498.78 | K136: 734124.84 | L136: 675821.68 | M136: 641728.73 | N136: 641849.11 | O136: 695112.41 | P136: 617557.32 | Q136: 733865.1 | R136: 637108.74 | S136: 695837.73 | T136: 676411.95 | U136: 663382.5 | V136: 670321.32 | W136: 676438.84 | X136: 562857.55 | Y136: 766676.83 | Z136: 645787.21 | AA136: 708672 | AB136: 704439.78 | AC136: 731183.57 | AD136: 726737.75 | AE136: 658518.3 | AF136: 658267.37 | AG136: 573151.11 | AH136: 740045.83 | AI136: 743447.42 | AJ136: 832236.04 | AK136: 605947.63 | AL136: 681666.47 | AM136: 694059.97 | AN136: 610860.36 | AO136: 653240.97 | AP136: 240990.34 | AQ136: 775998.8 | AR136: 742312.8 | AS136: 686227.44 | AT136: 763835.96 | AU136: 668556.66 | AV136: 645911.99 | AW136: 559404.2 | AX136: 707826.51 | AY136: 682398.05 | AZ136: 752852.26 | BA136: 844409.23 | BB136: 33854354
A137: 南岗分公司 | B137: 255223.54 | C137: 234750.62 | D137: 302763.62 | E137: 393227.58 | F137: 37585.71 | G137: 32910.14 | H137: 369641.55 | I137: 261815.89 | J137: 252634.66 | K137: 265985.6 | L137: 284579.83 | M137: 223525.93 | N137: 424697.14 | O137: 289016.01 | P137: 330575.79 | Q137: 282212.73 | R137: 256963.72 | S137: 272298.35 | T137: 213514.45 | U137: 307113.62 | V137: 363263.48 | W137: 301863.84 | X137: 263718.07 | Y137: 410597.81 | Z137: 398483.28 | AA137: 458839 | AB137: 342464.78 | AC137: 419414.07 | AD137: 261302.64 | AE137: 278938.21 | AF137: 289591.78 | AG137: 304461.15 | AH137: 440032.65 | AI137: 539254.93 | AJ137: 657870.21 | AK137: 361180.03 | AL137: 227013.59 | AM137: 279240.4 | AN137: 360905.66 | AO137: 437324.31 | AP137: 71807.95 | AQ137: 329500.67 | AR137: 624828.33 | AS137: 630592 | AT137: 350729.96 | AU137: 305693.29 | AV137: 538410.56 | AW137: 555524.4 | AX137: 405341.07 | AY137: 360547.27 | AZ137: 500912.46 | BA137: 500628.99 | BB137: 17861313
A138: 自营总计 | B138: 3071111.7 | C138: 3462193.4 | D138: 3586752.8 | E138: 3153121.3 | F138: 1104378.1 | G138: 516638.32 | H138: 2516275.7 | I138: 3207262.1 | J138: 3133684 | K138: 3478074.8 | L138: 3648936.2 | M138: 3288775.6 | N138: 3697820.7 | O138: 3806769.4 | P138: 2958659.4 | Q138: 3673462 | R138: 3257768.3 | S138: 3764685.9 | T138: 2529519.2 | U138: 3548561.4 | V138: 3575871.8 | W138: 3489069.2 | X138: 3093045.5 | Y138: 3692028.8 | Z138: 3166431.9 | AA138: 3710230 | AB138: 3775259.7 | AC138: 3536365.5 | AD138: 3401718.4 | AE138: 3057443.2 | AF138: 3149559.5 | AG138: 2835902.2 | AH138: 3661443 | AI138: 3565067.3 | AJ138: 4253850.7 | AK138: 4123178.1 | AL138: 3375924.6 | AM138: 3335362.1 | AN138: 3026931.8 | AO138: 2935580 | AP138: 1160920.1 | AQ138: 4344541.3 | AR138: 4143678.2 | AS138: 5037433.4 | AT138: 4584559.7 | AU138: 3671134 | AV138: 3918798.7 | AW138: 4323861.5 | AX138: 4287228 | AY138: 3847281.2 | AZ138: 3934618.8 | BA138: 4379557.2 | BB138: 1.7779833e+08
